Workbook
Name ComisiónV: Comisiones!$A$34:$A$38
Name ComisiónAs: AsigTotalPTC!$A$14:$A$31
Name ComisiónAs: Comisiones!$A$14:$A$31
Name ComisiónV: Comisiones!$A$34:$A$38
Name ComisiónUNSIS: Comisiones!$A$4:$A$11
Name ComisiónV: Comisiones!$A$34:$A$38
Name ComisiónViceRectoríaAcadémica: Comisiones!$A$36:$A$38
Name ComisiónAsignaciónConsejoAcadémico: Comisiones!$A$16:$A$29
Name ComisiónAc: Comisiones!$A$62:$A$68
Name Coordinación_del_Curso_de_Computación_para_Niños_de_Educación_Básica: Comisiones!$A$59
Name ComisiónACA: Comisiones!$A$16:$A$29
Name ComisiónAs: Comisiones!$A$14:$A$31
Name ComisiónU: Comisiones!$A$2:$A$11
Name ApoyoActividades: Comisiones!$A$64:$A$67
Name ComisiónVRA: Comisiones!$A$36:$A$38
Name ComisiónD: Comisiones!$A$51:$A$54
Name ComisiónU: Comisiones!$A$2:$A$11
Name ComisiónAc: Comisiones!$A$62:$A$68
Name ComisiónJefaturaCarreraDEP: Comisiones!$A$43:$A$45
Name ComisiónD: AsigTotalPTC!$A$51:$A$54
Name ComisiónP: Comisiones!$A$57:$A$59
Name ComisióndeViceRectoríaAcadémica: Comisiones!$A$36:$A$38
Name Comisión_de_Personal_Académico: Comisiones!$A$16:$A$29
Name ComisiónJ: AsigTotalPTC!$A$41:$A$48
Name ComisiónU: Comisiones!$A$2:$A$11
Name ComisiónP: AsigTotalPTC!$A$57:$A$59
Name ComisiónJ: Comisiones!$A$41:$A$48
Name ComisiónAc: AsigTotalPTC!$A$62:$A$68
Name ComisiónAc: Comisiones!$A$62:$A$68
Name ComisiónP: Comisiones!$A$57:$A$59
Name ComisiónDirecciónInstituto: Comisiones!$A$53:$A$54
Name ComisiónD: Comisiones!$A$51:$A$54
Name ComisiónD: Comisiones!$A$51:$A$54
Name ComisiónU: AsigTotalPTC!$A$2:$A$11
Name ComisiónAs: Comisiones!$A$14:$A$31
Name ComisiónJ: Comisiones!$A$41:$A$48
Name ComisiónoAsignacióndelConsejoAcadémico: Comisiones!$A$16:$A$29
Name ComisiónV: AsigTotalPTC!$A$34:$A$38
Name ComisiónP: Comisiones!$A$57:$A$59
Name ComisiónJ: Comisiones!$A$41:$A$48

Sheet LCB
A1: ASIGNACIÓN DE MATERIAS PARA EL SEMESTRE 26-27A
B2: Materia | C2: Profesor asignado | D2: PE-Adscripción | E2: Horas por semana | F2: Número de alumnos
B3: 116-A
B4: Química General | C4: M.B.E. Raúl Misael Cortés Olivera | D4: LCB | E4: 6
B5: Biología Celular | C5: M.B.E. Ruth Monserrat Rodríguez Hernández | D5: LCB | E5: 6
B6: Matemáticas | C6: M.C. Mónica Pérez Meza | D6: LI | E6: 5
B7: Introducción a la Metodología de la Investigación | C7: Dra. Karla Esmeralda Tello Ortega | D7: LCB | E7: 4
B8: Historia del Pensamiento Filosófico | C8: Mtro. Diego Toto Jiménez | D8: LAP | E8: 4
B10: 116-B
B11: Química General | C11: Dr. Edgar Rodrigo Guzmán Bautista | D11: LCB | E11: 6
B12: Biología Celular | C12: M.B.E. Ruth Monserrat Rodríguez Hernández | D12: LCB | E12: 6
B13: Matemáticas | C13: Dr. Amando Alejandro Ruiz Figueroa | D13: LI | E13: 5
B14: Introducción a la Metodología de la Investigación | C14: Dra. Victoria Vera Pineda | D14: LCB | E14: 4
B15: Historia del Pensamiento Filosófico | C15: M.F. Araceli Luz Alva Rodríguez Martínez | D15: LAP | E15: 4
B17: 316-A
B18: Bioquímica Metabólica | C18: Dra. Claudia Chávez López | D18: LCB | E18: 6
B19: Anatomía | C19: PTC3-LM | E19: 5
B20: Histología | C20: Dra. Melisa Karina Chacón Lázaro | D20: LCB | E20: 6
B21: Bioseguridad | C21: Dra. Victoria Vera Pineda | D21: LCB | E21: 4
B22: TIC Aplicadas a las Ciencias Biomédicas | C22: Dra. Aidee Cruz Barragán | D22: LI | E22: 4
B24: 316-B
B25: Bioquímica Metabólica | C25: Dra. Claudia Chávez López | D25: LCB | E25: 6
B26: Anatomía | C26: PTC3-LM | E26: 5
B27: Histología | C27: Dra. Melisa Karina Chacón Lázaro | D27: LCB | E27: 5
B28: Bioseguridad | C28: M.C.I.B. Ericay Berenice Martínez Ramos | D28: LCB | E28: 5
B29: TIC Aplicadas a las Ciencias Biomédicas | C29: M.T.C.A. Rolando Pedro Gabriel | D29: LI | E29: 4
B31: 516
B32: Inmunología I | C32: Dr. Edgar Rodrigo Guzmán Bautista | D32: LCB | E32: 5
B33: Fisiología Sistémica | E33: 5
B34: Bacteriología | C34: Dra. Melisa Karina Chacón Lázaro | D34: LCB | E34: 6
B35: Biología Molecular de los Eucariontes | C35: Dr. Juan Carlos Barragán Gálvez | D35: LCB | E35: 6 | G35: colocar un dia con 4 horas seguidas de esta materia
B36: Modelos de Investigación | C36: M.B.E. Diego Sait Cruz Hernández | D36: LCB | E36: 4
B41: Bioinformatica Básica
C47: PROFESORES DE LCB | D47: TOTAL DE MATERIAS | E47: Otras carreras | F47: Total Grupos | G47: Total alumnos | H47: Total horas a la semana | I47: Status | J47: Reincorporación | K47: Horario Laboral | L47: Observaciones
B48: 1 | C48: M.B.E. Raúl Misael Cortés Olivera | D48: =COUNTIF($C$4:$C$44,C48) -> 1 | E48: ='Asignación-Profesor'!D3-D48 -> 0 | F48: ='Asignación-Profesor'!D3 -> 1 | G48: ='Asignación-Profesor'!P3 -> 0 | H48: ='Asignación-Profesor'!Q3 -> 6 | K48: 9:00-14:00 y 16:00-19:00
B49: 2 | C49: M.C.C.A.R.B. Guilibaldo Gabriel Zurita Vásquez | D49: =COUNTIF($C$4:$C$44,C49) -> 0 | E49: ='Asignación-Profesor'!D4-D49 -> 3 | F49: ='Asignación-Profesor'!D4 -> 3 | G49: ='Asignación-Profesor'!P4 -> 126 | H49: ='Asignación-Profesor'!Q4 -> 18 | K49: 8:00-13:00 y 16:00-19:00
B50: 3 | C50: M.C.I.B. Ericay Berenice Martínez Ramos | D50: =COUNTIF($C$4:$C$44,C50) -> 1 | E50: ='Asignación-Profesor'!D5-D50 -> 3 | F50: ='Asignación-Profesor'!D5 -> 4 | G50: ='Asignación-Profesor'!P5 -> 0 | H50: ='Asignación-Profesor'!Q5 -> 23 | K50: 8:00-13:00 y 16:00-19:00
B51: 4 | C51: Dra. Claudia Chávez López | D51: =COUNTIF($C$4:$C$44,C51) -> 2 | E51: ='Asignación-Profesor'!D6-D51 -> 2 | F51: ='Asignación-Profesor'!D6 -> 4 | G51: ='Asignación-Profesor'!P6 -> 0 | H51: ='Asignación-Profesor'!Q6 -> 22 | K51: 8:00-13:00 y 16:00-19:00
B52: 5 | C52: M.C. Andrea Itayetzzi Ortiz García | D52: =COUNTIF($C$4:$C$44,C52) -> 0 | E52: ='Asignación-Profesor'!D7-D52 -> 4 | F52: ='Asignación-Profesor'!D7 -> 4 | G52: ='Asignación-Profesor'!P7 -> 0 | H52: ='Asignación-Profesor'!Q7 -> 21 | K52: 8:00-13:00 y 16:00-19:00 | L52: Proyecto
B53: 6 | C53: Dr. Abisaí Martínez Sánchez | D53: =COUNTIF($C$4:$C$44,C53) -> 0 | E53: ='Asignación-Profesor'!D8-D53 -> 4 | F53: ='Asignación-Profesor'!D8 -> 4 | G53: ='Asignación-Profesor'!P8 -> 0 | H53: ='Asignación-Profesor'!Q8 -> 23 | K53: 9:00-14:00 y 16:00-19:00
B54: 7 | C54: Dra. Lilian Arzeta Pino | D54: =COUNTIF($C$4:$C$44,C54) -> 0 | E54: ='Asignación-Profesor'!D9-D54 -> 4 | F54: ='Asignación-Profesor'!D9 -> 4 | G54: ='Asignación-Profesor'!P9 -> 0 | H54: ='Asignación-Profesor'!Q9 -> 21 | I54: Sábatico | J54: Septiembre | K54: 9:00-14:00 y 16:00-19:00
B55: 8 | C55: Dr. Edgar Rodrigo Guzmán Bautista | D55: =COUNTIF($C$4:$C$44,C55) -> 2 | E55: ='Asignación-Profesor'!D10-D55 -> 0 | F55: ='Asignación-Profesor'!D10 -> 2 | G55: ='Asignación-Profesor'!P10 -> 0 | H55: ='Asignación-Profesor'!Q10 -> 11 | K55: 9:00-14:00 y 16:00-19:00 | L55: Proyecto, SOLO CLASES EN LA MAÑANA
B56: 9 | C56: Dr. Juan Carlos Barragán Gálvez | D56: =COUNTIF($C$4:$C$44,C56) -> 1 | E56: ='Asignación-Profesor'!D11-D56 -> 2 | F56: ='Asignación-Profesor'!D11 -> 3 | G56: ='Asignación-Profesor'!P11 -> 70 | H56: ='Asignación-Profesor'!Q11 -> 18 | K56: 9:00-14:00 y 16:00-19:00 | L56: Proyecto,
B57: 10 | C57: Dra. Karla Esmeralda Tello Ortega | D57: =COUNTIF($C$4:$C$44,C57) -> 1 | E57: ='Asignación-Profesor'!D12-D57 -> 2 | F57: ='Asignación-Profesor'!D12 -> 3 | G57: ='Asignación-Profesor'!P12 -> 0 | H57: ='Asignación-Profesor'!Q12 -> 16 | K57: 9:00-14:00 y 16:00-19:00
B58: 11 | C58: M.B.E. Diego Sait Cruz Hernández | D58: =COUNTIF($C$4:$C$44,C58) -> 1 | E58: ='Asignación-Profesor'!D13-D58 -> 3 | F58: ='Asignación-Profesor'!D13 -> 4 | G58: ='Asignación-Profesor'!P13 -> 80 | H58: ='Asignación-Profesor'!Q13 -> 19 | K58: 9:00-14:00 y 16:00-19:00
B59: 12 | C59: M.C.T.A. Iliana Vásquez Lara | D59: =COUNTIF($C$4:$C$44,C59) -> 0 | E59: ='Asignación-Profesor'!D14-D59 -> 4 | F59: ='Asignación-Profesor'!D14 -> 4 | G59: ='Asignación-Profesor'!P14 -> 120 | H59: ='Asignación-Profesor'!Q14 -> 21 | K59: 9:00-14:00 y 16:00-19:00
B60: 13 | C60: M.B.E. Ruth Monserrat Rodríguez Hernández | D60: =COUNTIF($C$4:$C$44,C60) -> 2 | E60: ='Asignación-Profesor'!D15-D60 -> 2 | F60: ='Asignación-Profesor'!D15 -> 4 | G60: ='Asignación-Profesor'!P15 -> 70 | H60: ='Asignación-Profesor'!Q15 -> 24 | K60: 9:00-14:00 y 16:00-19:00
B61: 14 | C61: Dra. Melisa Karina Chacón Lázaro | D61: =COUNTIF($C$4:$C$44,C61) -> 3 | E61: ='Asignación-Profesor'!D16-D61 -> 2 | F61: ='Asignación-Profesor'!D16 -> 5 | G61: ='Asignación-Profesor'!P16 -> 0 | H61: ='Asignación-Profesor'!Q16 -> 27 | K61: 8:00-13:00 y 16:00-19:00
B62: 15 | C62: Dra. Victoria Vera Pineda | D62: =COUNTIF($C$4:$C$44,C62) -> 2 | E62: ='Asignación-Profesor'!D17-D62 -> 3 | F62: ='Asignación-Profesor'!D17 -> 5 | G62: ='Asignación-Profesor'!P17 -> 120 | H62: ='Asignación-Profesor'!Q17 -> 23 | K62: 8:00-13:00 y 16:00-19:00

Sheet LM
A1: Dr. Juan Carlos Barragán Gálvez
B2: Materia | C2: Profesor asignado | D2: PE-Adscripción | E2: Horas por semana | F2: Número de alumnos
B3: 114-A (1)
B4: Anatomía Humana I | C4: PTC3-LM | D4: LM | E4: 6 | F4: 35
B5: Histología I | C5: Dr. Alejandro Francisco Cruz | D5: LM | E5: 5 | F5: 35
B6: Bioquímica | C6: M.B.E. Ruth Monserrat Rodríguez Hernández | D6: LCB | E6: 6 | F6: 35
B7: Embriología | C7: PTC8-LM | D7: LM | E7: 5 | F7: 35
B8: Historia del Pensamiento Filosófico | C8: M.F. Araceli Luz Alva Rodríguez Martínez | D8: LCE | E8: 4 | F8: 35
B10: 114-B (2)
B11: Anatomía Humana I | C11: PTC3-LM | D11: LM | E11: 6 | F11: 35
B12: Histología I | C12: Dr. Alejandro Francisco Cruz | D12: LM | E12: 5 | F12: 35
B13: Bioquímica | C13: Dr. Juan Carlos Barragán Gálvez | D13: LCB | E13: 6 | F13: 35
B14: Embriología | C14: PTC8-LM | D14: LM | E14: 5 | F14: 35
B15: Historia del Pensamiento Filosófico | C15: M.F. Araceli Luz Alva Rodríguez Martínez | D15: LCE | E15: 4 | F15: 35
B17: 114-C (3)
B18: Anatomía Humana I | C18: PTC3-LM | D18: LM | E18: 6 | F18: 35
B19: Histología I | C19: E.E. Edgar García Casas | D19: LM | E19: 5 | F19: 35
B20: Bioquímica | C20: Dr. Juan Carlos Barragán Gálvez | D20: LCB | E20: 6 | F20: 35
B21: Embriología | C21: PTC10-LM | D21: LM | E21: 5 | F21: 35
B22: Historia del Pensamiento Filosófico | C22: Dr. Guadalupe Gabriel Durán Férman | D22: DEP | E22: 4 | F22: 35
B24: 114-D (4)
B25: Anatomía Humana I | C25: PTC13-LM | D25: LM | E25: 6 | F25: 35
B26: Histología I | C26: E.E. Edgar García Casas | D26: LM | E26: 5 | F26: 35
B27: Bioquímica | C27: M.B.E. Ruth Monserrat Rodríguez Hernández | D27: LCB | E27: 6 | F27: 35
B28: Embriología | C28: PTC10-LM | D28: LM | E28: 5 | F28: 35
B29: Historia del Pensamiento Filosófico | C29: M.A.P. Diego Toto Jiménez | D29: LAP | E29: 4 | F29: 35
B31: 314-A
B32: Fisiología I | C32: PTC11-LM | D32: LM | E32: 6 | F32: 42
B33: Bacteriología y Micología Médica | C33: M.C.C.A.R.B. Guilibaldo Gabriel Zurita Vásquez | D33: LCB | E33: 6 | F33: 42
B34: Inmunología | C34: E.P.C. Yuniza Jocabeth Hernández Morales | D34: LM | E34: 5 | F34: 42
B35: Psicología Médica | E35: 4 | F35: 42
B36: Historia y Antropología Médica | C36: Méd. Guadalupe Ithalivi Olivera Domínguez | D36: LM | E36: 4 | F36: 42
B38: 314-B
B39: Fisiología I | C39: PTC11-LM | D39: LM | E39: 6 | F39: 42
B40: Bacteriología y Micología Médica | C40: M.C.C.A.R.B. Guilibaldo Gabriel Zurita Vásquez | D40: LCB | E40: 6 | F40: 42
B41: Inmunología | C41: E.P.C. Yuniza Jocabeth Hernández Morales | D41: LM | E41: 5 | F41: 42
B42: Psicología Médica | E42: 4 | F42: 42
B43: Historia y Antropología Médica | C43: M.S.P. Pablo Cataneo Pérez | D43: LM | E43: 4 | F43: 42
B45: 314-C
B46: Fisiología I | C46: PTC11-LM | D46: LM | E46: 6 | F46: 42
B47: Bacteriología y Micología Médica | C47: M.C.C.A.R.B. Guilibaldo Gabriel Zurita Vásquez | D47: LCB | E47: 6 | F47: 42
B48: Inmunología | C48: M.C.Q.B. David Gómez Martínez | D48: LM | E48: 5 | F48: 42
B49: Psicología Médica | E49: 4 | F49: 42
B50: Historia y Antropología Médica | C50: M.S.P. Pablo Cataneo Pérez | D50: LM | E50: 4 | F50: 42
B52: 514-A
B53: Fundamentos de Cirugía | C53: PTC1-LM | D53: LM | E53: 6 | F53: 38
B54: Anatomía y Fisiología Patológica | C54: E.P.C. Yuniza Jocabeth Hernández Morales | D54: LM | E54: 5 | F54: 38
B55: Farmacología II | C55: PTC12-LM | D55: LM | E55: 5 | F55: 38
B56: Imagenología Médica | C56: PTC6-LM | D56: LM | E56: 5 | F56: 38
B57: Salud Pública | C57: M.S.P. José Luis Eliazar Torralba Flores | D57: LM | E57: 4 | F57: 38
B59: 514-B
B60: Fundamentos de Cirugía | C60: PTC1-LM | D60: LM | E60: 6 | F60: 38
B61: Anatomía y Fisiología Patológica | C61: E.P.C. Yuniza Jocabeth Hernández Morales | D61: LM | E61: 5 | F61: 38
B62: Farmacología II | C62: PTC12-LM | D62: LM | E62: 5 | F62: 38
B63: Imagenología Médica | C63: PTC6-LM | D63: LM | E63: 5 | F63: 38
B64: Salud Pública | C64: M.S.P. José Luis Eliazar Torralba Flores | D64: LM | E64: 4 | F64: 38
B66: 514-C
B67: Fundamentos de Cirugía | C67: PTC1-LM | D67: LM | E67: 6 | F67: 38
B68: Anatomía y Fisiología Patológica | C68: E.P.C. Yuniza Jocabeth Hernández Morales | D68: LM | E68: 5 | F68: 38
B69: Farmacología II | C69: PTC12-LM | D69: LM | E69: 5 | F69: 38
B70: Imagenología Médica | C70: PTC6-LM | D70: LM | E70: 5 | F70: 38
B71: Salud Pública | C71: M.S.P. José Luis Eliazar Torralba Flores | D71: LM | E71: 4 | F71: 38
B73: 714-A
B74: Cirugía cardiotorácica | C74: M.S.P. Pablo Cataneo Pérez | D74: LM | E74: 6 | F74: 37
B75: Neumología | C75: E.N. Daniela Ruiz Ramírez | D75: LM | E75: 5 | F75: 37
B76: Cardiología | C76: PTC5-LM | D76: LM | E76: 5 | F76: 37
B77: Genética | C77: E.M.F. Arturo José Moreno Juárez | D77: LM | E77: 5 | F77: 37
B78: Epidemiología | C78: E.E. Edgar García Casas | D78: LM | E78: 4 | F78: 37
B80: 714-B
B81: Cirugía cardiotorácica | C81: PTC6-LM | D81: LM | E81: 6 | F81: 37
B82: Neumología | C82: E.N. Daniela Ruiz Ramírez | D82: LM | E82: 5 | F82: 37
B83: Cardiología | C83: PTC5-LM | D83: LM | E83: 5 | F83: 37
B84: Genética | C84: M.D.C.S. Concepción Julián López | D84: LM | E84: 5 | F84: 37
B85: Epidemiología | C85: E.E. Edgar García Casas | D85: LM | E85: 4 | F85: 37
B87: 714-C
B88: Cirugía cardiotorácica | C88: PTC6-LM | D88: LM | E88: 6 | F88: 37
B89: Neumología | C89: E.N. Daniela Ruiz Ramírez | D89: LM | E89: 5 | F89: 37
B90: Cardiología | C90: PTC5-LM | D90: LM | E90: 5 | F90: 37
B91: Genética | C91: M.D.C.S. Concepción Julián López | D91: LM | E91: 5 | F91: 37
B92: Epidemiología | C92: E.E. Edgar García Casas | D92: LM | E92: 4 | F92: 37
B94: 914-A
B95: Ginecología | C95: PTC7-LM | D95: LM | E95: 6 | F95: 38
B96: Nefrología | C96: PTC5-LM | D96: LM | E96: 5 | F96: 38
B97: Reumatología | C97: Dr. Alejandro Francisco Cruz | D97: LM | E97: 5 | F97: 38
B98: Pediatría II | C98: Méd. Jennifer de la Luz Santos Santos | D98: LM | E98: 5 | F98: 38
B99: Metodología de la investigación cualitativa | C99: M.C.E. Ignacio Grajales Alonso | D99: LE | E99: 4 | F99: 38
B101: 914-B
B102: Ginecología | C102: PTC7-LM | D102: LM | E102: 6 | F102: 38
B103: Nefrología | C103: PTC5-LM | D103: LM | E103: 5 | F103: 38
B104: Reumatología | C104: Dr. Alejandro Francisco Cruz | D104: LM | E104: 5 | F104: 38
B105: Pediatría II | C105: PTC11-LM | D105: LM | E105: 5 | F105: 38
B106: Metodología de la investigación cualitativa | C106: M.C.E. Ignacio Grajales Alonso | D106: LE | E106: 4 | F106: 38
B108: 1114-A
B109: Urología | C109: Méd. Jasibe Ivette Cruz Vásquez | D109: LM | E109: 5 | F109: 46
B110: Hematología | C110: M.C.Q.B. David Gómez Martínez | D110: LM | E110: 5 | F110: 46
B111: Endocrinología | C111: PTC2-LM | D111: LM | E111: 5 | F111: 46
B112: Urgencias Médicas | C112: E.N. Daniela Ruiz Ramírez | D112: LM | E112: 6 | F112: 46
B113: Administración de Organizaciones y Servicios de Salud | C113: M.C.P.E.D.R. Elsa A. Mendoza Cortés | D113: LCE | E113: 4 | F113: 46
B115: 1114-B
B116: Urología | C116: Méd. Jasibe Ivette Cruz Vásquez | D116: LM | E116: 5 | F116: 46
...

Sheet LO
A1: ASIGNACIÓN DE MATERIAS PARA EL SEMESTRE 26-27A
B2: Materia | C2: Profesor asignado | D2: PE-Adscripción | E2: Horas por semana | F2: Número de alumnos
B3: 113-A
B4: Anatomía y Fisiología Humana | C4: E.M.F. Arturo José Moreno Juárez | D4: LM | E4: 6
B5: Embriología Aplicada a la Odontología | C5: PTC8-LM | D5: LM | E5: 5
B6: Bioquímica Aplicada a la Odontología | C6: M.B.E. Diego Sait Cruz Hernández | D6: LCB | E6: 5
B7: Historia del Pensamiento Filosófico | C7: M.F. Araceli Luz Alva Rodríguez Martínez | D7: LCE | E7: 5
B8: Materiales Dentales | C8: C.D. Luis Bernardo Martínez Martínez | D8: LO | E8: 6 | G8: Materia que requiere de prácticas en laboratorio
B10: 113-B
B11: Anatomía y Fisiología Humana | C11: E.M.F. Arturo José Moreno Juárez | D11: LM | E11: 6
B12: Embriología Aplicada a la Odontología | C12: PTC8-LM | D12: LM | E12: 5
B13: Bioquímica Aplicada a la Odontología | C13: M.C. Andrea Itayetzzi Ortiz García | D13: LCB | E13: 5
B14: Historia del Pensamiento Filosófico | C14: Dra. Deisy Coromoto Rebolledo López | D14: DEP | E14: 5
B15: Materiales Dentales | C15: L.O. Yamile Yolotzin Vásquez Ríos | D15: LO | E15: 6 | G15: Materia que requiere de prácticas en laboratorio
B17: 113-C
B18: Anatomía y Fisiología Humana | C18: E.M.F. Arturo José Moreno Juárez | D18: LM | E18: 6
B19: Embriología Aplicada a la Odontología | C19: PTC8-LM | D19: LM | E19: 5
B20: Bioquímica Aplicada a la Odontología | C20: M.C. Andrea Itayetzzi Ortiz García | D20: LCB | E20: 5
B21: Historia del Pensamiento Filosófico | C21: Dr. Horacio González Pérez | D21: DEP | E21: 5
B22: Materiales Dentales | C22: L.O. Yamile Yolotzin Vásquez Ríos | D22: LO | E22: 6 | G22: Materia que requiere de prácticas en laboratorio
B24: 113-D
B25: Anatomía y Fisiología Humana | C25: E.M.F. Arturo José Moreno Juárez | D25: LM | E25: 6
B26: Embriología Aplicada a la Odontología | C26: PTC7-LM | D26: LM | E26: 5
B27: Bioquímica Aplicada a la Odontología | C27: M.C. Andrea Itayetzzi Ortiz García | D27: LCB | E27: 5
B28: Historia del Pensamiento Filosófico | C28: Dr. Horacio González Pérez | D28: DEP | E28: 5
B29: Materiales Dentales | C29: C.D. Luis Bernardo Martínez Martínez | D29: LO | E29: 6 | G29: Materia que requiere de prácticas en laboratorio
B31: 113-E
B32: Anatomía y Fisiología Humana | C32: Méd. Jennifer de la Luz Santos Santos | D32: LM | E32: 6
B33: Embriología Aplicada a la Odontología | C33: PTC7-LM | D33: LM | E33: 5
B34: Bioquímica Aplicada a la Odontología | C34: Dra. Melisa Karina Chacón Lázaro | D34: LCB | E34: 5
B35: Historia del Pensamiento Filosófico | C35: Dr. Joselito Fernández Tapia | D35: DEP | E35: 5
B36: Materiales Dentales | C36: L.O. César Yazid Martínez Martínez | D36: LO | E36: 6 | G36: Materia que requiere de prácticas en laboratorio
B38: 113-F
B39: Anatomía y Fisiología Humana | C39: Méd. Jennifer de la Luz Santos Santos | D39: LM | E39: 6
B40: Embriología Aplicada a la Odontología | C40: PTC7-LM | D40: LM | E40: 5
B41: Bioquímica Aplicada a la Odontología | C41: Dr. Abisaí Martínez Sánchez | D41: LCB | E41: 5
B42: Historia del Pensamiento Filosófico | C42: Dr. Mauricio Sosa Montes | D42: LAP | E42: 5
B43: Materiales Dentales | C43: L.O. Joel Abisai Hernández López | D43: LO | E43: 6 | G43: Materia que requiere de prácticas en laboratorio
B45: 113-G
B46: Anatomía y Fisiología Humana | C46: Méd. Jennifer de la Luz Santos Santos | D46: LM | E46: 6 | F46: PTC7-LM
B47: Embriología Aplicada a la Odontología | E47: 5
B48: Bioquímica Aplicada a la Odontología | C48: Dra. Melisa Karina Chacón Lázaro | D48: LCB | E48: 5
B49: Historia del Pensamiento Filosófico | D49: LI | E49: 5
B50: Materiales Dentales | C50: L.O. Litzi Citlalic Serra Suárez | D50: LO | E50: 6 | G50: Materia que requiere de prácticas en laboratorio
B52: 113-H
B53: Anatomía y Fisiología Humana | C53: Méd. Jennifer de la Luz Santos Santos | D53: LM | E53: 6
B54: Embriología Aplicada a la Odontología | E54: 5
B55: Bioquímica Aplicada a la Odontología | C55: Dra. Claudia Chávez López | D55: LCB | E55: 5
B56: Historia del Pensamiento Filosófico | C56: M.A. Aurelia Gómez Gómez | D56: LCE | E56: 5
B57: Materiales Dentales | C57: L.O. Joel Abisai Hernández López | D57: LO | E57: 6 | G57: Materia que requiere de prácticas en laboratorio
B59: 113-I
B60: Anatomía y Fisiología Humana | C60: Méd. Xochiquetzalli García Mendoza | D60: LM | E60: 6
B61: Embriología Aplicada a la Odontología | E61: 5
B62: Bioquímica Aplicada a la Odontología | C62: Dra. Lilian Arzeta Pino | D62: LCB | E62: 5
B63: Historia del Pensamiento Filosófico | C63: M.A. Aurelia Gómez Gómez | D63: LCE | E63: 5
B64: Materiales Dentales | C64: L.O. Litzi Citlalic Serra Suárez | D64: LO | E64: 6 | G64: Materia que requiere de prácticas en laboratorio
B66: 113-J
B67: Anatomía y Fisiología Humana | C67: Méd. Xochiquetzalli García Mendoza | D67: LM | E67: 6
B68: Embriología Aplicada a la Odontología | E68: 5
B69: Bioquímica Aplicada a la Odontología | C69: Dra. Claudia Chávez López | D69: LCB | E69: 5
B70: Historia del Pensamiento Filosófico | C70: Dr. Pedro Durán Férman | D70: LCE | E70: 5
B71: Materiales Dentales | C71: L.O. César Yazid Martínez Martínez | D71: LO | E71: 6 | G71: Materia que requiere de prácticas en laboratorio
B73: 313-A
B74: Anatomía e Histología Dental | C74: C.D. Jesús Cruz Velazquez | D74: LO | E74: 5 | F74: 40 | G74: Materia que requiere de prácticas en laboratorio
B75: Patología General e Inmunología | C75: PTC2-LM | D75: LM | E75: 5 | F75: 40
B76: Farmacología en Odontología | C76: M.B.E. Diego Sait Cruz Hernández | D76: LCB | E76: 5 | F76: 40
B77: Odontología Preventiva y Salud Pública I | C77: Dr. José Eduardo Orellana Centeno | D77: LO | E77: 5 | F77: 40
B78: Radiología e Imagenología | C78: C.D. Luis Bernardo Martínez Martínez | D78: LO | E78: 5 | F78: 40 | G78: Materia que requiere de prácticas en laboratorio
B80: 313-B
B81: Anatomía e Histología Dental | C81: L.O. Yamile Yolotzin Vásquez Ríos | D81: LO | E81: 5 | F81: 40 | G81: Materia que requiere de prácticas en laboratorio
B82: Patología General e Inmunología | C82: PTC2-LM | D82: LM | E82: 5 | F82: 40
B83: Farmacología en Odontología | C83: M.B.E. Diego Sait Cruz Hernández | D83: LCB | E83: 5 | F83: 40
B84: Odontología Preventiva y Salud Pública I | C84: Dr. José Eduardo Orellana Centeno | D84: LO | E84: 5 | F84: 40
B85: Radiología e Imagenología | C85: C.D. Amalinalli Barón Zaragoza | D85: LO | E85: 5 | F85: 40 | G85: Materia que requiere de prácticas en laboratorio
B87: 313-C
B88: Anatomía e Histología Dental | C88: M.E. Laura Alejandra Mora González | D88: LO | E88: 5 | F88: 40 | G88: Materia que requiere de prácticas en laboratorio
B89: Patología General e Inmunología | C89: PTC2-LM | D89: LM | E89: 5 | F89: 40
B90: Farmacología en Odontología | C90: Dra. Victoria Vera Pineda | D90: LCB | E90: 5 | F90: 40
B91: Odontología Preventiva y Salud Pública I | C91: C.D. Katia Cecilia González Vázquez | D91: LO | E91: 5 | F91: 40
B92: Radiología e Imagenología | C92: C.D. Amalinalli Barón Zaragoza | D92: LO | E92: 5 | F92: 40 | G92: Materia que requiere de prácticas en laboratorio
B94: 313-D
B95: Anatomía e Histología Dental | C95: L.O. Yamile Yolotzin Vásquez Ríos | D95: LO | E95: 5 | F95: 40 | G95: Materia que requiere de prácticas en laboratorio
B96: Patología General e Inmunología | C96: PTC4-LM | D96: LM | E96: 5 | F96: 40
B97: Farmacología en Odontología | C97: Dra. Victoria Vera Pineda | D97: LCB | E97: 5 | F97: 40
B98: Odontología Preventiva y Salud Pública I | C98: L.O. Jocabet Ramírez García | D98: LO | E98: 5 | F98: 40
B99: Radiología e Imagenología | C99: C.D. Luis Bernardo Martínez Martínez | D99: LO | E99: 5 | F99: 40 | G99: Materia que requiere de prácticas en laboratorio
B101: 313-E
B102: Anatomía e Histología Dental | C102: M.E. Laura Alejandra Mora González | D102: LO | E102: 5 | F102: 40 | G102: Materia que requiere de prácticas en laboratorio
B103: Patología General e Inmunología | C103: PTC4-LM | D103: LM | E103: 5 | F103: 40
B104: Farmacología en Odontología | C104: Dra. Victoria Vera Pineda | D104: LCB | E104: 5 | F104: 40
B105: Odontología Preventiva y Salud Pública I | C105: Dr. José Eduardo Orellana Centeno | D105: LO | E105: 5 | F105: 40
B106: Radiología e Imagenología | C106: L.O. Litzi Citlalic Serra Suárez | D106: LO | E106: 5 | F106: 40 | G106: Materia que requiere de prácticas en laboratorio
B108: 313-F
B109: Anatomía e Histología Dental | C109: L.O. Zoe Mabel Méndez Cruz | D109: LO | E109: 5 | F109: 40 | G109: Materia que requiere de prácticas en laboratorio
B110: Patología General e Inmunología | C110: PTC4-LM | D110: LM | E110: 5 | F110: 40
B111: Farmacología en Odontología | C111: Dr. Hady Keita | D111: LCB | E111: 5 | F111: 40
B112: Odontología Preventiva y Salud Pública I | C112: L.O. Jocabet Ramírez García | D112: LO | E112: 5 | F112: 40
B113: Radiología e Imagenología | C113: L.O. Litzi Citlalic Serra Suárez | D113: LO | E113: 5 | F113: 40 | G113: Materia que requiere de prácticas en laboratorio
B115: 313-G
B116: Anatomía e Histología Dental | C116: L.O. Jocabet Ramírez García | D116: LO | E116: 5 | F116: 40 | G116: Materia que requiere de prácticas en laboratorio
...

Sheet LE
A1: ASIGNACIÓN DE MATERIAS PARA EL SEMESTRE 26-27A
B2: Materia | C2: Profesor asignado | D2: PE-Adscripción | E2: Horas por semana | F2: Número de alumnos
B3: 103-A PE 2024
B4: Bases Epistemológicas de la Enfermería | C4: M.E.A.T.E. Daniela Alonso Osorio | D4: LE | E4: 5
B5: Bioquímica para Enfermería | C5: M.C.I.B. Ericay Berenice Martínez Ramos | D5: LCB | E5: 6
B6: Historia del Pensamiento Filosófico | C6: Dra. Roxana Nayeli Guerrero Sotelo | D6: LE | E6: 4
B7: Anatomía Humana | C7: L.E. Amalia Hernández Blas | D7: LE | E7: 5
B8: Sociología y Salud | C8: M.C.E. Douglas Crittenden Nance | D8: LE | E8: 4
B10: 103-B PE 2024
B11: Bases Epistemológicas de la Enfermería | C11: L.E. Yarely Yaneth Zurita López | D11: LE | E11: 5
B12: Bioquímica para Enfermería | C12: M.C.I.B. Ericay Berenice Martínez Ramos | D12: LCB | E12: 6
B13: Historia del Pensamiento Filosófico | C13: Dra. Maria Guadalupe Temores Alcántara | D13: DEP | E13: 4
B14: Anatomía Humana | C14: L.E. Amalia Hernández Blas | D14: LE | E14: 5
B15: Sociología y Salud | C15: M.C.E. Douglas Crittenden Nance | D15: LE | E15: 4
B17: 103-C PE 2024
B18: Bases Epistemológicas de la Enfermería | C18: L.E. Yarely Yaneth Zurita López | D18: LE | E18: 5
B19: Bioquímica para Enfermería | C19: M.C.I.B. Ericay Berenice Martínez Ramos | D19: LCB | E19: 6
B20: Historia del Pensamiento Filosófico | C20: Dra. Maria Guadalupe Temores Alcántara | D20: DEP | E20: 4
B21: Anatomía Humana | C21: PTC-LE1 | D21: LE | E21: 5
B22: Sociología y Salud | C22: PTC-LE2 | D22: LE | E22: 4
B24: 103-D PE 2024
B25: Bases Epistemológicas de la Enfermería | C25: M.S.P. Maleni Rodríguez García | D25: LE | E25: 5
B26: Bioquímica para Enfermería | C26: Dr. Abisaí Martínez Sánchez | D26: LCB | E26: 6
B27: Historia del Pensamiento Filosófico | C27: M.T.C.A. Rolando Pedro Gabriel | D27: LCE | E27: 4 | F27: Lo cubrirá informatica
B28: Anatomía Humana | C28: PTC-LE1 | D28: LE | E28: 5
B29: Sociología y Salud | E29: 4
B31: 103-E PE 2024
B32: Bases Epistemológicas de la Enfermería | C32: M.E.S. Adriana Zúñiga Jiménez | D32: LE | E32: 5
B33: Bioquímica para Enfermería | C33: Dr. Abisaí Martínez Sánchez | D33: LCB | E33: 6
B34: Historia del Pensamiento Filosófico | C34: M.I.T.I. Oswaldo Rey Ávila Barrón | D34: LCE | E34: 4 | F34: Lo cubrirá informatica
B35: Anatomía Humana | C35: M.A.I.S. Amelia Roselia Juárez Agudo | D35: LE | E35: 5
B36: Sociología y Salud | C36: Dr. Gerardo Roberto Aragón Gonzalez | D36: LE | E36: 4
B38: 103-F PE 2024
B39: Bases Epistemológicas de la Enfermería | C39: M.E.S. Adriana Zúñiga Jiménez | D39: LE | E39: 5
B40: Bioquímica para Enfermería | C40: Dra. Karla Esmeralda Tello Ortega | D40: LCB | E40: 6
B41: Historia del Pensamiento Filosófico | C41: Dra. Reyna Minerva Hernández Vásquez | D41: LCE | E41: 4
B42: Anatomía Humana | C42: M.A.I.S. Amelia Roselia Juárez Agudo | D42: LE | E42: 5
B43: Sociología y Salud | C43: Dr. Gerardo Roberto Aragón Gonzalez | D43: LE | E43: 4
B45: 103-G PE 2024
B46: Bases Epistemológicas de la Enfermería | C46: M.E.A.T.E. Daniela Alonso Osorio | D46: LE | E46: 5
B47: Bioquímica para Enfermería | C47: Dra. Karla Esmeralda Tello Ortega | D47: LCB | E47: 6
B48: Historia del Pensamiento Filosófico | C48: Dra. Reyna Minerva Hernández Vásquez | D48: LCE | E48: 4
B49: Anatomía Humana | C49: M.A.I.S. Amelia Roselia Juárez Agudo | D49: LE | E49: 5
B50: Sociología y Salud | C50: Dr. Gerardo Roberto Aragón Gonzalez | D50: LE | E50: 4
B52: 103-H PE 2024
B53: Bases Epistemológicas de la Enfermería | C53: M.C.E. Ignacio Grajales Alonso | D53: LE | E53: 5
B54: Bioquímica para Enfermería | C54: Dra. Lilian Arzeta Pino | D54: LCB | E54: 6
B55: Historia del Pensamiento Filosófico | C55: M.C.P.E.D.R. Elsa A. Mendoza Cortés | D55: LCE | E55: 4
B56: Anatomía Humana | C56: PTC-LE1 | D56: LE | E56: 5
B57: Sociología y Salud | C57: Dr. Gerardo Roberto Aragón Gonzalez | D57: LE | E57: 4
B59: 103-I PE 2024
B60: Bases Epistemológicas de la Enfermería | C60: M.C.E. Ignacio Grajales Alonso | D60: LE | E60: 5
B61: Bioquímica para Enfermería | C61: Dra. Lilian Arzeta Pino | D61: LCB | E61: 6
B62: Historia del Pensamiento Filosófico | C62: M.C.P.E.D.R. Elsa A. Mendoza Cortés | D62: LCE | E62: 4
B63: Anatomía Humana | E63: 5
B64: Sociología y Salud | E64: 4
B66: 103-J PE 2024
B67: Bases Epistemológicas de la Enfermería | C67: E.E.S.M.P. Dania Velasco Ramírez | D67: LE | E67: 5
B68: Bioquímica para Enfermería | C68: Dr. Abisaí Martínez Sánchez | D68: LCB | E68: 6
B69: Historia del Pensamiento Filosófico | C69: M.C.D.R.T. Lizeth Daniza Gómez Hernández | D69: LAP | E69: 4
B70: Anatomía Humana | E70: 5
B71: Sociología y Salud | E71: 4
B73: 103-K PE 2024
B74: Bases Epistemológicas de la Enfermería | C74: E.E.S.M.P. Dania Velasco Ramírez | D74: LE | E74: 5
B75: Bioquímica para Enfermería | C75: M.C. Andrea Itayetzzi Ortiz García | D75: LCB | E75: 6
B76: Historia del Pensamiento Filosófico | C76: M.C.D.R.T. Lizeth Daniza Gómez Hernández | D76: LAP | E76: 4
B77: Anatomía Humana | E77: 5
B78: Sociología y Salud | E78: 4
B80: 303-A PE 2024
B81: Bases de la Enfermería Clínica | C81: E.E.S.M.P. Isabel Santos Ruiz | D81: LE | E81: 6 | F81: 31
B82: Bases de la Enfermería Comunitaría | C82: M.E.A.T.E. Daniela Alonso Osorio | D82: LE | E82: 5 | F82: 31
B83: Introducción a la Psicología | C83: M.S.P. Gloria Verónica Alba Alba | D83: LE | E83: 5 | F83: 31
B84: Salud Pública | C84: M.S.P. Maleni Rodríguez García | D84: LE | E84: 5 | F84: 31
B85: Fisiología Avanzada | C85: Méd. Xochiquetzalli García Mendoza | D85: LM | E85: 5 | F85: 31
B87: 303-B PE 2024
B88: Bases de la Enfermería Clínica | C88: E.E.P. Rossell Perla Stockett Hernández | D88: LE | E88: 6 | F88: 31
B89: Bases de la Enfermería Comunitaría | C89: M.E.A.T.E. Daniela Alonso Osorio | D89: LE | E89: 5 | F89: 31
B90: Introducción a la Psicología | C90: M.S.P. Gloria Verónica Alba Alba | D90: LE | E90: 5 | F90: 31
B91: Salud Pública | C91: M.S.P. Maleni Rodríguez García | D91: LE | E91: 5 | F91: 31
B92: Fisiología Avanzada | C92: Méd. Xochiquetzalli García Mendoza | D92: LM | E92: 5 | F92: 31
B94: 303-C PE 2024
B95: Bases de la Enfermería Clínica | C95: E.E.S.M.P. Isabel Santos Ruiz | D95: LE | E95: 6 | F95: 30
B96: Bases de la Enfermería Comunitaría | C96: M.A.S.E. Porfiria Sánchez Martínez | D96: LE | E96: 5 | F96: 30
B97: Introducción a la Psicología | C97: M.S.P. Gloria Verónica Alba Alba | D97: LE | E97: 5 | F97: 30
B98: Salud Pública | C98: M.S.P. Maleni Rodríguez García | D98: LE | E98: 5 | F98: 30
B99: Fisiología Avanzada | C99: Méd. Xochiquetzalli García Mendoza | D99: LM | E99: 5 | F99: 30
B101: 303-D PE 2024
B102: Bases de la Enfermería Clínica | C102: E.E.P. Rossell Perla Stockett Hernández | D102: LE | E102: 6 | F102: 30
B103: Bases de la Enfermería Comunitaría | C103: M.A.S.E. Porfiria Sánchez Martínez | D103: LE | E103: 5 | F103: 30
B104: Introducción a la Psicología | C104: M.S.P. Gloria Verónica Alba Alba | D104: LE | E104: 5 | F104: 30
B105: Salud Pública | C105: M.C.E. Luis Miguel Márquez Valdez | D105: LE | E105: 5 | F105: 30
B106: Fisiología Avanzada | C106: PTC10-LM | D106: LM | E106: 5 | F106: 30
B108: 303-E PE 2024
B109: Bases de la Enfermería Clínica | C109: Dra. Verónica Marilú Brena Ramos | D109: LE | E109: 6 | F109: 30
B110: Bases de la Enfermería Comunitaría | C110: L.E. Yarely Yaneth Zurita López | D110: LE | E110: 5 | F110: 30
B111: Introducción a la Psicología | C111: M.R.N. Pedro Luis Hernández González | D111: LE | E111: 5 | F111: 30
B112: Salud Pública | C112: M.C.E. Luis Miguel Márquez Valdez | D112: LE | E112: 5 | F112: 30
B113: Fisiología Avanzada | C113: PTC10-LM | D113: LM | E113: 5 | F113: 30
B115: 303-F PE 2024
B116: Bases de la Enfermería Clínica | C116: Dra. Verónica Marilú Brena Ramos | D116: LE | E116: 6 | F116: 30
...

Sheet LN
A1: ASIGNACIÓN DE MATERIAS PARA EL SEMESTRE 26-27A
B2: Materia | C2: Profesor asignado | D2: PE-Adscripción | E2: Horas por semana | F2: Número de alumnos
B3: 107-A PE 2025
B4: Fundamentos de Nutrición Humana | C4: M.S.P. Felipe de Jesús Parada Luna | D4: LN | E4: 6 | F4: 25 | H4: M.C.A. Laura Jocelyn Valdez Gutiérrez
B5: Anatomía y fisiología Humana I | C5: PTC9-LM | D5: LM | E5: 6 | F5: 25
B6: Antropología de la Alimentación | C6: L.N. César Juárez Durán | D6: LN | E6: 5 | F6: 25
B7: Química Nutricional | C7: M.C.T.A. Iliana Vásquez Lara | D7: LCB | E7: 6 | F7: 25
B8: Historia del Pensamiento Filosófico | C8: Mtro. Diego Toto Jiménez | D8: LAP/LAM | E8: 4 | F8: 25
B10: 107-B PE 2025
B11: Fundamentos de Nutrición Humana | C11: M.S.P. Felipe de Jesús Parada Luna | D11: LN | E11: 6 | F11: 25 | H11: M.C.A. Laura Jocelyn Valdez Gutiérrez
B12: Anatomía y fisiología Humana I | C12: PTC9-LM | D12: LM | E12: 6 | F12: 25
B13: Antropología de la Alimentación | C13: L.N. César Juárez Durán | D13: LN | E13: 5 | F13: 25
B14: Química Nutricional | C14: M.C.T.A. Iliana Vásquez Lara | D14: LCB | E14: 6 | F14: 25
B15: Historia del Pensamiento Filosófico | C15: M.C.D.R.T. Lizeth Daniza Gómez Hernández | D15: LAP/LAM | E15: 4 | F15: 25
B17: 307 PE 2025
B18: Evaluación del Estado de Nutrición I | C18: M.S.P. Teófila Enriquez Almaraz | D18: LN | E18: 5 | F18: 34
B19: Educación Alimentaria Nutricional | C19: L.N. César Juárez Durán | D19: LN | E19: 5 | F19: 34
B20: Patología General y Trastornos Asociados a la Nutrición | D20: LM | E20: 5 | F20: 34
B21: Bioquímica Nutricional II | C21: Dra. Claudia Villanueva Cañongo | D21: LN | E21: 5 | F21: 34
B22: Microbiología de los Alimentos | C22: M.C.T.A. Iliana Vásquez Lara | D22: LCB | E22: 5 | F22: 34
B24: 507 PE 2017
B25: Cálculo y Laboratorio de Nutrición en el Ciclo de Vida | C25: M.S.P. Teófila Enriquez Almaraz | D25: LN | E25: 6 | F25: 43
B26: Gastroenterología Nutricional | D26: LM | E26: 5 | F26: 43
B27: Laboratorio de Evaluación del Estado de Nutrición | C27: Dra. Maria Dolores Caballero Sánchez | D27: LN | E27: 5 | F27: 43
B28: Administración general | C28: Dra. Reyna Minerva Hernández Vásquez | D28: LCE | E28: 5 | F28: 43
B29: Nutrición Poblacional II | C29: M.S.P. Eric Ramirez Bohorquez | D29: LN | E29: 4 | F29: 43
B31: 707 PE 2017
B32: Cálculo y Dietoterapia en Situaciones Patológicas II | C32: Dra. Maria Dolores Caballero Sánchez | D32: LN | E32: 6 | F32: 36
B33: Nutrición y Farmacología | D33: LM | E33: 4 | F33: 36
B34: Química de los Alimentos | C34: M.C.T.A. Iliana Vásquez Lara | D34: LCB | E34: 4 | F34: 36 | H34: M.C.A. Laura Jocelyn Valdez Gutiérrez
B35: Análisis de Alimentos | C35: Dra. Claudia Villanueva Cañongo | D35: LN | E35: 6 | F35: 36
B36: Administración de Servicios de Alimentos II | C36: M.S.P. Felipe de Jesús Parada Luna | D36: LN | E36: 5 | F36: 36
B38: 907 PE 2017
B39: Atención Clínica Nutricional | C39: M.N.C. Griselda Belén Avendaño Rodríguez | D39: LN | E39: 6 | F39: 34
B40: Bioestadística | C40: M.C.M. Jesús Pacheco Mendoza | D40: LI | E40: 5 | F40: 34
B41: Nutrición en Salud Pública | C41: M.S.P. Eric Ramirez Bohorquez | D41: LN | E41: 4 | F41: 34
B42: Métodos y Técnicas de Investigación | E42: 5 | F42: 34
B43: Tecnología de Alimentos de Origen Animal | C43: Dra. Claudia Villanueva Cañongo | D43: LN | E43: 5 | F43: 34
H48: *M.C.A. Laura Jocelyn Valdez Gutiérrez 1 grupo de enfermería/Odonto
C57: PROFESORES DE LN | D57: TOTAL DE MATERIAS | E57: Otras carreras | F57: Total | G57: Total alumnos | H57: Total horas a la semana | I57: Status | J57: Reincorporación | K57: Horario Laboral
B58: 1 | C58: M.N.C. Griselda Belén Avendaño Rodríguez | D58: =COUNTIF($C$4:$C$53,C58) -> 1 | E58: ='Asignación-Profesor'!D114-D58 -> 0 | F58: =E58+D58 -> 1 | G58: ='Asignación-Profesor'!P114 -> 34 | H58: ='Asignación-Profesor'!Q114 -> 6 | K58: 9:00-14:00 16:00-19:00
B59: 2 | C59: M.C.A. Laura Jocelyn Valdez Gutiérrez | D59: =COUNTIF($C$4:$C$53,C59) -> 0 | E59: ='Asignación-Profesor'!D115-D59 -> 0 | F59: =E59+D59 -> 0 | G59: ='Asignación-Profesor'!P115 -> 0 | H59: ='Asignación-Profesor'!Q115 -> 0 | K59: 8:00-13:00 16:00-19:00 | L59: Solicitud de sábatico con resolución pendiente
B60: 3 | C60: L.N. César Juárez Durán | D60: =COUNTIF($C$4:$C$53,C60) -> 3 | E60: ='Asignación-Profesor'!D116-D60 -> 2 | F60: =E60+D60 -> 5 | G60: ='Asignación-Profesor'!P116 -> 148 | H60: ='Asignación-Profesor'!Q116 -> 25 | K60: 8:00-13:00 16:00-19:00
B61: 4 | C61: Dra. Claudia Villanueva Cañongo | D61: =COUNTIF($C$4:$C$53,C61) -> 3 | E61: ='Asignación-Profesor'!D117-D61 -> 0 | F61: =E61+D61 -> 3 | G61: ='Asignación-Profesor'!P117 -> 104 | H61: ='Asignación-Profesor'!Q117 -> 16 | K61: 9:00-14:00 16:00-19:00
B62: 5 | C62: M.S.P. Eric Ramirez Bohorquez | D62: =COUNTIF($C$4:$C$53,C62) -> 2 | E62: ='Asignación-Profesor'!D118-D62 -> 2 | F62: =E62+D62 -> 4 | G62: ='Asignación-Profesor'!P118 -> 145 | H62: ='Asignación-Profesor'!Q118 -> 20 | K62: 9:00-14:00 16:00-19:00
B63: 6 | C63: M.S.P. Teófila Enriquez Almaraz | D63: =COUNTIF($C$4:$C$53,C63) -> 2 | E63: ='Asignación-Profesor'!D119-D63 -> 1 | F63: =E63+D63 -> 3 | G63: ='Asignación-Profesor'!P119 -> 77 | H63: ='Asignación-Profesor'!Q119 -> 15 | K63: 9:00-14:00 16:00-19:00
B64: 7 | C64: M.S.P. Felipe de Jesús Parada Luna | D64: =COUNTIF($C$4:$C$53,C64) -> 3 | E64: ='Asignación-Profesor'!D120-D64 -> 2 | F64: =E64+D64 -> 5 | G64: ='Asignación-Profesor'!P120 -> 154 | H64: ='Asignación-Profesor'!Q120 -> 29 | K64: 9:00-14:00 16:00-19:00
B65: 8 | C65: Dra. Maria Dolores Caballero Sánchez | D65: =COUNTIF($C$4:$C$53,C65) -> 2 | E65: ='Asignación-Profesor'!D121-D65 -> 2 | F65: =E65+D65 -> 4 | G65: ='Asignación-Profesor'!P121 -> 143 | H65: ='Asignación-Profesor'!Q121 -> 21 | K65: 9:00-14:00 16:00-19:00
B66: 9 | C66: M.C. Fátima Araceli Ramírez Caballero | K66: LICENCIA
B67: 10 | C67: M.C.S. Olaf Montes de Oca Juárez | K67: LICENCIA
B68: 11 | C68: M.C.B. Aracelí Meneses Corona | K68: SABÁTICO

Sheet LCE
A1: ASIGNACIÓN DE MATERIAS PARA EL SEMESTRE 26-27A
B2: Materia | C2: Profesor asignado | D2: PE-Adscripción | E2: Horas por semana | F2: Número de alumnos
B3: 104
B4: Introducción a las Ciencias Administrativas | C4: M.E.O. Mariano Olvera Ramírez | D4: LCE | E4: 5 | F4: 28 | G4: CEDGE - DO
B5: Informática empresarial | C5: M.T.E. Everardo de Jesús Pacheco Antonio | D5: LI | E5: 5 | F5: 28 | G5: CEDGE, Sala de Cómputo
B6: Matemáticas para ciencias empresariales | C6: M.E. Jorge Lamas Carlos | D6: LCE | E6: 5 | F6: 28 | G6: Aula con mesas, sillas y cañon
B7: Introducción a la contabilidad | C7: L.C. Zayra Trujillo Báez | D7: LCE | E7: 5 | F7: 28 | G7: Aula con mesas, sillas y cañon | H7: Asignar 2 clases de 2 horas y una clase de 1 hora.
B8: Historia del Pensamiento Filosófico | C8: Dra. Maria Guadalupe Temores Alcántara | D8: LCE | E8: 4 | F8: 28
B10: 304
B11: Administración de Recursos Humanos II | C11: Dra. Reyna Minerva Hernández Vásquez | D11: LCE | E11: 5 | F11: 25
B12: Administración de Compras e Inventarios | C12: M.C.P.E.D.R. Elsa A. Mendoza Cortés | D12: LCE | E12: 5 | F12: 25
B13: Estadística Inferencial | C13: Dr. Horacio González Pérez | D13: DEP | E13: 5 | F13: 25
B14: Contabilidad de Costos | C14: M.I.A. Hadya Concepción Díaz Ortíz | D14: LCE | E14: 5 | F14: 25 | G14: No asignar clase a las 16:00
B15: Derecho Mercantil | C15: M.G.P. Rafael Rentería Gaeta | D15: LAP | E15: 5 | F15: 25 | G15: Clase de 8:00 a 9:00
B17: 504
B18: Administración de Sueldos y Salarios | C18: L.C. Zayra Trujillo Báez | D18: LCE | E18: 5 | F18: 15 | G18: Aula con mesas, sillas y cañon | H18: Asignar 2 clases de 2 horas y una clase de 1 hora.
B19: Taller de Metodología de la Investigación | C19: M.E.O. Mariano Olvera Ramírez | D19: LCE | E19: 5 | F19: 15 | G19: CEDGE - DO
B20: Macroeconomía | C20: Dr. Ramón Inzunza Acosta | D20: LCE | E20: 5 | F20: 15 | G20: CEDGE - Sala Computo
B21: Finanzas Empresariales I | C21: M.F. Máximo Jorge Saavedra García | D21: LCE | E21: 5 | F21: 15
B22: Derecho Fiscal | C22: M.E. Benito Güizado Hernández | D22: LAP | E22: 5 | F22: 15
B24: 704
B25: Administración Estratégica de Ventas | C25: M.C.D.R.T. Víctor Santiago Sarmiento | D25: LCE | E25: 5 | F25: 21 | G25: CEDGE - Sala SIG
B26: Investigación de Operaciones | C26: M.E. Jorge Lamas Carlos | D26: LGDM | E26: 5 | F26: 21 | G26: Aula con mesas, sillas y cañon
B27: Economía del Sector Público México | C27: Dr. Ramón Inzunza Acosta | D27: LCE | E27: 5 | F27: 21
B28: Sistema Financiero | C28: M.F. Máximo Jorge Saavedra García | D28: LCE | E28: 5 | F28: 21
B29: Planeación Estratégica | C29: M.I.S. Fabiola Crespo Barrios | D29: LCE | E29: 5 | F29: 21
B31: 904
B32: Cultura Empresarial | C32: M.E.O. Mariano Olvera Ramírez | D32: LCE | E32: 5 | F32: 19 | G32: CEDGE - DO
B33: Emprendimiento de Negocios | C33: M.C.D.R.T. Víctor Santiago Sarmiento | D33: LCE | E33: 5 | F33: 19 | G33: CEDGE - DO
B34: Comercio Exterior | C34: Dr. Ramón Inzunza Acosta | D34: LCE | E34: 5 | F34: 19 | G34: CEDGE - Sala SIG
B35: Finanzas Corporativas | C35: M.I.S. Fabiola Crespo Barrios | D35: LCE | E35: 5 | F35: 19
B36: Gestión de la Calidad | C36: M.I.A. Hadya Concepción Díaz Ortíz | D36: LCE | E36: 5 | F36: 19 | G36: CEDGE - Sala Computo
C47: PROFESORES DE LCE | D47: TOTAL DE MATERIAS | E47: Otras carreras | F47: Total | G47: Total alumnos | H47: Total horas a la semana | I47: Status | J47: Reincorporación | K47: Horario Laboral | L47: Observaciones
B48: 1 | C48: Dr. Pedro Durán Férman | D48: =COUNTIF($C$4:$C$43,C48) -> 0 | E48: ='Asignación-Profesor'!D129-D48 -> 1 | F48: =E48+D48 -> 1 | G48: ='Asignación-Profesor'!P129 -> 0 | H48: ='Asignación-Profesor'!Q129 -> 5 | K48: 09:00 - 14:00 y 16:00 - 19:00
B49: 2 | C49: Dr. Ramón Inzunza Acosta | D49: =COUNTIF($C$4:$C$43,C49) -> 3 | E49: ='Asignación-Profesor'!D130-D49 -> 0 | F49: =E49+D49 -> 3 | G49: ='Asignación-Profesor'!P130 -> 55 | H49: ='Asignación-Profesor'!Q130 -> 15 | K49: 09:00 - 14:00 y 16:00 - 19:00
B50: 3 | C50: M.I.S. Fabiola Crespo Barrios | D50: =COUNTIF($C$4:$C$43,C50) -> 2 | E50: ='Asignación-Profesor'!D131-D50 -> 1 | F50: =E50+D50 -> 3 | G50: ='Asignación-Profesor'!P131 -> 67 | H50: ='Asignación-Profesor'!Q131 -> 15 | K50: 09:00 - 14:00 y 16:00 - 19:00
B51: 4 | C51: M.E.O. Mariano Olvera Ramírez | D51: =COUNTIF($C$4:$C$43,C51) -> 3 | E51: ='Asignación-Profesor'!D132-D51 -> 0 | F51: =E51+D51 -> 3 | G51: ='Asignación-Profesor'!P132 -> 62 | H51: ='Asignación-Profesor'!Q132 -> 15 | K51: 8:00-13:00 y 16:00-19:00
B52: 5 | C52: M.I.A. Hadya Concepción Díaz Ortíz | D52: =COUNTIF($C$4:$C$43,C52) -> 2 | E52: ='Asignación-Profesor'!D133-D52 -> 1 | F52: =E52+D52 -> 3 | G52: ='Asignación-Profesor'!P133 -> 68 | H52: ='Asignación-Profesor'!Q133 -> 15 | K52: 8:00-13:00 y 16:00-19:00 | L52: Asignar clase de 8:00 a 13:00
B53: =B52+1 -> 6 | C53: Dra. Reyna Minerva Hernández Vásquez | D53: =COUNTIF($C$4:$C$43,C53) -> 1 | E53: ='Asignación-Profesor'!D134-D53 -> 3 | F53: =E53+D53 -> 4 | G53: ='Asignación-Profesor'!P134 -> 68 | H53: ='Asignación-Profesor'!Q134 -> 18 | K53: 09:00 - 14:00 y 16:00 - 19:00 | L53: Asignar clases de 12 a 14:00 y de 16:00 a 18:00. En planta baja
B54: =B53+1 -> 7 | C54: L.C. Zayra Trujillo Báez | D54: =COUNTIF($C$4:$C$43,C54) -> 2 | E54: ='Asignación-Profesor'!D135-D54 -> 1 | F54: =E54+D54 -> 3 | G54: ='Asignación-Profesor'!P135 -> 57 | H54: ='Asignación-Profesor'!Q135 -> 15 | K54: 8:00-13:00 y 16:00-19:00
B55: =B54+1 -> 8 | C55: M.C.P.E.D.R. Elsa A. Mendoza Cortés | D55: =COUNTIF($C$4:$C$43,C55) -> 1 | E55: ='Asignación-Profesor'!D136-D55 -> 3 | F55: =E55+D55 -> 4 | G55: ='Asignación-Profesor'!P136 -> 71 | H55: ='Asignación-Profesor'!Q136 -> 17 | K55: 09:00 - 14:00 y 16:00 - 19:00
B56: 9 | C56: M.C.D.R.T. Víctor Santiago Sarmiento | D56: =COUNTIF($C$4:$C$43,C56) -> 2 | E56: ='Asignación-Profesor'!D137-D56 -> 0 | F56: =E56+D56 -> 2 | G56: ='Asignación-Profesor'!P137 -> 40 | H56: ='Asignación-Profesor'!Q137 -> 10 | K56: 8:00-13:00 y 16:00-19:00
B57: =B56+1 -> 10 | C57: M.F. Araceli Luz Alva Rodríguez Martínez | D57: =COUNTIF($C$4:$C$43,C57) -> 0 | E57: ='Asignación-Profesor'!D138-D57 -> 4 | F57: =E57+D57 -> 4 | G57: ='Asignación-Profesor'!P138 -> 70 | H57: ='Asignación-Profesor'!Q138 -> 17 | K57: 8:00-13:00 y 16:00-19:00
B58: =B57+1 -> 11 | C58: M.A. Aurelia Gómez Gómez | D58: =COUNTIF($C$4:$C$43,C58) -> 0 | E58: ='Asignación-Profesor'!D139-D58 -> 4 | F58: =E58+D58 -> 4 | G58: ='Asignación-Profesor'!P139 -> 92 | H58: ='Asignación-Profesor'!Q139 -> 18 | K58: 09:00 - 14:00 y 16:00 - 19:00
B59: =B58+1 -> 12 | C59: M.F. Máximo Jorge Saavedra García | D59: 2 | E59: ='Asignación-Profesor'!D140-D59 -> 1 | F59: =E59+D59 -> 3 | G59: ='Asignación-Profesor'!P140 -> 43 | H59: ='Asignación-Profesor'!Q140 -> 15 | K59: 8:00-13:00 y 16:00-19:00
B60: =B59+1 -> 13 | C60: M.C.P.E.D.R. Marco A. Santos Martínez | I60: Sabático | J60: 24 sept 2027
B61: =B60+1 -> 14 | C61: Dra. Felícitas Ortíz García | I61: 1/2 sabático | J61: 46439

Sheet LI
A1: ASIGNACIÓN DE MATERIAS PARA EL SEMESTRE 26-27A
B2: Materia | C2: Profesor asignado | D2: PE-Adscripción | E2: Horas por semana | F2: Número de alumnos
B3: 106-A PE 2022
B4: Diseño Estructurado de Algoritmos | C4: M.T.E. Everardo de Jesús Pacheco Antonio | D4: LI | E4: 5 | F4: 14
B5: Administración | C5: M.I.S. Fabiola Crespo Barrios | D5: LCE | E5: 5 | F5: 27
B6: Historia del Pensamiento Filosófico | C6: Dr. Guadalupe Gabriel Durán Férman | D6: DEP | E6: 5 | F6: 27
B7: Lógica Matemática | C7: M.C.M. Jesús Pacheco Mendoza | D7: LI | E7: 5 | F7: 14 | G7: El Mtro Pacheco está en la disponibilidad de atender el grupo fusionado al ser de 27 alumnos
B8: Cálculo I | C8: M.C. Enrique García Reyes | D8: LI | E8: 5 | F8: 27 | G8: El Mtro Enrique está en la disponibilidad de atender el grupo fusionado al ser de 27 alumnos
B10: 106-B PE 2022
B11: Diseño Estructurado de Algoritmos | C11: M.C.C Eliezer Álcazar Silva | D11: LI | E11: 5 | F11: 13 | G11: Esta materia es difícil y podría divirse solo para esta materia el grupo
B12: Administración | C12: M.I.S. Fabiola Crespo Barrios * | D12: LCE | E12: 5 | G12: Se une con 106-A
B13: Historia del Pensamiento Filosófico | C13: Dr. Guadalupe Gabriel Durán Férman * | D13: DEP | E13: 5 | G13: Se une con 106-A
B14: Lógica Matemática | C14: M.C.M. Jesús Pacheco Mendoza* | D14: LI | E14: 5 | F14: 13 | G14: Se une con 106-A
B15: Cálculo I | C15: M.C. Enrique García Reyes * | D15: LI | E15: 5 | G15: Se une con 106-A
B17: 306 A PE 2022
B18: Estructuras de Datos | C18: M.C.C. Lirio Ruíz Guerra | D18: LI | E18: 5 | F18: 24
B19: Electrónica Digital | C19: Dr. Amando Alejandro Ruiz Figueroa | D19: LI | E19: 6 | F19: 24
B20: Contabilidad y Finanzas | C20: M.I.A. Hadya Concepción Díaz Ortíz | D20: LCE | E20: 5 | F20: 24 | G20: Asignar Sala de Redes en CETI
B21: Teoría de Autómatas | C21: M.C. Mónica Pérez Meza | D21: LI | E21: 5 | F21: 24 | H21: Podrían haber bajas
B22: Álgebra Lineal | C22: M.C. Enrique García Reyes | D22: LI | E22: 5 | F22: 24
B24: 306 B PE 2022
B25: Estructuras de Datos | E25: 5 | F25: 28
B26: Electrónica Digital | E26: 6 | F26: 28
B27: Contabilidad y Finanzas | E27: 5 | F27: 28
B28: Teoría de Autómatas | E28: 5 | F28: 28
B29: Álgebra Lineal | E29: 5 | F29: 28
B31: 506 PE 2022
B32: Paradigmas de Programación II | C32: M.T.E. Everardo de Jesús Pacheco Antonio | D32: LI | E32: 5 | F32: 21
B33: Redes I | C33: Dr. Arisaí Darío Barragán López | D33: LI | E33: 5 | F33: 21
B34: Bases de Datos II | C34: M.C.C. Lirio Ruíz Guerra | D34: LI | E34: 5 | F34: 21 | H34: Podrían haber bajas
B35: Fundamentos de Sistemas Operativos | C35: M.I.T.I. Oswaldo Rey Ávila Barrón | D35: LI | E35: 5 | F35: 21
B36: Diseño Web | C36: M.C.C Eliezer Álcazar Silva | D36: LI | E36: 5 | F36: 21
B38: 706 PE 2022
B39: Tecnologías Web II | C39: M.T.I.E. Irving Ulises Hernández Miguel | D39: LI | E39: 5 | F39: 16
B40: Derecho y Legislación en Informática | C40: M.T.C.A. Rolando Pedro Gabriel | D40: LI | E40: 5 | F40: 16
B41: Bases de Datos Avanzadas | C41: M.C.C. Lirio Ruíz Guerra | D41: LI | E41: 5 | F41: 16
B42: Ingeniería de Software II | C42: Dr. Jesús Cruz Ahuactzi | D42: LI | E42: 5 | F42: 16
B43: Probabilidad y Estadística | C43: M.C. Enrique García Reyes | D43: LI | E43: 5 | F43: 16
B45: 906 PE 2022
B46: Metodología de la Investigación | C46: Dra. María Alejandra Sánchez Bandala | D46: DEP | E46: 5 | F46: 19
B47: Seguridad de Centros de Informática | C47: Dr. Arisaí Darío Barragán López | D47: LI | E47: 5 | F47: 19
B48: Proyectos de Tecnologías de Información | C48: Dr. Jesús Cruz Ahuactzi | D48: LI | E48: 5 | F48: 19
B49: Opt 1 – Tecnologías de Información I | C49: M.C.C Eliezer Álcazar Silva | D49: LI | E49: 5 | F49: 19
B50: Opt 2 – Inteligencia Artificial I | C50: M.C. Mónica Pérez Meza | D50: LI | E50: 5 | F50: 19
C64: PROFESORES DE LI | D64: TOTAL DE MATERIAS | E64: Otras carreras | F64: Total | G64: Total alumnos | H64: Total horas a la semana | I64: Status | J64: Reincorporación | K64: Horario Laboral | L64: Observaciones
B65: 1 | C65: M.T.I.E. Irving Ulises Hernández Miguel | D65: =COUNTIF($C$4:$C$60,C65) -> 1 | E65: ='Asignación-Profesor'!D146-D65 -> 0 | F65: =E65+D65 -> 1 | G65: ='Asignación-Profesor'!P146 -> 16 | H65: ='Asignación-Profesor'!Q146 -> 5 | K65: 9:00-14:00 y 16:00-19:00 | L65: Clase de 9 a 10
B66: 2 | C66: M.C.C. Lirio Ruíz Guerra | D66: =COUNTIF($C$4:$C$60,C66) -> 3 | E66: ='Asignación-Profesor'!D147-D66 -> 0 | F66: =E66+D66 -> 3 | G66: ='Asignación-Profesor'!P147 -> 61 | H66: ='Asignación-Profesor'!Q147 -> 15 | K66: 8:00-13:00 y 16:00-19:00
B67: 3 | C67: M.C. Mónica Pérez Meza | D67: =COUNTIF($C$4:$C$60,C67) -> 2 | E67: ='Asignación-Profesor'!D148-D67 -> 1 | F67: =E67+D67 -> 3 | G67: ='Asignación-Profesor'!P148 -> 43 | H67: ='Asignación-Profesor'!Q148 -> 15 | K67: 8:00-13:00 y 16:00-19:00
B68: 4 | C68: M.C.A.C. José Alberto Cruz Tolentino | D68: =COUNTIF($C$4:$C$60,C68) -> 0 | E68: ='Asignación-Profesor'!D149-D68 -> 3 | F68: =E68+D68 -> 3 | G68: ='Asignación-Profesor'!P149 -> 96 | H68: ='Asignación-Profesor'!Q149 -> 15 | K68: 8:00-13:00 y 16:00-19:00
B69: -5 | C69: Dra. Aidee Cruz Barragán | D69: =COUNTIF($C$4:$C$60,C69) -> 0 | E69: ='Asignación-Profesor'!D150-D69 -> 3 | F69: =E69+D69 -> 3 | G69: ='Asignación-Profesor'!P150 -> 0 | H69: ='Asignación-Profesor'!Q150 -> 12 | K69: 9:00-14:00 y 16:00-19:00 | L69: Revisa tesis de posgrado, dirección de tesis de posgrado
B70: DI-6 | C70: Dr. Arisaí Darío Barragán López | D70: =COUNTIF($C$4:$C$60,C70) -> 2 | E70: ='Asignación-Profesor'!D151-D70 -> 0 | F70: =E70+D70 -> 2 | G70: ='Asignación-Profesor'!P151 -> 40 | H70: ='Asignación-Profesor'!Q151 -> 10 | K70: 9:00-14:00 y 16:00-19:00 | L70: Revisa tesis de posgrado, dirección de tesis de posgrado
B71: 7 | C71: M.C. Enrique García Reyes | D71: =COUNTIF($C$4:$C$60,C71) -> 3 | E71: ='Asignación-Profesor'!D152-D71 -> 0 | F71: =E71+D71 -> 3 | G71: ='Asignación-Profesor'!P152 -> 67 | H71: ='Asignación-Profesor'!Q152 -> 15 | K71: 8:00-13:00 y 16:00-19:00
B72: 8 | C72: M.I.T.I. Oswaldo Rey Ávila Barrón | D72: =COUNTIF($C$4:$C$60,C72) -> 1 | E72: ='Asignación-Profesor'!D153-D72 -> 2 | F72: =E72+D72 -> 3 | G72: ='Asignación-Profesor'!P153 -> 56 | H72: ='Asignación-Profesor'!Q153 -> 14 | K72: 8:00-13:00 y 16:00-19:00
B73: -9 | C73: Dr. Alejandro Jarillo Silva | D73: =COUNTIF($C$4:$C$60,C73) -> 0 | E73: ='Asignación-Profesor'!D154-D73 -> 3 | F73: =E73+D73 -> 3 | G73: ='Asignación-Profesor'!P154 -> 32 | H73: ='Asignación-Profesor'!Q154 -> 13 | K73: 8:00-13:00 y 16:00-19:00 | L73: Revisa tesis de posgrado, dirección de tesis de posgrado
B74: 10 | C74: M.C.M. Jesús Pacheco Mendoza | D74: =COUNTIF($C$4:$C$60,C74) -> 1 | E74: ='Asignación-Profesor'!D155-D74 -> 2 | F74: =E74+D74 -> 3 | G74: ='Asignación-Profesor'!P155 -> 83 | H74: ='Asignación-Profesor'!Q155 -> 15 | K74: 8:00-13:00 y 16:00-19:00
B75: 11 | C75: Dr. Amando Alejandro Ruiz Figueroa | D75: =COUNTIF($C$4:$C$60,C75) -> 1 | E75: ='Asignación-Profesor'!D156-D75 -> 2 | F75: =E75+D75 -> 3 | G75: ='Asignación-Profesor'!P156 -> 59 | H75: ='Asignación-Profesor'!Q156 -> 16 | K75: 8:00-13:00 y 16:00-19:00
B76: 12 | C76: M.T.E. Everardo de Jesús Pacheco Antonio | D76: =COUNTIF($C$4:$C$60,C76) -> 2 | E76: ='Asignación-Profesor'!D157-D76 -> 1 | F76: =E76+D76 -> 3 | G76: ='Asignación-Profesor'!P157 -> 63 | H76: ='Asignación-Profesor'!Q157 -> 15 | K76: 9:00-14:00 y 16:00-19:00
B77: -13 | C77: Dr. Jesús Cruz Ahuactzi | D77: =COUNTIF($C$4:$C$60,C77) -> 2 | E77: ='Asignación-Profesor'!D158-D77 -> 1 | F77: =E77+D77 -> 3 | G77: ='Asignación-Profesor'!P158 -> 35 | H77: ='Asignación-Profesor'!Q158 -> 14 | K77: 9:00-14:00 y 16:00-19:00 | L77: Revisa tesis de posgrado, dirección de tesis de posgrado
B78: 14 | C78: M.T.C.A. Rolando Pedro Gabriel | D78: =COUNTIF($C$4:$C$60,C78) -> 1 | E78: ='Asignación-Profesor'!D159-D78 -> 2 | F78: =E78+D78 -> 3 | G78: ='Asignación-Profesor'!P159 -> 16 | H78: ='Asignación-Profesor'!Q159 -> 13 | K78: 8:00-13:00 y 16:00-19:00
B79: 15 | C79: M.C.C Eliezer Álcazar Silva | D79: =COUNTIF($C$4:$C$60,C79) -> 3 | E79: ='Asignación-Profesor'!D160-D79 -> 0 | F79: =E79+D79 -> 3 | G79: ='Asignación-Profesor'!P160 -> 53 | H79: ='Asignación-Profesor'!Q160 -> 15 | K79: 9:00-14:00 y 16:00-19:00
B80: 16 | C80: Dr. Arturo Benítez Hernández | I80: Sabático
B81: 17 | C81: Dr. José Javier Hernández Barriga | I81: Sabático
B82: 18 | C82: M.C. Teresita de Jesús Mijangos Martínez | I82: Licencia
B83: 19 | C83: M.C.C. Silviana Juárez Chalini | I83: Licencia
B84: 20 | C84: M.C.M. Oscar Cuauhtémoc Esperanza Contreras | I84: Renunció

Sheet LAP
B2: Materia | C2: Profesor asignado | D2: PE-Adscripción | E2: Horas por semana | F2: Número de alumnos | I2: Aula solicitada | J2: Horario preferente | K2: Observaciones
B3: 105 PE 2024
B4: Introducción al Sistema Jurídico Mexicano | C4: M.E. Benito Güizado Hernández | D4: LAP | E4: 5 | F4: 13 | I4: Sala de Cabildos (CEDGE) | J4: 8:00-9:00 | K4: El Mtro. Benito ya tiene asignadas 4 clases
B5: Fundamentos de la Administración Pública | C5: Dr. Christian Arturo Cruz Meléndez | D5: LAP | E5: 5 | F5: 13 | I5: Sala SIG (CEDGE) | J5: 10:00-11:00
B6: Historia del Pensamiento Filosófico | C6: M.A.P. Diego Toto Jiménez | D6: LAP | E6: 5 | F6: 13 | I6: Aula | J6: 17:00-18:00 | K6: El Mtro. Diego Toto ha impartido HPF
B7: Historia Mundial | C7: Dra. Rocío Bravo Salazar | D7: LAP | E7: 5 | F7: 13 | I7: Sala de Desarrollo Organizacional (CEDGE) | J7: 12:00-13:00
B8: Matemáticas Aplicadas a las Ciencias Sociales | C8: M.E. Jorge Lamas Carlos | D8: LGDM | E8: 5 | F8: 13 | I8: Aula | J8: 9:00-10:00
B10: 305 PE 2024
B11: Derecho Administrativo | C11: M.E. Benito Güizado Hernández | D11: LAP | E11: 5 | F11: 15 | I11: Aula | J11: 10:00-11:00
B12: Microeconomía | C12: Dr. Mauricio Sosa Montes | D12: LAP | E12: 5 | F12: 15 | I12: Aula | J12: 08:00-9:00
B13: Enfoques y Tendencias de la Administración Pública | C13: Dr. Daniel Robles Torres | D13: DEP | E13: 5 | F13: 15 | I13: Aula DEP | J13: 9:00-10:00
B14: Ciencia Política | C14: M.C.P. Rocío Bravo Salazar | D14: LAP | E14: 5 | F14: 15 | I14: Sala de Cabildos (CEDGE) | J14: 11:00-12:00
B15: Gobierno y Asuntos Públicos | C15: M.P.P. Juan Carlos Mata Espinoza | D15: LAP | E15: 5 | F15: 15 | I15: Aula | J15: 17:00-18:00 | K15: El Mtro. Juan Carlos NO ha impartido HPF pero puede apoyar en asignaturas relacionadas con políticas públicas.
B17: 505 PE 2024
B18: Procesos de Gobierno en el Ámbito Municipal | C18: M.C.S. Rosario Maya Lucas | D18: LAP | E18: 5 | F18: 7 | I18: Aula | J18: 12:00-1:00 | K18: 0.70833333 | L18: La Mtra. Daniza ha impartido HPF
B19: Contabilidad Gubernamental | C19: M.C.D.R.T. Lizeth Daniza Gómez Hernández | D19: LAP | E19: 5 | F19: 7 | I19: Sala de Desarrollo Organizacional (CEDGE) | J19: 09:00-10:00
B20: Finanzas Públicas I | C20: M.F. Máximo Jorge Saavedra García | D20: LCE | E20: 5 | F20: 7 | I20: Sala de Cabildos (CEDGE) | J20: 17:00-18:00 | K20: 0.5 | L20: Unir con el grupo 905
B21: Sistemas de Información Geográfica | C21: Dra. Deisy Coromoto Rebolledo López | D21: DEP | E21: 5 | F21: 7 | I21: Sala SIG (CEDGE) | J21: 11:00-12:00 | K21: 0.41666667
B22: Implementación de Políticas Públicas | C22: M.P.P. Juan Carlos Mata Espinoza | D22: LAP | E22: 5 | F22: 7 | I22: Aula | J22: 10:00-11:00 | K22: 0.45833333
B24: 705 PE 2012
B25: Gestión de Recursos Humanos | C25: Dr. Christian Arturo Cruz Meléndez | D25: DEP | E25: 5 | F25: 15 | I25: Aula DEP | J25: 10:00-11:00
B26: Políticas Públicas II | C26: M.P.P. Juan Carlos Mata Espinoza | D26: LAP | E26: 5 | F26: 15 | I26: Sala SIG (CEDGE) | J26: 12:00- 1:00 | K26: 0.375
B27: Sistemas de Auditoría Gubernamental | C27: M.C.D.R.T. Lizeth Daniza Gómez Hernández | D27: LAP | E27: 5 | F27: 15 | I27: Aula | J27: 17:00-18:00
B28: Procesos de Gobierno en México (Ámbito Federal) | C28: M.E. Benito Güizado Hernández | D28: LAP | E28: 5 | F28: 15 | I28: Sala de Cabildos (CEDGE) | J28: 9:00-10:00 | K28: 0.5
B29: Gerencia Social | C29: Dra. Alicia Martínez Cruz | D29: LAP | E29: 4 | F29: 15 | I29: Aula | J29: 11:00 -12:00
B31: 905 PE 2012
B32: Ética y Rendición de Cuentas Públicas | C32: M.P.P. Juan Carlos Mata Espinoza | D32: DEP | E32: 4 | F32: 15 | I32: Aula DEP | J32: 10:00-11:00 | K32: Se programaron todas las materias por la mañana para que los alumnos puedan avanzar con su servicio social para evitar que en décimo semestre se saturen con las materias y las tesis.
B33: Planeación Estratégica | C33: M.A.E. Enrique Martínez Sánchez | D33: LAP | E33: 4 | F33: 15 | I33: Sala Cabildo (CEDGE) | J33: 12:00 - 1:00 | K33: 0.375
B34: Gestión y Administración Urbana | C34: Dr. Omar Ávila Flores | D34: LGDM | E34: 4 | F34: 15 | I34: Sala SIG (CEDGE) | J34: 8:00-9:00 | K34: Los alumnos podrían tomar inglés de 4:00 a 5:00 y biblioteca de 1:00 a 2:00
B35: Procesos de Gobierno en México (Ámbito Municipal) | C35: Dr. Arturo César López García | D35: LGDM | E35: 4 | F35: 15 | I35: Sala Cabildo (CEDGE) | J35: 11:00 - 12:00 | K35: Sala de Cabildos, asignar clase por la mañana
B36: Seminario de Tesis I | C36: Dr. Mauricio Sosa Montes | D36: LAP | E36: 5 | F36: 15 | I36: Aula | J36: 09:00-10:00
C49: PROFESORES DE LAP | D49: TOTAL DE MATERIAS | E49: Otras carreras | F49: Total | G49: Total alumnos | H49: Total horas a la semana | I49: Total alumnos | J49: Total horas a la semana | K49: Status | L49: Reincorporación | M49: Horario Laboral | N49: Observaciones
B50: 1 | C50: M.G.P. Rafael Rentería Gaeta | D50: =COUNTIF($C$5:$C$45,C50) -> 0 | E50: ='Asignación-Profesor'!D169-D50 -> 1 | F50: =E50+D50 -> 1 | I50: ='Asignación-Profesor'!P169 -> 25 | J50: ='Asignación-Profesor'!Q169 -> 5 | M50: 08:00 - 13:00 y 16:00 - 19:00
B51: 2 | C51: M.A.E. Enrique Martínez Sánchez | D51: =COUNTIF($C$5:$C$45,C51) -> 1 | E51: ='Asignación-Profesor'!D170-D51 -> 0 | F51: =E51+D51 -> 1 | I51: ='Asignación-Profesor'!P170 -> 15 | J51: ='Asignación-Profesor'!Q170 -> 4 | K51: Coordinación UNSIS Evaluación SEAES | M51: 09:00 - 14:00 y 16:00 - 19:00
B52: 3 | C52: Dra. Alicia Martínez Cruz | D52: =COUNTIF($C$5:$C$45,C52) -> 1 | E52: 1 | F52: =E52+D52 -> 2 | I52: 28 | J52: 10 | K52: Comisión de Planes Micro-Regional y Municipales | M52: 09:00 - 14:00 y 16:00 - 19:00 | N52: Comisión de Planes
B53: 4 | C53: M.A.P. Diego Toto Jiménez | D53: 1 | E53: 3 | F53: =E53+D53 -> 4 | I53: ='Asignación-Profesor'!P172 -> 48 | J53: ='Asignación-Profesor'!Q172 -> 9 | M53: 09:00 - 14:00 y 16:00 - 19:00
B54: 5 | C54: M.C.D.R.T. Lizeth Daniza Gómez Hernández | D54: =COUNTIF($C$5:$C$45,C54) -> 1 | E54: ='Asignación-Profesor'!D173-D54 -> 3 | F54: =E54+D54 -> 4 | I54: 22 | J54: 10 | M54: 09:00 - 14:00 y 16:00 - 19:00
B55: 6 | C55: M.P.P. Juan Carlos Mata Espinoza | D55: =COUNTIF($C$5:$C$45,C55) -> 4 | E55: ='Asignación-Profesor'!D174-D55 -> 0 | F55: =E55+D55 -> 4 | I55: 37 | J55: 15 | M55: 09:00 - 14:00 y 16:00 - 19:00
C56: Dra. Nina Martínez Cruz | D56: =COUNTIF($C$5:$C$45,C56) -> 0 | E56: ='Asignación-Profesor'!D175-D56 -> 1 | F56: =E56+D56 -> 1 | I56: 15 | J56: ='Asignación-Profesor'!Q175 -> 4 | K56: Comisión de Planes Micro-Regional y Municipales | M56: 09:00 - 14:00 y 16:00 - 19:00 | N56: Comisión de Planes
B57: 8 | C57: Dr. Mauricio Sosa Montes | D57: =COUNTIF($C$5:$C$45,C57) -> 2 | E57: ='Asignación-Profesor'!D176-D57 -> 1 | F57: =E57+D57 -> 3 | I57: 30 | J57: 10 | M57: 09:00 - 14:00 y 16:00 - 19:00 | N57: Proyectos de investigación (protocolos) de los alumnos de del Grupo 905 y requiere tiempo para asesorías.
B58: 9 | C58: Dra. Rocío Bravo Salazar | D58: 2 | E58: 0 | F58: =E58+D58 -> 2 | I58: 28 | J58: 10 | K58: Comisión de Planes Micro-Regional y Municipales | M58: 08:00 - 13:00 y 16:00 - 19:00 | N58: Comisión de Planes
B59: 10 | C59: M.E. Benito Güizado Hernández | D59: 3 | E59: 1 | F59: =E59+D59 -> 4 | I59: ='Asignación-Profesor'!P178 -> 58 | J59: ='Asignación-Profesor'!Q178 -> 20 | K59: Coordinación LAP Evaluación SEAES | M59: 08:00 - 13:00 y 16:00 - 19:00
B60: 11 | C60: M.A.I.A Abisaí Aragón Cruz | D60: 0 | E60: 0 | F60: =E60+D60 -> 0 | I60: 13 | J60: 5 | K60: Solicitó 1/2 sabático a partir del 03 de octubre | M60: 08:00 - 13:00 y 16:00 - 19:00
B61: 12 | C61: Dr. Roberto García Zúñiga | D61: =COUNTIF($C$5:$C$45,C61) -> 0 | E61: ='Asignación-Profesor'!D180-D61 -> 0 | F61: =E61+D61 -> 0 | I61: ='Asignación-Profesor'!P180 | J61: ='Asignación-Profesor'!Q180 | K61: 1/2 Sábatico | L61: 20 de Febrero 2027 | M61: 09:00 - 14:00 y 16:00 - 19:00

Sheet LGDM
A1: ASIGNACIÓN DE MATERIAS PARA EL SEMESTRE 26-27A
B2: Materia | C2: Profesor asignado | D2: PE-Adscripción | E2: Horas por semana | F2: Número de alumnos
B3: 117 | G3: Horarios/Ejemplo:
B4: Fundamentos de la Administración Pública | C4: M.C.P. Joann Etienne Olivier Picard | D4: LGDM | E4: 5 | F4: 14 | G4: 09:00-10:00 | H4: Sala SIG
B5: Historia y Cultura de los Pueblos Originarios | C5: Dr. Joaquín Huitzilihuitl Camacho Vera | D5: DEP | E5: 5 | F5: 14 | G5: 13:00-14:00 | H5: Aula con mesas, sillas y cañon en DEP
B6: Contabilidad I | C6: L.C. Zayra Trujillo Báez | D6: LCE | E6: 5 | F6: 14 | G6: 11:00-12:00 | H6: Aula con mesas, sillas y cañon
B7: Matemáticas Aplicadas a las Ciencias Sociales | C7: M.E. Jorge Lamas Carlos | D7: LGDM | E7: 5 | F7: 14 | G7: 08:00-09:00 | H7: Aula con mesas, sillas y cañon
B8: Historia del Pensamiento Filosófico | C8: M.D.G.P.L. Eleazar Brena García | D8: LGDM | E8: 5 | F8: 14 | G8: 12:00-13:00 | H8: por la mañana, sin preferencia de aulas
G10: 10:00-11:00 | H10: Asesoría
C21: PROFESORES DE LAP | D21: TOTAL DE MATERIAS | E21: Otras carreras | F21: Total | G21: Total alumnos | H21: Total horas a la semana | I21: Status | J21: Reincorporación | K21: Horario Laboral
B22: 1 | C22: M.C.P. Joann Etienne Olivier Picard | D22: =COUNTIF($C$4:$C$19,C22) -> 1 | E22: 0 | F22: =E22+D22 -> 1 | G22: ='Asignación-Profesor'!P184 -> 15 | H22: ='Asignación-Profesor'!Q184 -> 5 | K22: 09:00-14:00 / 16:00-19:00
B23: 2 | C23: M.P.E.M. Emanuel Lorenzo Ramírez Arellanes | D23: =COUNTIF($C$4:$C$19,C23) -> 0 | E23: ='Asignación-Profesor'!D185-D23 -> 2 | F23: =E23+D23 -> 2 | G23: ='Asignación-Profesor'!P185 -> 4 | H23: ='Asignación-Profesor'!Q185 -> 9 | I23: Comisión de Planes Micro-Regional y Municipales | K23: 09:00-14:00 / 16:00-19:00
B24: 3 | C24: M.C.S. Rosario Maya Lucas | D24: 0 | E24: 2 | F24: =E24+D24 -> 2 | G24: ='Asignación-Profesor'!P186 -> 7 | H24: 10 | I24: Comisión de Planes Micro-Regional y Municipales | K24: 09:00-14:00 / 16:00-19:00
B25: 4 | C25: M.D.G.P.L. Eleazar Brena García | D25: =COUNTIF($C$4:$C$19,C25) -> 1 | E25: ='Asignación-Profesor'!D187-D25 -> 2 | F25: =E25+D25 -> 3 | G25: ='Asignación-Profesor'!P187 -> 23 | H25: ='Asignación-Profesor'!Q187 -> 15 | I25: Comisión SEAES | K25: 09:00-14:00 / 16:00-19:00
B26: 5 | C26: M.E. Jorge Lamas Carlos | D26: =COUNTIF($C$4:$C$19,C26) -> 1 | E26: ='Asignación-Profesor'!D188-D26 -> 4 | F26: =E26+D26 -> 5 | G26: ='Asignación-Profesor'!P188 -> 80 | H26: ='Asignación-Profesor'!Q188 -> 25 | K26: 08:00-13:00 / 16:00-19:00 | L26: poner todas las clases en la mañana
B27: 6 | C27: Dr. Arturo César López García | D27: =COUNTIF($C$4:$C$19,C27) -> 0 | E27: ='Asignación-Profesor'!D189-D27 -> 2 | F27: =E27+D27 -> 2 | G27: ='Asignación-Profesor'!P189 -> 20 | H27: ='Asignación-Profesor'!Q189 -> 9 | I27: SNII - Nivel 1, Comisión de Planes Micro-Regional y Municipales | K27: 09:00-14:00 / 16:00-19:00
B28: 7 | C28: Dr. Omar Ávila Flores | D28: =COUNTIF($C$4:$C$19,C28) -> 0 | E28: ='Asignación-Profesor'!D190-D28 -> 3 | F28: =E28+D28 -> 3 | G28: ='Asignación-Profesor'!P190 -> 24 | H28: ='Asignación-Profesor'!Q190 -> 14 | I28: SNII - Nivel 1, Dirección de tesis de doctorado y licenciatura | K28: 08:00-13:00 / 16:00-19:00

Sheet LAM
A1: ASIGNACIÓN DE MATERIAS PARA EL SEMESTRE 26-27A
B2: Materia | C2: Profesor asignado | D2: PE-Adscripción | E2: Horas por semana | F2: Número de alumnos
B3: 701
B4: Auditoría Gubernamental | D4: LGDM | E4: 5 | F4: 4
B5: Sustentabilidad y Gestión Local | C5: M.D.G.P.L. Eleazar Brena García | D5: LGDM | E5: 5 | F5: 4 | G5: asignar clase por la mañana
B6: Metodología de la Investigación Cuantitativa | C6: M.E. Jorge Lamas Carlos | D6: LGDM | E6: 5 | F6: 4 | G6: asignar clase por la mañana
B7: Planeación, Programación y Presupuesto | C7: M.P.E.M. Emanuel Lorenzo Ramírez Arellanes | D7: LGDM | E7: 5 | F7: 4 | G7: Sala de Cabildos, asignar clase por la mañana
B8: Desarrollo Urbano | C8: Dr. Omar Ávila Flores | D8: LGDM | E8: 5 | F8: 4 | G8: Sala de Cabildos, asignar clase por la mañana
B10: 901
B11: Administración de Obras Públicas | C11: Dr. Omar Ávila Flores | D11: LGDM | E11: 5 | F11: 5 | G11: Sala de Cabildos, asignar clase por la mañana
B12: Administración de Servicios Públicos Municipales | C12: Dr. Oscar David Valencia López | D12: DEP | E12: 5 | F12: 5 | G12: en DEP
B13: Sistemas de Evaluación y Seguimiento | C13: Dr. Arturo César López García | D13: LGDM | E13: 5 | F13: 5 | G13: Sala de Cabildos, asignar clase por la mañana
B14: Formulación y Evaluación de Proyectos de Inversión | C14: M.D.G.P.L. Eleazar Brena García | D14: LGDM | E14: 5 | F14: 5 | G14: asignar clase por la mañana
B15: Taller de Redacción de Tesis I | C15: Dr. Jose Rudier López Hernández | D15: DEP | E15: 5 | F15: 5 | G15: asignar clase por la mañana, en DEP

Sheet DEP
A1: ASIGNACIÓN DE MATERIAS PARA EL SEMESTRE 26-27A
B2: Materia | C2: Profesor asignado | D2: PE-Adscripción | E2: Horas por semana | F2: Número de alumnos
B3: MPEM 108
B4: Fundamentos, Métodos y Técnicas de Planeación | C4: M.P.E.M. Emanuel Lorenzo Ramírez Arellanes | D4: LGDM | E4: 4 | F4: asignar clase por la mañana
B5: Teoría del Desarrollo | C5: Dr. Jose Rudier López Hernández | D5: DEP | E5: 4
B6: Teoría y Marco Jurídico del Municipio | C6: M.C.S. Rosario Maya Lucas | D6: LGDM | E6: 4
B7: Estadística para las Ciencias Sociales | C7: Dr. Horacio González Pérez | D7: DEP | E7: 4
B8: Taller de Tesis I: Protocolo de Investigación | C8: Dr. Guadalupe Gabriel Durán Férman | D8: DEP | E8: 4
B10: MPEM 308
B11: Diagnóstico Municipal para la Planeación | C11: Dra. Nina Martínez Cruz | D11: LAP | E11: 4
B12: Ordenamiento Territorial Sostenible | C12: Dra. Deisy Coromoto Rebolledo López | D12: DEP | E12: 4
B13: Análisis de Información de Campo | C13: Dr. Joaquín Huitzilihuitl Camacho Vera | D13: DEP | E13: 4
B14: OPT1 Gestión de proyectos de Innovación Social en el Municipio | C14: Dr. Daniel Robles Torres | E14: 4
B16: MSP 109 - PE2026
B17: Demografia y salud pública | C17: Dra. Maria Dolores Caballero Sánchez* | D17: LN | E17: 4
B18: Salud, Sociedad y Derechos Humanos | C18: Dra. Maria Guadalupe Temores Alcántara | D18: DEP | E18: 4
B19: Epidemiología I | C19: Dr. José Eduardo Orellana Centeno | D19: LO | E19: 4
B20: Bioestadística I | C20: Dr. Alejandro Jarillo Silva | D20: LI | E20: 4
B21: Metodología de la Investigación Científica | C21: Dra. Araceli Hernández Flores | D21: DEP | E21: 4
B22: Metodología de la Investigación Cualitativa | C22: Dra. María Alejandra Sánchez Bandala | D22: DEP | E22: 4
B24: MSP 309 - PE2016
B25: Políticas de Salud | C25: M.S.P. Teófila Enriquez Almaraz | D25: LN | E25: 4
B26: Seminario de Investigación | C26: Dr. Roberto Ariel Abeldaño Zúñiga | D26: DEP | E26: 4
B27: OPT-Farmacología Regional y Salud Pública | C27: Dr. Hady Keita | D27: DEP | E27: 4
B28: OPT-Enfermedades transmitidas por vector | C28: Dra. Lilian Arzeta Pino | E28: 4
B30: MGE 110 - PE2026
B31: Gobierno Electrónico y Administración Pública | C31: Dr. Christian Arturo Cruz Meléndez | D31: DEP | E31: 4
B32: Derecho Digital y Protección de Datos | C32: Dr. Gerardo Roberto Aragón Gonzalez | D32: LE | E32: 4
B33: Interoperabilidad y Privacidad en la Administración Digital | C33: Dra. Aidee Cruz Barragán | D33: LI | E33: 4
B34: Gobernanza Digital y Ética Pública | C34: Dr. Oscar David Valencia López | D34: DEP | E34: 4
B35: Investigación en Ciencias Sociales | C35: Dr. Diego Soto Hernández | D35: DEP | E35: 4
B37: DGE 111
B38: Gestión y Administración Pública Electrónico | C38: Dr. Joselito Fernández Tapia | D38: DEP | E38: 4
B39: Sistemas para la Toma de Decisiones en Gobierno Elcetrónico | C39: Dr. Jesús Cruz Ahuactzi | D39: LI | E39: 4
B40: Marco Juridico e Institucional de Gobierno Electrónico | C40: Dr. Oscar David Valencia López | D40: DEP | E40: 4
B41: Metodologia de la Investigación I | C41: Dr. Daniel Robles Torres | D41: DEP | E41: 4
B43: DGE 311
B44: Finanzas Públicas y Gobierno Electrónico | C44: Dr. Diego Soto Hernández | D44: DEP | E44: 4
B45: Aplicaciones Web y Móviles para Gobierno Electrónico | C45: Dra. Aidee Cruz Barragán | D45: LI | E45: 4
B46: Gestión de Proyectos Tecnológicos de Gobierno Electrónico | C46: Dr. Alejandro Jarillo Silva | D46: LI | E46: 4
B47: Tesis Doctoral I | C47: Dra. Alicia Martínez Cruz | D47: DEP | E47: 4
B49: DGE 511
B50: Tesis Doctoral III | C50: Dr. Diego Soto Hernández | D50: DEP | E50: 4
B51: Optativa II Ciudades Inteligentes desde la Perspectiva del Gobierno Electrónico | C51: Dr. Joselito Fernández Tapia | D51: DEP | E51: 6
C64: PROFESORES DE DEP | D64: TOTAL DE MATERIAS | E64: Otras carreras | F64: Total | G64: Total alumnos | H64: Total horas a la semana | I64: Status | J64: Reincorporación | K64: Horario Laboral
B65: 1 | C65: Dra. Araceli Hernández Flores | D65: =COUNTIF($C$40:$C$61,C65) -> 0 | E65: ='Asignación-Profesor'!D194-D65 -> 1 | F65: =E65+D65 -> 1 | G65: ='Asignación-Profesor'!P194 -> 0 | H65: ='Asignación-Profesor'!Q194 -> 4 | K65: 9-14 Y 16-19
B66: 2 | C66: Dr. Guadalupe Gabriel Durán Férman | D66: =COUNTIF($C$40:$C$61,C66) -> 0 | E66: ='Asignación-Profesor'!D195-D66 -> 3 | F66: =E67+D67 -> 2 | G66: ='Asignación-Profesor'!P195 -> 62 | H66: ='Asignación-Profesor'!Q195 -> 13 | K66: 9-14 Y 16-19
B67: 3 | C67: Dr. Joaquín Huitzilihuitl Camacho Vera | D67: =COUNTIF($C$40:$C$61,C67) -> 0 | E67: ='Asignación-Profesor'!D196-D67 -> 2 | F67: =E68+D68 -> 0 | G67: ='Asignación-Profesor'!P196 -> 14 | H67: ='Asignación-Profesor'!Q196 -> 9 | K67: 9-14 Y 16-19 | M67: clases por la mañana
B68: 4 | C68: Dr. Daniel Robles Torres | D68: =COUNTIF($C$40:$C$61,C68) -> 1 | E68: ='Asignación-Profesor'!D197-D68 -> -1 | F68: =E69+D69 -> 3 | G68: ='Asignación-Profesor'!P197 -> 0 | H68: ='Asignación-Profesor'!Q197 -> 0 | K68: 9-14 Y 16-19
B69: 5 | C69: Dr. Christian Arturo Cruz Meléndez | D69: =COUNTIF($C$40:$C$61,C69) -> 0 | E69: ='Asignación-Profesor'!D198-D69 -> 3 | F69: =E70+D70 -> 4 | G69: ='Asignación-Profesor'!P198 -> 28 | H69: ='Asignación-Profesor'!Q198 -> 14 | K69: 9-14 Y 16-19
B70: 6 | C70: Dr. Horacio González Pérez | D70: =COUNTIF($C$40:$C$61,C70) -> 0 | E70: ='Asignación-Profesor'!D199-D70 -> 4 | F70: =E71+D71 -> 3 | G70: ='Asignación-Profesor'!P199 -> 25 | H70: ='Asignación-Profesor'!Q199 -> 19 | K70: 9-14 Y 16-19
B71: 7 | C71: Dra. María Alejandra Sánchez Bandala | D71: =COUNTIF($C$40:$C$61,C71) -> 0 | E71: ='Asignación-Profesor'!D200-D71 -> 3 | F71: =E71+D71 -> 3 | G71: ='Asignación-Profesor'!P200 -> 51 | H71: ='Asignación-Profesor'!Q200 -> 14 | K71: 8-13 Y 16-19 | M71: clases por la mañana coordinadora de la MSP
B72: 8 | C72: Dr. Roberto Ariel Abeldaño Zúñiga | D72: =COUNTIF($C$40:$C$61,C72) -> 0 | E72: ='Asignación-Profesor'!D201-D72 -> 1 | F72: =E72+D72 -> 1 | G72: ='Asignación-Profesor'!P201 -> 0 | H72: ='Asignación-Profesor'!Q201 -> 4 | K72: 9-14 Y 16-19
B73: 9 | C73: Dr. Diego Soto Hernández | D73: =COUNTIF($C$40:$C$61,C73) -> 2 | E73: ='Asignación-Profesor'!D202-D73 -> 1 | F73: =E73+D73 -> 3 | G73: ='Asignación-Profesor'!P202 -> 0 | H73: ='Asignación-Profesor'!Q202 -> 12 | K73: 9-14 Y 16-19 | M73: clases por la mañana coordinador de la MGE
B74: 10 | C74: Dra. Deisy Coromoto Rebolledo López | D74: =COUNTIF($C$40:$C$61,C74) -> 0 | E74: ='Asignación-Profesor'!D203-D74 -> 3 | F74: =E74+D74 -> 3 | G74: ='Asignación-Profesor'!P203 -> 7 | H74: ='Asignación-Profesor'!Q203 -> 14 | K74: 9-14 Y 16-19
B75: 11 | C75: Dr. Hady Keita | D75: =COUNTIF($C$40:$C$61,C75) -> 0 | E75: ='Asignación-Profesor'!D204-D75 -> 3 | F75: =E75+D75 -> 3 | G75: ='Asignación-Profesor'!P204 -> 80 | H75: ='Asignación-Profesor'!Q204 -> 14 | K75: 9-14 Y 16-19
B76: 12 | C76: Dr. Joselito Fernández Tapia | D76: =COUNTIF($C$40:$C$61,C76) -> 1 | E76: ='Asignación-Profesor'!D205-D76 -> 2 | F76: =E76+D76 -> 3 | G76: ='Asignación-Profesor'!P205 -> 0 | H76: ='Asignación-Profesor'!Q205 -> 15 | K76: 8-13 Y 16-19
B77: 13 | C77: Dr. Oscar David Valencia López | D77: =COUNTIF($C$40:$C$61,C77) -> 1 | E77: ='Asignación-Profesor'!D206-D77 -> 2 | F77: =E77+D77 -> 3 | G77: ='Asignación-Profesor'!P206 -> 5 | H77: ='Asignación-Profesor'!Q206 -> 13 | K77: 9-14 Y 16-19 | M77: clases por la mañana coordinador del DGE
B78: 14 | C78: Dr. Jose Rudier López Hernández | D78: =COUNTIF($C$40:$C$61,C78) -> 0 | E78: ='Asignación-Profesor'!D207-D78 -> 2 | F78: =E78+D78 -> 2 | G78: ='Asignación-Profesor'!P207 -> 5 | H78: ='Asignación-Profesor'!Q207 -> 9 | K78: 9-14 Y 16-19 | M78: clases por la mañana coordinador de la MPEM
B79: 15 | C79: Dra. Maria Guadalupe Temores Alcántara | D79: =COUNTIF($C$40:$C$61,C79) -> 0 | E79: ='Asignación-Profesor'!D208-D79 -> 4 | F79: =E79+D79 -> 4 | G79: ='Asignación-Profesor'!P208 -> 28 | H79: ='Asignación-Profesor'!Q208 -> 16 | K79: 9-14 Y 16-19

Sheet Asignación-Profesor
B2: LCB | C2: Profesor@ | D2: Materias | E2: LCB | F2: LM | G2: LO | H2: LE | I2: LN | J2: LCE | K2: LI | L2: LAP | M2: LGDM | N2: LAM | O2: DEP | P2: Total alumnos | Q2: Total hrs sem | R2: Observaciones
B3: 1 | C3: M.B.E. Raúl Misael Cortés Olivera | D3: =SUM(E3:O3) -> 1 | E3: =COUNTIF(LCB!$C$4:$C$40,C3) -> 1 | F3: =COUNTIF(LM!$C$4:$C$144,C3) -> 0 | G3: =COUNTIF(LO!$C$4:$C$227,C3) -> 0 | H3: =COUNTIF(LE!$C$4:$C$214,C3) -> 0 | I3: =COUNTIF(LN!$C$4:$C$53,C3) -> 0 | J3: =COUNTIF(LCE!$C$3:$C$43,C3) -> 0 | K3: =COUNTIF(LI!$C$4:$C$60,C3) -> 0 | L3: =COUNTIF(LAP!$C$5:$C$45,C3) -> 0 | M3: =COUNTIF(LGDM!$C$4:$C$22,C3) -> 0 | N3: =COUNTIF(LAM!$C$5:$C$21,C3) -> 0 | O3: =COUNTIF(DEP!$C$3:$C$61,C3) -> 0 | P3: =SUMIF(LCB!$C$4:$C$45,C3,LCB!$F$4:$F$45)+SUMIF(LM!$C$4:$C$140,C3,LM!$F$4:$F$140)+SUMIF(LO!$C$4:$C$230,C3,LO!$F$4:$F$230)+SUMIF(LE!$C$4:$C$200,C3,LE!$F$4:$F$200)+SUMIF(LN!$C$4:$C$48,C3,LN!$F$4:$F$48)+SUMIF(LCE!$C$4:$C$40,C3,LCE!$F$4:$F$40)+SUMIF(LI!$C$4:$C$55,C3,LI!$F$4:$F$55)+SUMIF(LAP!$C$4:$C$45,C3,LAP!$F$4:$F$45)+SUMIF(LGDM!$C$4:$C$22,C3,LGDM!$F$4:$F$22)+SUMIF(LAM!$C$4:$C$18,C3,LAM!$F$4:$F$18)+SUMIF(DEP!$C$4:$C$55,C3,DEP!$F$4:$F$55) -> 0 | Q3: =SUMIF(LCB!$C$4:$C$45,C3,LCB!$E$4:$E$45)+SUMIF(LM!$C$4:$C$140,C3,LM!$E$4:$E$140)+SUMIF(LO!$C$4:$C$230,C3,LO!$E$4:$E$230)+SUMIF(LE!$C$4:$C$200,C3,LE!$E$4:$E$200)+SUMIF(LN!$C$4:$C$48,C3,LN!$E$4:$E$48)+SUMIF(LCE!$C$4:$C$40,C3,LCE!$E$4:$E$40)+SUMIF(LI!$C$4:$C$55,C3,LI!$E$4:$E$55)+SUMIF(LAP!$C$4:$C$45,C3,LAP!$E$4:$E$45)+SUMIF(LGDM!$C$4:$C$15,C3,LGDM!$E$4:$E$15)+SUMIF(LAM!$C$5:$C$18,C3,LAM!$E$5:$E$18)+SUMIF(DEP!$C$4:$C$55,C3,DEP!$E$4:$E$55) -> 6
B4: 2 | C4: M.C.C.A.R.B. Guilibaldo Gabriel Zurita Vásquez | D4: =SUM(E4:O4) -> 3 | E4: =COUNTIF(LCB!$C$4:$C$40,C4) -> 0 | F4: =COUNTIF(LM!$C$4:$C$144,C4) -> 3 | G4: =COUNTIF(LO!$C$4:$C$227,C4) -> 0 | H4: =COUNTIF(LE!$C$4:$C$214,C4) -> 0 | I4: =COUNTIF(LN!$C$4:$C$53,C4) -> 0 | J4: =COUNTIF(LCE!$C$3:$C$43,C4) -> 0 | K4: =COUNTIF(LI!$C$4:$C$60,C4) -> 0 | L4: =COUNTIF(LAP!$C$5:$C$45,C4) -> 0 | M4: =COUNTIF(LGDM!$C$4:$C$22,C4) -> 0 | N4: =COUNTIF(LAM!$C$5:$C$21,C4) -> 0 | O4: =COUNTIF(DEP!$C$3:$C$61,C4) -> 0 | P4: =SUMIF(LCB!$C$4:$C$45,C4,LCB!$F$4:$F$45)+SUMIF(LM!$C$4:$C$140,C4,LM!$F$4:$F$140)+SUMIF(LO!$C$4:$C$230,C4,LO!$F$4:$F$230)+SUMIF(LE!$C$4:$C$200,C4,LE!$F$4:$F$200)+SUMIF(LN!$C$4:$C$48,C4,LN!$F$4:$F$48)+SUMIF(LCE!$C$4:$C$40,C4,LCE!$F$4:$F$40)+SUMIF(LI!$C$4:$C$55,C4,LI!$F$4:$F$55)+SUMIF(LAP!$C$4:$C$45,C4,LAP!$F$4:$F$45)+SUMIF(LGDM!$C$4:$C$22,C4,LGDM!$F$4:$F$22)+SUMIF(LAM!$C$4:$C$18,C4,LAM!$F$4:$F$18)+SUMIF(DEP!$C$4:$C$55,C4,DEP!$F$4:$F$55) -> 126 | Q4: =SUMIF(LCB!$C$4:$C$45,C4,LCB!$E$4:$E$45)+SUMIF(LM!$C$4:$C$140,C4,LM!$E$4:$E$140)+SUMIF(LO!$C$4:$C$230,C4,LO!$E$4:$E$230)+SUMIF(LE!$C$4:$C$200,C4,LE!$E$4:$E$200)+SUMIF(LN!$C$4:$C$48,C4,LN!$E$4:$E$48)+SUMIF(LCE!$C$4:$C$40,C4,LCE!$E$4:$E$40)+SUMIF(LI!$C$4:$C$55,C4,LI!$E$4:$E$55)+SUMIF(LAP!$C$4:$C$45,C4,LAP!$E$4:$E$45)+SUMIF(LGDM!$C$4:$C$15,C4,LGDM!$E$4:$E$15)+SUMIF(LAM!$C$5:$C$18,C4,LAM!$E$5:$E$18)+SUMIF(DEP!$C$4:$C$55,C4,DEP!$E$4:$E$55) -> 18
B5: 3 | C5: M.C.I.B. Ericay Berenice Martínez Ramos | D5: =SUM(E5:O5) -> 4 | E5: =COUNTIF(LCB!$C$4:$C$40,C5) -> 1 | F5: =COUNTIF(LM!$C$4:$C$144,C5) -> 0 | G5: =COUNTIF(LO!$C$4:$C$227,C5) -> 0 | H5: =COUNTIF(LE!$C$4:$C$214,C5) -> 3 | I5: =COUNTIF(LN!$C$4:$C$53,C5) -> 0 | J5: =COUNTIF(LCE!$C$3:$C$43,C5) -> 0 | K5: =COUNTIF(LI!$C$4:$C$60,C5) -> 0 | L5: =COUNTIF(LAP!$C$5:$C$45,C5) -> 0 | M5: =COUNTIF(LGDM!$C$4:$C$22,C5) -> 0 | N5: =COUNTIF(LAM!$C$5:$C$21,C5) -> 0 | O5: =COUNTIF(DEP!$C$3:$C$61,C5) -> 0 | P5: =SUMIF(LCB!$C$4:$C$45,C5,LCB!$F$4:$F$45)+SUMIF(LM!$C$4:$C$140,C5,LM!$F$4:$F$140)+SUMIF(LO!$C$4:$C$230,C5,LO!$F$4:$F$230)+SUMIF(LE!$C$4:$C$200,C5,LE!$F$4:$F$200)+SUMIF(LN!$C$4:$C$48,C5,LN!$F$4:$F$48)+SUMIF(LCE!$C$4:$C$40,C5,LCE!$F$4:$F$40)+SUMIF(LI!$C$4:$C$55,C5,LI!$F$4:$F$55)+SUMIF(LAP!$C$4:$C$45,C5,LAP!$F$4:$F$45)+SUMIF(LGDM!$C$4:$C$22,C5,LGDM!$F$4:$F$22)+SUMIF(LAM!$C$4:$C$18,C5,LAM!$F$4:$F$18)+SUMIF(DEP!$C$4:$C$55,C5,DEP!$F$4:$F$55) -> 0 | Q5: =SUMIF(LCB!$C$4:$C$45,C5,LCB!$E$4:$E$45)+SUMIF(LM!$C$4:$C$140,C5,LM!$E$4:$E$140)+SUMIF(LO!$C$4:$C$230,C5,LO!$E$4:$E$230)+SUMIF(LE!$C$4:$C$200,C5,LE!$E$4:$E$200)+SUMIF(LN!$C$4:$C$48,C5,LN!$E$4:$E$48)+SUMIF(LCE!$C$4:$C$40,C5,LCE!$E$4:$E$40)+SUMIF(LI!$C$4:$C$55,C5,LI!$E$4:$E$55)+SUMIF(LAP!$C$4:$C$45,C5,LAP!$E$4:$E$45)+SUMIF(LGDM!$C$4:$C$15,C5,LGDM!$E$4:$E$15)+SUMIF(LAM!$C$5:$C$18,C5,LAM!$E$5:$E$18)+SUMIF(DEP!$C$4:$C$55,C5,DEP!$E$4:$E$55) -> 23
B6: 4 | C6: Dra. Claudia Chávez López | D6: =SUM(E6:O6) -> 4 | E6: =COUNTIF(LCB!$C$4:$C$40,C6) -> 2 | F6: =COUNTIF(LM!$C$4:$C$144,C6) -> 0 | G6: =COUNTIF(LO!$C$4:$C$227,C6) -> 2 | H6: =COUNTIF(LE!$C$4:$C$214,C6) -> 0 | I6: =COUNTIF(LN!$C$4:$C$53,C6) -> 0 | J6: =COUNTIF(LCE!$C$3:$C$43,C6) -> 0 | K6: =COUNTIF(LI!$C$4:$C$60,C6) -> 0 | L6: =COUNTIF(LAP!$C$5:$C$45,C6) -> 0 | M6: =COUNTIF(LGDM!$C$4:$C$22,C6) -> 0 | N6: =COUNTIF(LAM!$C$5:$C$21,C6) -> 0 | O6: =COUNTIF(DEP!$C$3:$C$61,C6) -> 0 | P6: =SUMIF(LCB!$C$4:$C$45,C6,LCB!$F$4:$F$45)+SUMIF(LM!$C$4:$C$140,C6,LM!$F$4:$F$140)+SUMIF(LO!$C$4:$C$230,C6,LO!$F$4:$F$230)+SUMIF(LE!$C$4:$C$200,C6,LE!$F$4:$F$200)+SUMIF(LN!$C$4:$C$48,C6,LN!$F$4:$F$48)+SUMIF(LCE!$C$4:$C$40,C6,LCE!$F$4:$F$40)+SUMIF(LI!$C$4:$C$55,C6,LI!$F$4:$F$55)+SUMIF(LAP!$C$4:$C$45,C6,LAP!$F$4:$F$45)+SUMIF(LGDM!$C$4:$C$22,C6,LGDM!$F$4:$F$22)+SUMIF(LAM!$C$4:$C$18,C6,LAM!$F$4:$F$18)+SUMIF(DEP!$C$4:$C$55,C6,DEP!$F$4:$F$55) -> 0 | Q6: =SUMIF(LCB!$C$4:$C$45,C6,LCB!$E$4:$E$45)+SUMIF(LM!$C$4:$C$140,C6,LM!$E$4:$E$140)+SUMIF(LO!$C$4:$C$230,C6,LO!$E$4:$E$230)+SUMIF(LE!$C$4:$C$200,C6,LE!$E$4:$E$200)+SUMIF(LN!$C$4:$C$48,C6,LN!$E$4:$E$48)+SUMIF(LCE!$C$4:$C$40,C6,LCE!$E$4:$E$40)+SUMIF(LI!$C$4:$C$55,C6,LI!$E$4:$E$55)+SUMIF(LAP!$C$4:$C$45,C6,LAP!$E$4:$E$45)+SUMIF(LGDM!$C$4:$C$15,C6,LGDM!$E$4:$E$15)+SUMIF(LAM!$C$5:$C$18,C6,LAM!$E$5:$E$18)+SUMIF(DEP!$C$4:$C$55,C6,DEP!$E$4:$E$55) -> 22
B7: 5 | C7: M.C. Andrea Itayetzzi Ortiz García | D7: =SUM(E7:O7) -> 4 | E7: =COUNTIF(LCB!$C$4:$C$40,C7) -> 0 | F7: =COUNTIF(LM!$C$4:$C$144,C7) -> 0 | G7: =COUNTIF(LO!$C$4:$C$227,C7) -> 3 | H7: =COUNTIF(LE!$C$4:$C$214,C7) -> 1 | I7: =COUNTIF(LN!$C$4:$C$53,C7) -> 0 | J7: =COUNTIF(LCE!$C$3:$C$43,C7) -> 0 | K7: =COUNTIF(LI!$C$4:$C$60,C7) -> 0 | L7: =COUNTIF(LAP!$C$5:$C$45,C7) -> 0 | M7: =COUNTIF(LGDM!$C$4:$C$22,C7) -> 0 | N7: =COUNTIF(LAM!$C$5:$C$21,C7) -> 0 | O7: =COUNTIF(DEP!$C$3:$C$61,C7) -> 0 | P7: =SUMIF(LCB!$C$4:$C$45,C7,LCB!$F$4:$F$45)+SUMIF(LM!$C$4:$C$140,C7,LM!$F$4:$F$140)+SUMIF(LO!$C$4:$C$230,C7,LO!$F$4:$F$230)+SUMIF(LE!$C$4:$C$200,C7,LE!$F$4:$F$200)+SUMIF(LN!$C$4:$C$48,C7,LN!$F$4:$F$48)+SUMIF(LCE!$C$4:$C$40,C7,LCE!$F$4:$F$40)+SUMIF(LI!$C$4:$C$55,C7,LI!$F$4:$F$55)+SUMIF(LAP!$C$4:$C$45,C7,LAP!$F$4:$F$45)+SUMIF(LGDM!$C$4:$C$22,C7,LGDM!$F$4:$F$22)+SUMIF(LAM!$C$4:$C$18,C7,LAM!$F$4:$F$18)+SUMIF(DEP!$C$4:$C$55,C7,DEP!$F$4:$F$55) -> 0 | Q7: =SUMIF(LCB!$C$4:$C$45,C7,LCB!$E$4:$E$45)+SUMIF(LM!$C$4:$C$140,C7,LM!$E$4:$E$140)+SUMIF(LO!$C$4:$C$230,C7,LO!$E$4:$E$230)+SUMIF(LE!$C$4:$C$200,C7,LE!$E$4:$E$200)+SUMIF(LN!$C$4:$C$48,C7,LN!$E$4:$E$48)+SUMIF(LCE!$C$4:$C$40,C7,LCE!$E$4:$E$40)+SUMIF(LI!$C$4:$C$55,C7,LI!$E$4:$E$55)+SUMIF(LAP!$C$4:$C$45,C7,LAP!$E$4:$E$45)+SUMIF(LGDM!$C$4:$C$15,C7,LGDM!$E$4:$E$15)+SUMIF(LAM!$C$5:$C$18,C7,LAM!$E$5:$E$18)+SUMIF(DEP!$C$4:$C$55,C7,DEP!$E$4:$E$55) -> 21
B8: 6 | C8: Dr. Abisaí Martínez Sánchez | D8: =SUM(E8:O8) -> 4 | E8: =COUNTIF(LCB!$C$4:$C$40,C8) -> 0 | F8: =COUNTIF(LM!$C$4:$C$144,C8) -> 0 | G8: =COUNTIF(LO!$C$4:$C$227,C8) -> 1 | H8: =COUNTIF(LE!$C$4:$C$214,C8) -> 3 | I8: =COUNTIF(LN!$C$4:$C$53,C8) -> 0 | J8: =COUNTIF(LCE!$C$3:$C$43,C8) -> 0 | K8: =COUNTIF(LI!$C$4:$C$60,C8) -> 0 | L8: =COUNTIF(LAP!$C$5:$C$45,C8) -> 0 | M8: =COUNTIF(LGDM!$C$4:$C$22,C8) -> 0 | N8: =COUNTIF(LAM!$C$5:$C$21,C8) -> 0 | O8: =COUNTIF(DEP!$C$3:$C$61,C8) -> 0 | P8: =SUMIF(LCB!$C$4:$C$45,C8,LCB!$F$4:$F$45)+SUMIF(LM!$C$4:$C$140,C8,LM!$F$4:$F$140)+SUMIF(LO!$C$4:$C$230,C8,LO!$F$4:$F$230)+SUMIF(LE!$C$4:$C$200,C8,LE!$F$4:$F$200)+SUMIF(LN!$C$4:$C$48,C8,LN!$F$4:$F$48)+SUMIF(LCE!$C$4:$C$40,C8,LCE!$F$4:$F$40)+SUMIF(LI!$C$4:$C$55,C8,LI!$F$4:$F$55)+SUMIF(LAP!$C$4:$C$45,C8,LAP!$F$4:$F$45)+SUMIF(LGDM!$C$4:$C$22,C8,LGDM!$F$4:$F$22)+SUMIF(LAM!$C$4:$C$18,C8,LAM!$F$4:$F$18)+SUMIF(DEP!$C$4:$C$55,C8,DEP!$F$4:$F$55) -> 0 | Q8: =SUMIF(LCB!$C$4:$C$45,C8,LCB!$E$4:$E$45)+SUMIF(LM!$C$4:$C$140,C8,LM!$E$4:$E$140)+SUMIF(LO!$C$4:$C$230,C8,LO!$E$4:$E$230)+SUMIF(LE!$C$4:$C$200,C8,LE!$E$4:$E$200)+SUMIF(LN!$C$4:$C$48,C8,LN!$E$4:$E$48)+SUMIF(LCE!$C$4:$C$40,C8,LCE!$E$4:$E$40)+SUMIF(LI!$C$4:$C$55,C8,LI!$E$4:$E$55)+SUMIF(LAP!$C$4:$C$45,C8,LAP!$E$4:$E$45)+SUMIF(LGDM!$C$4:$C$15,C8,LGDM!$E$4:$E$15)+SUMIF(LAM!$C$5:$C$18,C8,LAM!$E$5:$E$18)+SUMIF(DEP!$C$4:$C$55,C8,DEP!$E$4:$E$55) -> 23
B9: 7 | C9: Dra. Lilian Arzeta Pino | D9: =SUM(E9:O9) -> 4 | E9: =COUNTIF(LCB!$C$4:$C$40,C9) -> 0 | F9: =COUNTIF(LM!$C$4:$C$144,C9) -> 0 | G9: =COUNTIF(LO!$C$4:$C$227,C9) -> 1 | H9: =COUNTIF(LE!$C$4:$C$214,C9) -> 2 | I9: =COUNTIF(LN!$C$4:$C$53,C9) -> 0 | J9: =COUNTIF(LCE!$C$3:$C$43,C9) -> 0 | K9: =COUNTIF(LI!$C$4:$C$60,C9) -> 0 | L9: =COUNTIF(LAP!$C$5:$C$45,C9) -> 0 | M9: =COUNTIF(LGDM!$C$4:$C$22,C9) -> 0 | N9: =COUNTIF(LAM!$C$5:$C$21,C9) -> 0 | O9: =COUNTIF(DEP!$C$3:$C$61,C9) -> 1 | P9: =SUMIF(LCB!$C$4:$C$45,C9,LCB!$F$4:$F$45)+SUMIF(LM!$C$4:$C$140,C9,LM!$F$4:$F$140)+SUMIF(LO!$C$4:$C$230,C9,LO!$F$4:$F$230)+SUMIF(LE!$C$4:$C$200,C9,LE!$F$4:$F$200)+SUMIF(LN!$C$4:$C$48,C9,LN!$F$4:$F$48)+SUMIF(LCE!$C$4:$C$40,C9,LCE!$F$4:$F$40)+SUMIF(LI!$C$4:$C$55,C9,LI!$F$4:$F$55)+SUMIF(LAP!$C$4:$C$45,C9,LAP!$F$4:$F$45)+SUMIF(LGDM!$C$4:$C$22,C9,LGDM!$F$4:$F$22)+SUMIF(LAM!$C$4:$C$18,C9,LAM!$F$4:$F$18)+SUMIF(DEP!$C$4:$C$55,C9,DEP!$F$4:$F$55) -> 0 | Q9: =SUMIF(LCB!$C$4:$C$45,C9,LCB!$E$4:$E$45)+SUMIF(LM!$C$4:$C$140,C9,LM!$E$4:$E$140)+SUMIF(LO!$C$4:$C$230,C9,LO!$E$4:$E$230)+SUMIF(LE!$C$4:$C$200,C9,LE!$E$4:$E$200)+SUMIF(LN!$C$4:$C$48,C9,LN!$E$4:$E$48)+SUMIF(LCE!$C$4:$C$40,C9,LCE!$E$4:$E$40)+SUMIF(LI!$C$4:$C$55,C9,LI!$E$4:$E$55)+SUMIF(LAP!$C$4:$C$45,C9,LAP!$E$4:$E$45)+SUMIF(LGDM!$C$4:$C$15,C9,LGDM!$E$4:$E$15)+SUMIF(LAM!$C$5:$C$18,C9,LAM!$E$5:$E$18)+SUMIF(DEP!$C$4:$C$55,C9,DEP!$E$4:$E$55) -> 21
B10: 8 | C10: Dr. Edgar Rodrigo Guzmán Bautista | D10: =SUM(E10:O10) -> 2 | E10: =COUNTIF(LCB!$C$4:$C$40,C10) -> 2 | F10: =COUNTIF(LM!$C$4:$C$144,C10) -> 0 | G10: =COUNTIF(LO!$C$4:$C$227,C10) -> 0 | H10: =COUNTIF(LE!$C$4:$C$214,C10) -> 0 | I10: =COUNTIF(LN!$C$4:$C$53,C10) -> 0 | J10: =COUNTIF(LCE!$C$3:$C$43,C10) -> 0 | K10: =COUNTIF(LI!$C$4:$C$60,C10) -> 0 | L10: =COUNTIF(LAP!$C$5:$C$45,C10) -> 0 | M10: =COUNTIF(LGDM!$C$4:$C$22,C10) -> 0 | N10: =COUNTIF(LAM!$C$5:$C$21,C10) -> 0 | O10: =COUNTIF(DEP!$C$3:$C$61,C10) -> 0 | P10: =SUMIF(LCB!$C$4:$C$45,C10,LCB!$F$4:$F$45)+SUMIF(LM!$C$4:$C$140,C10,LM!$F$4:$F$140)+SUMIF(LO!$C$4:$C$230,C10,LO!$F$4:$F$230)+SUMIF(LE!$C$4:$C$200,C10,LE!$F$4:$F$200)+SUMIF(LN!$C$4:$C$48,C10,LN!$F$4:$F$48)+SUMIF(LCE!$C$4:$C$40,C10,LCE!$F$4:$F$40)+SUMIF(LI!$C$4:$C$55,C10,LI!$F$4:$F$55)+SUMIF(LAP!$C$4:$C$45,C10,LAP!$F$4:$F$45)+SUMIF(LGDM!$C$4:$C$22,C10,LGDM!$F$4:$F$22)+SUMIF(LAM!$C$4:$C$18,C10,LAM!$F$4:$F$18)+SUMIF(DEP!$C$4:$C$55,C10,DEP!$F$4:$F$55) -> 0 | Q10: =SUMIF(LCB!$C$4:$C$45,C10,LCB!$E$4:$E$45)+SUMIF(LM!$C$4:$C$140,C10,LM!$E$4:$E$140)+SUMIF(LO!$C$4:$C$230,C10,LO!$E$4:$E$230)+SUMIF(LE!$C$4:$C$200,C10,LE!$E$4:$E$200)+SUMIF(LN!$C$4:$C$48,C10,LN!$E$4:$E$48)+SUMIF(LCE!$C$4:$C$40,C10,LCE!$E$4:$E$40)+SUMIF(LI!$C$4:$C$55,C10,LI!$E$4:$E$55)+SUMIF(LAP!$C$4:$C$45,C10,LAP!$E$4:$E$45)+SUMIF(LGDM!$C$4:$C$15,C10,LGDM!$E$4:$E$15)+SUMIF(LAM!$C$5:$C$18,C10,LAM!$E$5:$E$18)+SUMIF(DEP!$C$4:$C$55,C10,DEP!$E$4:$E$55) -> 11
B11: 9 | C11: Dr. Juan Carlos Barragán Gálvez | D11: =SUM(E11:O11) -> 3 | E11: =COUNTIF(LCB!$C$4:$C$40,C11) -> 1 | F11: =COUNTIF(LM!$C$4:$C$144,C11) -> 2 | G11: =COUNTIF(LO!$C$4:$C$227,C11) -> 0 | H11: =COUNTIF(LE!$C$4:$C$214,C11) -> 0 | I11: =COUNTIF(LN!$C$4:$C$53,C11) -> 0 | J11: =COUNTIF(LCE!$C$3:$C$43,C11) -> 0 | K11: =COUNTIF(LI!$C$4:$C$60,C11) -> 0 | L11: =COUNTIF(LAP!$C$5:$C$45,C11) -> 0 | M11: =COUNTIF(LGDM!$C$4:$C$22,C11) -> 0 | N11: =COUNTIF(LAM!$C$5:$C$21,C11) -> 0 | O11: =COUNTIF(DEP!$C$3:$C$61,C11) -> 0 | P11: =SUMIF(LCB!$C$4:$C$45,C11,LCB!$F$4:$F$45)+SUMIF(LM!$C$4:$C$140,C11,LM!$F$4:$F$140)+SUMIF(LO!$C$4:$C$230,C11,LO!$F$4:$F$230)+SUMIF(LE!$C$4:$C$200,C11,LE!$F$4:$F$200)+SUMIF(LN!$C$4:$C$48,C11,LN!$F$4:$F$48)+SUMIF(LCE!$C$4:$C$40,C11,LCE!$F$4:$F$40)+SUMIF(LI!$C$4:$C$55,C11,LI!$F$4:$F$55)+SUMIF(LAP!$C$4:$C$45,C11,LAP!$F$4:$F$45)+SUMIF(LGDM!$C$4:$C$22,C11,LGDM!$F$4:$F$22)+SUMIF(LAM!$C$4:$C$18,C11,LAM!$F$4:$F$18)+SUMIF(DEP!$C$4:$C$55,C11,DEP!$F$4:$F$55) -> 70 | Q11: =SUMIF(LCB!$C$4:$C$45,C11,LCB!$E$4:$E$45)+SUMIF(LM!$C$4:$C$140,C11,LM!$E$4:$E$140)+SUMIF(LO!$C$4:$C$230,C11,LO!$E$4:$E$230)+SUMIF(LE!$C$4:$C$200,C11,LE!$E$4:$E$200)+SUMIF(LN!$C$4:$C$48,C11,LN!$E$4:$E$48)+SUMIF(LCE!$C$4:$C$40,C11,LCE!$E$4:$E$40)+SUMIF(LI!$C$4:$C$55,C11,LI!$E$4:$E$55)+SUMIF(LAP!$C$4:$C$45,C11,LAP!$E$4:$E$45)+SUMIF(LGDM!$C$4:$C$15,C11,LGDM!$E$4:$E$15)+SUMIF(LAM!$C$5:$C$18,C11,LAM!$E$5:$E$18)+SUMIF(DEP!$C$4:$C$55,C11,DEP!$E$4:$E$55) -> 18
B12: 10 | C12: Dra. Karla Esmeralda Tello Ortega | D12: =SUM(E12:O12) -> 3 | E12: =COUNTIF(LCB!$C$4:$C$40,C12) -> 1 | F12: =COUNTIF(LM!$C$4:$C$144,C12) -> 0 | G12: =COUNTIF(LO!$C$4:$C$227,C12) -> 0 | H12: =COUNTIF(LE!$C$4:$C$214,C12) -> 2 | I12: =COUNTIF(LN!$C$4:$C$53,C12) -> 0 | J12: =COUNTIF(LCE!$C$3:$C$43,C12) -> 0 | K12: =COUNTIF(LI!$C$4:$C$60,C12) -> 0 | L12: =COUNTIF(LAP!$C$5:$C$45,C12) -> 0 | M12: =COUNTIF(LGDM!$C$4:$C$22,C12) -> 0 | N12: =COUNTIF(LAM!$C$5:$C$21,C12) -> 0 | O12: =COUNTIF(DEP!$C$3:$C$61,C12) -> 0 | P12: =SUMIF(LCB!$C$4:$C$45,C12,LCB!$F$4:$F$45)+SUMIF(LM!$C$4:$C$140,C12,LM!$F$4:$F$140)+SUMIF(LO!$C$4:$C$230,C12,LO!$F$4:$F$230)+SUMIF(LE!$C$4:$C$200,C12,LE!$F$4:$F$200)+SUMIF(LN!$C$4:$C$48,C12,LN!$F$4:$F$48)+SUMIF(LCE!$C$4:$C$40,C12,LCE!$F$4:$F$40)+SUMIF(LI!$C$4:$C$55,C12,LI!$F$4:$F$55)+SUMIF(LAP!$C$4:$C$45,C12,LAP!$F$4:$F$45)+SUMIF(LGDM!$C$4:$C$22,C12,LGDM!$F$4:$F$22)+SUMIF(LAM!$C$4:$C$18,C12,LAM!$F$4:$F$18)+SUMIF(DEP!$C$4:$C$55,C12,DEP!$F$4:$F$55) -> 0 | Q12: =SUMIF(LCB!$C$4:$C$45,C12,LCB!$E$4:$E$45)+SUMIF(LM!$C$4:$C$140,C12,LM!$E$4:$E$140)+SUMIF(LO!$C$4:$C$230,C12,LO!$E$4:$E$230)+SUMIF(LE!$C$4:$C$200,C12,LE!$E$4:$E$200)+SUMIF(LN!$C$4:$C$48,C12,LN!$E$4:$E$48)+SUMIF(LCE!$C$4:$C$40,C12,LCE!$E$4:$E$40)+SUMIF(LI!$C$4:$C$55,C12,LI!$E$4:$E$55)+SUMIF(LAP!$C$4:$C$45,C12,LAP!$E$4:$E$45)+SUMIF(LGDM!$C$4:$C$15,C12,LGDM!$E$4:$E$15)+SUMIF(LAM!$C$5:$C$18,C12,LAM!$E$5:$E$18)+SUMIF(DEP!$C$4:$C$55,C12,DEP!$E$4:$E$55) -> 16
B13: 11 | C13: M.B.E. Diego Sait Cruz Hernández | D13: =SUM(E13:O13) -> 4 | E13: =COUNTIF(LCB!$C$4:$C$40,C13) -> 1 | F13: =COUNTIF(LM!$C$4:$C$144,C13) -> 0 | G13: =COUNTIF(LO!$C$4:$C$227,C13) -> 3 | H13: =COUNTIF(LE!$C$4:$C$214,C13) -> 0 | I13: =COUNTIF(LN!$C$4:$C$53,C13) -> 0 | J13: =COUNTIF(LCE!$C$3:$C$43,C13) -> 0 | K13: =COUNTIF(LI!$C$4:$C$60,C13) -> 0 | L13: =COUNTIF(LAP!$C$5:$C$45,C13) -> 0 | M13: =COUNTIF(LGDM!$C$4:$C$22,C13) -> 0 | N13: =COUNTIF(LAM!$C$5:$C$21,C13) -> 0 | O13: =COUNTIF(DEP!$C$3:$C$61,C13) -> 0 | P13: =SUMIF(LCB!$C$4:$C$45,C13,LCB!$F$4:$F$45)+SUMIF(LM!$C$4:$C$140,C13,LM!$F$4:$F$140)+SUMIF(LO!$C$4:$C$230,C13,LO!$F$4:$F$230)+SUMIF(LE!$C$4:$C$200,C13,LE!$F$4:$F$200)+SUMIF(LN!$C$4:$C$48,C13,LN!$F$4:$F$48)+SUMIF(LCE!$C$4:$C$40,C13,LCE!$F$4:$F$40)+SUMIF(LI!$C$4:$C$55,C13,LI!$F$4:$F$55)+SUMIF(LAP!$C$4:$C$45,C13,LAP!$F$4:$F$45)+SUMIF(LGDM!$C$4:$C$22,C13,LGDM!$F$4:$F$22)+SUMIF(LAM!$C$4:$C$18,C13,LAM!$F$4:$F$18)+SUMIF(DEP!$C$4:$C$55,C13,DEP!$F$4:$F$55) -> 80 | Q13: =SUMIF(LCB!$C$4:$C$45,C13,LCB!$E$4:$E$45)+SUMIF(LM!$C$4:$C$140,C13,LM!$E$4:$E$140)+SUMIF(LO!$C$4:$C$230,C13,LO!$E$4:$E$230)+SUMIF(LE!$C$4:$C$200,C13,LE!$E$4:$E$200)+SUMIF(LN!$C$4:$C$48,C13,LN!$E$4:$E$48)+SUMIF(LCE!$C$4:$C$40,C13,LCE!$E$4:$E$40)+SUMIF(LI!$C$4:$C$55,C13,LI!$E$4:$E$55)+SUMIF(LAP!$C$4:$C$45,C13,LAP!$E$4:$E$45)+SUMIF(LGDM!$C$4:$C$15,C13,LGDM!$E$4:$E$15)+SUMIF(LAM!$C$5:$C$18,C13,LAM!$E$5:$E$18)+SUMIF(DEP!$C$4:$C$55,C13,DEP!$E$4:$E$55) -> 19
B14: 12 | C14: M.C.T.A. Iliana Vásquez Lara | D14: =SUM(E14:O14) -> 4 | E14: =COUNTIF(LCB!$C$4:$C$40,C14) -> 0 | F14: =COUNTIF(LM!$C$4:$C$144,C14) -> 0 | G14: =COUNTIF(LO!$C$4:$C$227,C14) -> 0 | H14: =COUNTIF(LE!$C$4:$C$214,C14) -> 0 | I14: =COUNTIF(LN!$C$4:$C$53,C14) -> 4 | J14: =COUNTIF(LCE!$C$3:$C$43,C14) -> 0 | K14: =COUNTIF(LI!$C$4:$C$60,C14) -> 0 | L14: =COUNTIF(LAP!$C$5:$C$45,C14) -> 0 | M14: =COUNTIF(LGDM!$C$4:$C$22,C14) -> 0 | N14: =COUNTIF(LAM!$C$5:$C$21,C14) -> 0 | O14: =COUNTIF(DEP!$C$3:$C$61,C14) -> 0 | P14: =SUMIF(LCB!$C$4:$C$45,C14,LCB!$F$4:$F$45)+SUMIF(LM!$C$4:$C$140,C14,LM!$F$4:$F$140)+SUMIF(LO!$C$4:$C$230,C14,LO!$F$4:$F$230)+SUMIF(LE!$C$4:$C$200,C14,LE!$F$4:$F$200)+SUMIF(LN!$C$4:$C$48,C14,LN!$F$4:$F$48)+SUMIF(LCE!$C$4:$C$40,C14,LCE!$F$4:$F$40)+SUMIF(LI!$C$4:$C$55,C14,LI!$F$4:$F$55)+SUMIF(LAP!$C$4:$C$45,C14,LAP!$F$4:$F$45)+SUMIF(LGDM!$C$4:$C$22,C14,LGDM!$F$4:$F$22)+SUMIF(LAM!$C$4:$C$18,C14,LAM!$F$4:$F$18)+SUMIF(DEP!$C$4:$C$55,C14,DEP!$F$4:$F$55) -> 120 | Q14: =SUMIF(LCB!$C$4:$C$45,C14,LCB!$E$4:$E$45)+SUMIF(LM!$C$4:$C$140,C14,LM!$E$4:$E$140)+SUMIF(LO!$C$4:$C$230,C14,LO!$E$4:$E$230)+SUMIF(LE!$C$4:$C$200,C14,LE!$E$4:$E$200)+SUMIF(LN!$C$4:$C$48,C14,LN!$E$4:$E$48)+SUMIF(LCE!$C$4:$C$40,C14,LCE!$E$4:$E$40)+SUMIF(LI!$C$4:$C$55,C14,LI!$E$4:$E$55)+SUMIF(LAP!$C$4:$C$45,C14,LAP!$E$4:$E$45)+SUMIF(LGDM!$C$4:$C$15,C14,LGDM!$E$4:$E$15)+SUMIF(LAM!$C$5:$C$18,C14,LAM!$E$5:$E$18)+SUMIF(DEP!$C$4:$C$55,C14,DEP!$E$4:$E$55) -> 21
... B17: 15 | C17: Dra. Victoria Vera Pineda | D17: =SUM(E17:O17) -> 5 | E17: =COUNTIF(LCB!$C$4:$C$40,C17) -> 2 | F17: =COUNTIF(LM!$C$4:$C$144,C17) -> 0 | G17: =COUNTIF(LO!$C$4:$C$227,C17) -> 3 | H17: =COUNTIF(LE!$C$4:$C$214,C17) -> 0 | I17: =COUNTIF(LN!$C$4:$C$53,C17) -> 0 | J17: =COUNTIF(LCE!$C$3:$C$43,C17) -> 0 | K17: =COUNTIF(LI!$C$4:$C$60,C17) -> 0 | L17: =COUNTIF(LAP!$C$5:$C$45,C17) -> 0 | M17: =COUNTIF(LGDM!$C$4:$C$22,C17) -> 0 | N17: =COUNTIF(LAM!$C$5:$C$21,C17) -> 0 | O17: =COUNTIF(DEP!$C$3:$C$61,C17) -> 0 | P17: =SUMIF(LCB!$C$4:$C$45,C17,LCB!$F$4:$F$45)+SUMIF(LM!$C$4:$C$140,C17,LM!$F$4:$F$140)+SUMIF(LO!$C$4:$C$230,C17,LO!$F$4:$F$230)+SUMIF(LE!$C$4:$C$200,C17,LE!$F$4:$F$200)+SUMIF(LN!$C$4:$C$48,C17,LN!$F$4:$F$48)+SUMIF(LCE!$C$4:$C$40,C17,LCE!$F$4:$F$40)+SUMIF(LI!$C$4:$C$55,C17,LI!$F$4:$F$55)+SUMIF(LAP!$C$4:$C$45,C17,LAP!$F$4:$F$45)+SUMIF(LGDM!$C$4:$C$22,C17,LGDM!$F$4:$F$22)+SUMIF(LAM!$C$4:$C$18,C17,LAM!$F$4:$F$18)+SUMIF(DEP!$C$4:$C$55,C17,DEP!$F$4:$F$55) -> 120 | Q17: =SUMIF(LCB!$C$4:$C$45,C17,LCB!$E$4:$E$45)+SUMIF(LM!$C$4:$C$140,C17,LM!$E$4:$E$140)+SUMIF(LO!$C$4:$C$230,C17,LO!$E$4:$E$230)+SUMIF(LE!$C$4:$C$200,C17,LE!$E$4:$E$200)+SUMIF(LN!$C$4:$C$48,C17,LN!$E$4:$E$48)+SUMIF(LCE!$C$4:$C$40,C17,LCE!$E$4:$E$40)+SUMIF(LI!$C$4:$C$55,C17,LI!$E$4:$E$55)+SUMIF(LAP!$C$4:$C$45,C17,LAP!$E$4:$E$45)+SUMIF(LGDM!$C$4:$C$15,C17,LGDM!$E$4:$E$15)+SUMIF(LAM!$C$5:$C$18,C17,LAM!$E$5:$E$18)+SUMIF(DEP!$C$4:$C$55,C17,DEP!$E$4:$E$55) -> 23
B20: LM | C20: Profesor@ | D20: Materias | E20: LCB | F20: LM | G20: LO | H20: LE | I20: LN | J20: LCE | K20: LI | L20: LAP | M20: LGDM | N20: LAM | O20: DEP | P20: Total alumnos | Q20: Total hrs sem
B21: 1 | C21: Méd. Guadalupe Ithalivi Olivera Domínguez | D21: =SUM(E21:O21) -> 1 | E21: =COUNTIF(LCB!$C$4:$C$40,C21) -> 0 | F21: =COUNTIF(LM!$C$4:$C$144,C21) -> 1 | G21: =COUNTIF(LO!$C$4:$C$227,C21) -> 0 | H21: =COUNTIF(LE!$C$4:$C$214,C21) -> 0 | I21: =COUNTIF(LN!$C$4:$C$53,C21) -> 0 | J21: =COUNTIF(LCE!$C$3:$C$43,C21) -> 0 | K21: =COUNTIF(LI!$C$4:$C$60,C21) -> 0 | L21: =COUNTIF(LAP!$C$5:$C$45,C21) -> 0 | M21: =COUNTIF(LGDM!$C$4:$C$22,C21) -> 0 | N21: =COUNTIF(LAM!$C$5:$C$21,C21) -> 0 | O21: =COUNTIF(DEP!$C$3:$C$61,C21) -> 0 | P21: =SUMIF(LCB!$C$4:$C$45,C21,LCB!$F$4:$F$45)+SUMIF(LM!$C$4:$C$140,C21,LM!$F$4:$F$140)+SUMIF(LO!$C$4:$C$230,C21,LO!$F$4:$F$230)+SUMIF(LE!$C$4:$C$200,C21,LE!$F$4:$F$200)+SUMIF(LN!$C$4:$C$48,C21,LN!$F$4:$F$48)+SUMIF(LCE!$C$4:$C$40,C21,LCE!$F$4:$F$40)+SUMIF(LI!$C$4:$C$55,C21,LI!$F$4:$F$55)+SUMIF(LAP!$C$4:$C$45,C21,LAP!$F$4:$F$45)+SUMIF(LGDM!$C$4:$C$22,C21,LGDM!$F$4:$F$22)+SUMIF(LAM!$C$4:$C$18,C21,LAM!$F$4:$F$18)+SUMIF(DEP!$C$4:$C$55,C21,DEP!$F$4:$F$55) -> 42 | Q21: =SUMIF(LCB!$C$4:$C$45,C21,LCB!$E$4:$E$45)+SUMIF(LM!$C$4:$C$140,C21,LM!$E$4:$E$140)+SUMIF(LO!$C$4:$C$230,C21,LO!$E$4:$E$230)+SUMIF(LE!$C$4:$C$200,C21,LE!$E$4:$E$200)+SUMIF(LN!$C$4:$C$48,C21,LN!$E$4:$E$48)+SUMIF(LCE!$C$4:$C$40,C21,LCE!$E$4:$E$40)+SUMIF(LI!$C$4:$C$55,C21,LI!$E$4:$E$55)+SUMIF(LAP!$C$4:$C$45,C21,LAP!$E$4:$E$45)+SUMIF(LGDM!$C$4:$C$15,C21,LGDM!$E$4:$E$15)+SUMIF(LAM!$C$5:$C$18,C21,LAM!$E$5:$E$18)+SUMIF(DEP!$C$4:$C$55,C21,DEP!$E$4:$E$55) -> 4
B22: 2 | C22: M.S.P. Pablo Cataneo Pérez | D22: =SUM(E22:O22) -> 4 | E22: =COUNTIF(LCB!$C$4:$C$40,C22) -> 0 | F22: =COUNTIF(LM!$C$4:$C$144,C22) -> 4 | G22: =COUNTIF(LO!$C$4:$C$227,C22) -> 0 | H22: =COUNTIF(LE!$C$4:$C$214,C22) -> 0 | I22: =COUNTIF(LN!$C$4:$C$53,C22) -> 0 | J22: =COUNTIF(LCE!$C$3:$C$43,C22) -> 0 | K22: =COUNTIF(LI!$C$4:$C$60,C22) -> 0 | L22: =COUNTIF(LAP!$C$5:$C$45,C22) -> 0 | M22: =COUNTIF(LGDM!$C$4:$C$22,C22) -> 0 | N22: =COUNTIF(LAM!$C$5:$C$21,C22) -> 0 | O22: =COUNTIF(DEP!$C$3:$C$61,C22) -> 0 | P22: =SUMIF(LCB!$C$4:$C$45,C22,LCB!$F$4:$F$45)+SUMIF(LM!$C$4:$C$140,C22,LM!$F$4:$F$140)+SUMIF(LO!$C$4:$C$230,C22,LO!$F$4:$F$230)+SUMIF(LE!$C$4:$C$200,C22,LE!$F$4:$F$200)+SUMIF(LN!$C$4:$C$48,C22,LN!$F$4:$F$48)+SUMIF(LCE!$C$4:$C$40,C22,LCE!$F$4:$F$40)+SUMIF(LI!$C$4:$C$55,C22,LI!$F$4:$F$55)+SUMIF(LAP!$C$4:$C$45,C22,LAP!$F$4:$F$45)+SUMIF(LGDM!$C$4:$C$22,C22,LGDM!$F$4:$F$22)+SUMIF(LAM!$C$4:$C$18,C22,LAM!$F$4:$F$18)+SUMIF(DEP!$C$4:$C$55,C22,DEP!$F$4:$F$55) -> 121 | Q22: =SUMIF(LCB!$C$4:$C$45,C22,LCB!$E$4:$E$45)+SUMIF(LM!$C$4:$C$140,C22,LM!$E$4:$E$140)+SUMIF(LO!$C$4:$C$230,C22,LO!$E$4:$E$230)+SUMIF(LE!$C$4:$C$200,C22,LE!$E$4:$E$200)+SUMIF(LN!$C$4:$C$48,C22,LN!$E$4:$E$48)+SUMIF(LCE!$C$4:$C$40,C22,LCE!$E$4:$E$40)+SUMIF(LI!$C$4:$C$55,C22,LI!$E$4:$E$55)+SUMIF(LAP!$C$4:$C$45,C22,LAP!$E$4:$E$45)+SUMIF(LGDM!$C$4:$C$15,C22,LGDM!$E$4:$E$15)+SUMIF(LAM!$C$5:$C$18,C22,LAM!$E$5:$E$18)+SUMIF(DEP!$C$4:$C$55,C22,DEP!$E$4:$E$55) -> 24
B23: 3 | C23: M.D.C.S. Concepción Julián López | D23: =SUM(E23:O23) -> 4 | E23: =COUNTIF(LCB!$C$4:$C$40,C23) -> 0 | F23: =COUNTIF(LM!$C$4:$C$144,C23) -> 4 | G23: =COUNTIF(LO!$C$4:$C$227,C23) -> 0 | H23: =COUNTIF(LE!$C$4:$C$214,C23) -> 0 | I23: =COUNTIF(LN!$C$4:$C$53,C23) -> 0 | J23: =COUNTIF(LCE!$C$3:$C$43,C23) -> 0 | K23: =COUNTIF(LI!$C$4:$C$60,C23) -> 0 | L23: =COUNTIF(LAP!$C$5:$C$45,C23) -> 0 | M23: =COUNTIF(LGDM!$C$4:$C$22,C23) -> 0 | N23: =COUNTIF(LAM!$C$5:$C$21,C23) -> 0 | O23: =COUNTIF(DEP!$C$3:$C$61,C23) -> 0 | P23: =SUMIF(LCB!$C$4:$C$45,C23,LCB!$F$4:$F$45)+SUMIF(LM!$C$4:$C$140,C23,LM!$F$4:$F$140)+SUMIF(LO!$C$4:$C$230,C23,LO!$F$4:$F$230)+SUMIF(LE!$C$4:$C$200,C23,LE!$F$4:$F$200)+SUMIF(LN!$C$4:$C$48,C23,LN!$F$4:$F$48)+SUMIF(LCE!$C$4:$C$40,C23,LCE!$F$4:$F$40)+SUMIF(LI!$C$4:$C$55,C23,LI!$F$4:$F$55)+SUMIF(LAP!$C$4:$C$45,C23,LAP!$F$4:$F$45)+SUMIF(LGDM!$C$4:$C$22,C23,LGDM!$F$4:$F$22)+SUMIF(LAM!$C$4:$C$18,C23,LAM!$F$4:$F$18)+SUMIF(DEP!$C$4:$C$55,C23,DEP!$F$4:$F$55) -> 120 | Q23: =SUMIF(LCB!$C$4:$C$45,C23,LCB!$E$4:$E$45)+SUMIF(LM!$C$4:$C$140,C23,LM!$E$4:$E$140)+SUMIF(LO!$C$4:$C$230,C23,LO!$E$4:$E$230)+SUMIF(LE!$C$4:$C$200,C23,LE!$E$4:$E$200)+SUMIF(LN!$C$4:$C$48,C23,LN!$E$4:$E$48)+SUMIF(LCE!$C$4:$C$40,C23,LCE!$E$4:$E$40)+SUMIF(LI!$C$4:$C$55,C23,LI!$E$4:$E$55)+SUMIF(LAP!$C$4:$C$45,C23,LAP!$E$4:$E$45)+SUMIF(LGDM!$C$4:$C$15,C23,LGDM!$E$4:$E$15)+SUMIF(LAM!$C$5:$C$18,C23,LAM!$E$5:$E$18)+SUMIF(DEP!$C$4:$C$55,C23,DEP!$E$4:$E$55) -> 26
B24: 4 | C24: Méd. José Guadalupe Reyes Ramírez | D24: =SUM(E24:O24) -> 4 | E24: =COUNTIF(LCB!$C$4:$C$40,C24) -> 0 | F24: =COUNTIF(LM!$C$4:$C$144,C24) -> 0 | G24: =COUNTIF(LO!$C$4:$C$227,C24) -> 0 | H24: =COUNTIF(LE!$C$4:$C$214,C24) -> 4 | I24: =COUNTIF(LN!$C$4:$C$53,C24) -> 0 | J24: =COUNTIF(LCE!$C$3:$C$43,C24) -> 0 | K24: =COUNTIF(LI!$C$4:$C$60,C24) -> 0 | L24: =COUNTIF(LAP!$C$5:$C$45,C24) -> 0 | M24: =COUNTIF(LGDM!$C$4:$C$22,C24) -> 0 | N24: =COUNTIF(LAM!$C$5:$C$21,C24) -> 0 | O24: =COUNTIF(DEP!$C$3:$C$61,C24) -> 0 | P24: =SUMIF(LCB!$C$4:$C$45,C24,LCB!$F$4:$F$45)+SUMIF(LM!$C$4:$C$140,C24,LM!$F$4:$F$140)+SUMIF(LO!$C$4:$C$230,C24,LO!$F$4:$F$230)+SUMIF(LE!$C$4:$C$200,C24,LE!$F$4:$F$200)+SUMIF(LN!$C$4:$C$48,C24,LN!$F$4:$F$48)+SUMIF(LCE!$C$4:$C$40,C24,LCE!$F$4:$F$40)+SUMIF(LI!$C$4:$C$55,C24,LI!$F$4:$F$55)+SUMIF(LAP!$C$4:$C$45,C24,LAP!$F$4:$F$45)+SUMIF(LGDM!$C$4:$C$22,C24,LGDM!$F$4:$F$22)+SUMIF(LAM!$C$4:$C$18,C24,LAM!$F$4:$F$18)+SUMIF(DEP!$C$4:$C$55,C24,DEP!$F$4:$F$55) -> 136 | Q24: =SUMIF(LCB!$C$4:$C$45,C24,LCB!$E$4:$E$45)+SUMIF(LM!$C$4:$C$140,C24,LM!$E$4:$E$140)+SUMIF(LO!$C$4:$C$230,C24,LO!$E$4:$E$230)+SUMIF(LE!$C$4:$C$200,C24,LE!$E$4:$E$200)+SUMIF(LN!$C$4:$C$48,C24,LN!$E$4:$E$48)+SUMIF(LCE!$C$4:$C$40,C24,LCE!$E$4:$E$40)+SUMIF(LI!$C$4:$C$55,C24,LI!$E$4:$E$55)+SUMIF(LAP!$C$4:$C$45,C24,LAP!$E$4:$E$45)+SUMIF(LGDM!$C$4:$C$15,C24,LGDM!$E$4:$E$15)+SUMIF(LAM!$C$5:$C$18,C24,LAM!$E$5:$E$18)+SUMIF(DEP!$C$4:$C$55,C24,DEP!$E$4:$E$55) -> 20
B25: 5 | C25: M.C.Q.B. David Gómez Martínez | D25: =SUM(E25:O25) -> 4 | E25: =COUNTIF(LCB!$C$4:$C$40,C25) -> 0 | F25: =COUNTIF(LM!$C$4:$C$144,C25) -> 4 | G25: =COUNTIF(LO!$C$4:$C$227,C25) -> 0 | H25: =COUNTIF(LE!$C$4:$C$214,C25) -> 0 | I25: =COUNTIF(LN!$C$4:$C$53,C25) -> 0 | J25: =COUNTIF(LCE!$C$3:$C$43,C25) -> 0 | K25: =COUNTIF(LI!$C$4:$C$60,C25) -> 0 | L25: =COUNTIF(LAP!$C$5:$C$45,C25) -> 0 | M25: =COUNTIF(LGDM!$C$4:$C$22,C25) -> 0 | N25: =COUNTIF(LAM!$C$5:$C$21,C25) -> 0 | O25: =COUNTIF(DEP!$C$3:$C$61,C25) -> 0 | P25: =SUMIF(LCB!$C$4:$C$45,C25,LCB!$F$4:$F$45)+SUMIF(LM!$C$4:$C$140,C25,LM!$F$4:$F$140)+SUMIF(LO!$C$4:$C$230,C25,LO!$F$4:$F$230)+SUMIF(LE!$C$4:$C$200,C25,LE!$F$4:$F$200)+SUMIF(LN!$C$4:$C$48,C25,LN!$F$4:$F$48)+SUMIF(LCE!$C$4:$C$40,C25,LCE!$F$4:$F$40)+SUMIF(LI!$C$4:$C$55,C25,LI!$F$4:$F$55)+SUMIF(LAP!$C$4:$C$45,C25,LAP!$F$4:$F$45)+SUMIF(LGDM!$C$4:$C$22,C25,LGDM!$F$4:$F$22)+SUMIF(LAM!$C$4:$C$18,C25,LAM!$F$4:$F$18)+SUMIF(DEP!$C$4:$C$55,C25,DEP!$F$4:$F$55) -> 180 | Q25: =SUMIF(LCB!$C$4:$C$45,C25,LCB!$E$4:$E$45)+SUMIF(LM!$C$4:$C$140,C25,LM!$E$4:$E$140)+SUMIF(LO!$C$4:$C$230,C25,LO!$E$4:$E$230)+SUMIF(LE!$C$4:$C$200,C25,LE!$E$4:$E$200)+SUMIF(LN!$C$4:$C$48,C25,LN!$E$4:$E$48)+SUMIF(LCE!$C$4:$C$40,C25,LCE!$E$4:$E$40)+SUMIF(LI!$C$4:$C$55,C25,LI!$E$4:$E$55)+SUMIF(LAP!$C$4:$C$45,C25,LAP!$E$4:$E$45)+SUMIF(LGDM!$C$4:$C$15,C25,LGDM!$E$4:$E$15)+SUMIF(LAM!$C$5:$C$18,C25,LAM!$E$5:$E$18)+SUMIF(DEP!$C$4:$C$55,C25,DEP!$E$4:$E$55) -> 20
B26: 6 | C26: Méd. Jasibe Ivette Cruz Vásquez | D26: =SUM(E26:O26) -> 4 | E26: =COUNTIF(LCB!$C$4:$C$40,C26) -> 0 | F26: =COUNTIF(LM!$C$4:$C$144,C26) -> 4 | G26: =COUNTIF(LO!$C$4:$C$227,C26) -> 0 | H26: =COUNTIF(LE!$C$4:$C$214,C26) -> 0 | I26: =COUNTIF(LN!$C$4:$C$53,C26) -> 0 | J26: =COUNTIF(LCE!$C$3:$C$43,C26) -> 0 | K26: =COUNTIF(LI!$C$4:$C$60,C26) -> 0 | L26: =COUNTIF(LAP!$C$5:$C$45,C26) -> 0 | M26: =COUNTIF(LGDM!$C$4:$C$22,C26) -> 0 | N26: =COUNTIF(LAM!$C$5:$C$21,C26) -> 0 | O26: =COUNTIF(DEP!$C$3:$C$61,C26) -> 0 | P26: =SUMIF(LCB!$C$4:$C$45,C26,LCB!$F$4:$F$45)+SUMIF(LM!$C$4:$C$140,C26,LM!$F$4:$F$140)+SUMIF(LO!$C$4:$C$230,C26,LO!$F$4:$F$230)+SUMIF(LE!$C$4:$C$200,C26,LE!$F$4:$F$200)+SUMIF(LN!$C$4:$C$48,C26,LN!$F$4:$F$48)+SUMIF(LCE!$C$4:$C$40,C26,LCE!$F$4:$F$40)+SUMIF(LI!$C$4:$C$55,C26,LI!$F$4:$F$55)+SUMIF(LAP!$C$4:$C$45,C26,LAP!$F$4:$F$45)+SUMIF(LGDM!$C$4:$C$22,C26,LGDM!$F$4:$F$22)+SUMIF(LAM!$C$4:$C$18,C26,LAM!$F$4:$F$18)+SUMIF(DEP!$C$4:$C$55,C26,DEP!$F$4:$F$55) -> 138 | Q26: =SUMIF(LCB!$C$4:$C$45,C26,LCB!$E$4:$E$45)+SUMIF(LM!$C$4:$C$140,C26,LM!$E$4:$E$140)+SUMIF(LO!$C$4:$C$230,C26,LO!$E$4:$E$230)+SUMIF(LE!$C$4:$C$200,C26,LE!$E$4:$E$200)+SUMIF(LN!$C$4:$C$48,C26,LN!$E$4:$E$48)+SUMIF(LCE!$C$4:$C$40,C26,LCE!$E$4:$E$40)+SUMIF(LI!$C$4:$C$55,C26,LI!$E$4:$E$55)+SUMIF(LAP!$C$4:$C$45,C26,LAP!$E$4:$E$45)+SUMIF(LGDM!$C$4:$C$15,C26,LGDM!$E$4:$E$15)+SUMIF(LAM!$C$5:$C$18,C26,LAM!$E$5:$E$18)+SUMIF(DEP!$C$4:$C$55,C26,DEP!$E$4:$E$55) -> 25
B27: 7 | C27: Dr. Alejandro Francisco Cruz | D27: =SUM(E27:O27) -> 4 | E27: =COUNTIF(LCB!$C$4:$C$40,C27) -> 0 | F27: =COUNTIF(LM!$C$4:$C$144,C27) -> 4 | G27: =COUNTIF(LO!$C$4:$C$227,C27) -> 0 | H27: =COUNTIF(LE!$C$4:$C$214,C27) -> 0 | I27: =COUNTIF(LN!$C$4:$C$53,C27) -> 0 | J27: =COUNTIF(LCE!$C$3:$C$43,C27) -> 0 | K27: =COUNTIF(LI!$C$4:$C$60,C27) -> 0 | L27: =COUNTIF(LAP!$C$5:$C$45,C27) -> 0 | M27: =COUNTIF(LGDM!$C$4:$C$22,C27) -> 0 | N27: =COUNTIF(LAM!$C$5:$C$21,C27) -> 0 | O27: =COUNTIF(DEP!$C$3:$C$61,C27) -> 0 | P27: =SUMIF(LCB!$C$4:$C$45,C27,LCB!$F$4:$F$45)+SUMIF(LM!$C$4:$C$140,C27,LM!$F$4:$F$140)+SUMIF(LO!$C$4:$C$230,C27,LO!$F$4:$F$230)+SUMIF(LE!$C$4:$C$200,C27,LE!$F$4:$F$200)+SUMIF(LN!$C$4:$C$48,C27,LN!$F$4:$F$48)+SUMIF(LCE!$C$4:$C$40,C27,LCE!$F$4:$F$40)+SUMIF(LI!$C$4:$C$55,C27,LI!$F$4:$F$55)+SUMIF(LAP!$C$4:$C$45,C27,LAP!$F$4:$F$45)+SUMIF(LGDM!$C$4:$C$22,C27,LGDM!$F$4:$F$22)+SUMIF(LAM!$C$4:$C$18,C27,LAM!$F$4:$F$18)+SUMIF(DEP!$C$4:$C$55,C27,DEP!$F$4:$F$55) -> 146 | Q27: =SUMIF(LCB!$C$4:$C$45,C27,LCB!$E$4:$E$45)+SUMIF(LM!$C$4:$C$140,C27,LM!$E$4:$E$140)+SUMIF(LO!$C$4:$C$230,C27,LO!$E$4:$E$230)+SUMIF(LE!$C$4:$C$200,C27,LE!$E$4:$E$200)+SUMIF(LN!$C$4:$C$48,C27,LN!$E$4:$E$48)+SUMIF(LCE!$C$4:$C$40,C27,LCE!$E$4:$E$40)+SUMIF(LI!$C$4:$C$55,C27,LI!$E$4:$E$55)+SUMIF(LAP!$C$4:$C$45,C27,LAP!$E$4:$E$45)+SUMIF(LGDM!$C$4:$C$15,C27,LGDM!$E$4:$E$15)+SUMIF(LAM!$C$5:$C$18,C27,LAM!$E$5:$E$18)+SUMIF(DEP!$C$4:$C$55,C27,DEP!$E$4:$E$55) -> 20
B28: 8 | C28: M.S.P. José Luis Eliazar Torralba Flores | D28: =SUM(E28:O28) -> 4 | E28: =COUNTIF(LCB!$C$4:$C$40,C28) -> 0 | F28: =COUNTIF(LM!$C$4:$C$144,C28) -> 4 | G28: =COUNTIF(LO!$C$4:$C$227,C28) -> 0 | H28: =COUNTIF(LE!$C$4:$C$214,C28) -> 0 | I28: =COUNTIF(LN!$C$4:$C$53,C28) -> 0 | J28: =COUNTIF(LCE!$C$3:$C$43,C28) -> 0 | K28: =COUNTIF(LI!$C$4:$C$60,C28) -> 0 | L28: =COUNTIF(LAP!$C$5:$C$45,C28) -> 0 | M28: =COUNTIF(LGDM!$C$4:$C$22,C28) -> 0 | N28: =COUNTIF(LAM!$C$5:$C$21,C28) -> 0 | O28: =COUNTIF(DEP!$C$3:$C$61,C28) -> 0 | P28: =SUMIF(LCB!$C$4:$C$45,C28,LCB!$F$4:$F$45)+SUMIF(LM!$C$4:$C$140,C28,LM!$F$4:$F$140)+SUMIF(LO!$C$4:$C$230,C28,LO!$F$4:$F$230)+SUMIF(LE!$C$4:$C$200,C28,LE!$F$4:$F$200)+SUMIF(LN!$C$4:$C$48,C28,LN!$F$4:$F$48)+SUMIF(LCE!$C$4:$C$40,C28,LCE!$F$4:$F$40)+SUMIF(LI!$C$4:$C$55,C28,LI!$F$4:$F$55)+SUMIF(LAP!$C$4:$C$45,C28,LAP!$F$4:$F$45)+SUMIF(LGDM!$C$4:$C$22,C28,LGDM!$F$4:$F$22)+SUMIF(LAM!$C$4:$C$18,C28,LAM!$F$4:$F$18)+SUMIF(DEP!$C$4:$C$55,C28,DEP!$F$4:$F$55) -> 114 | Q28: =SUMIF(LCB!$C$4:$C$45,C28,LCB!$E$4:$E$45)+SUMIF(LM!$C$4:$C$140,C28,LM!$E$4:$E$140)+SUMIF(LO!$C$4:$C$230,C28,LO!$E$4:$E$230)+SUMIF(LE!$C$4:$C$200,C28,LE!$E$4:$E$200)+SUMIF(LN!$C$4:$C$48,C28,LN!$E$4:$E$48)+SUMIF(LCE!$C$4:$C$40,C28,LCE!$E$4:$E$40)+SUMIF(LI!$C$4:$C$55,C28,LI!$E$4:$E$55)+SUMIF(LAP!$C$4:$C$45,C28,LAP!$E$4:$E$45)+SUMIF(LGDM!$C$4:$C$15,C28,LGDM!$E$4:$E$15)+SUMIF(LAM!$C$5:$C$18,C28,LAM!$E$5:$E$18)+SUMIF(DEP!$C$4:$C$55,C28,DEP!$E$4:$E$55) -> 22
B29: 9 | C29: Méd. Jennifer de la Luz Santos Santos | D29: =SUM(E29:O29) -> 5 | E29: =COUNTIF(LCB!$C$4:$C$40,C29) -> 0 | F29: =COUNTIF(LM!$C$4:$C$144,C29) -> 1 | G29: =COUNTIF(LO!$C$4:$C$227,C29) -> 4 | H29: =COUNTIF(LE!$C$4:$C$214,C29) -> 0 | I29: =COUNTIF(LN!$C$4:$C$53,C29) -> 0 | J29: =COUNTIF(LCE!$C$3:$C$43,C29) -> 0 | K29: =COUNTIF(LI!$C$4:$C$60,C29) -> 0 | L29: =COUNTIF(LAP!$C$5:$C$45,C29) -> 0 | M29: =COUNTIF(LGDM!$C$4:$C$22,C29) -> 0 | N29: =COUNTIF(LAM!$C$5:$C$21,C29) -> 0 | O29: =COUNTIF(DEP!$C$3:$C$61,C29) -> 0 | P29: =SUMIF(LCB!$C$4:$C$45,C29,LCB!$F$4:$F$45)+SUMIF(LM!$C$4:$C$140,C29,LM!$F$4:$F$140)+SUMIF(LO!$C$4:$C$230,C29,LO!$F$4:$F$230)+SUMIF(LE!$C$4:$C$200,C29,LE!$F$4:$F$200)+SUMIF(LN!$C$4:$C$48,C29,LN!$F$4:$F$48)+SUMIF(LCE!$C$4:$C$40,C29,LCE!$F$4:$F$40)+SUMIF(LI!$C$4:$C$55,C29,LI!$F$4:$F$55)+SUMIF(LAP!$C$4:$C$45,C29,LAP!$F$4:$F$45)+SUMIF(LGDM!$C$4:$C$22,C29,LGDM!$F$4:$F$22)+SUMIF(LAM!$C$4:$C$18,C29,LAM!$F$4:$F$18)+SUMIF(DEP!$C$4:$C$55,C29,DEP!$F$4:$F$55) -> 38 | Q29: =SUMIF(LCB!$C$4:$C$45,C29,LCB!$E$4:$E$45)+SUMIF(LM!$C$4:$C$140,C29,LM!$E$4:$E$140)+SUMIF(LO!$C$4:$C$230,C29,LO!$E$4:$E$230)+SUMIF(LE!$C$4:$C$200,C29,LE!$E$4:$E$200)+SUMIF(LN!$C$4:$C$48,C29,LN!$E$4:$E$48)+SUMIF(LCE!$C$4:$C$40,C29,LCE!$E$4:$E$40)+SUMIF(LI!$C$4:$C$55,C29,LI!$E$4:$E$55)+SUMIF(LAP!$C$4:$C$45,C29,LAP!$E$4:$E$45)+SUMIF(LGDM!$C$4:$C$15,C29,LGDM!$E$4:$E$15)+SUMIF(LAM!$C$5:$C$18,C29,LAM!$E$5:$E$18)+SUMIF(DEP!$C$4:$C$55,C29,DEP!$E$4:$E$55) -> 29
B30: 10 | C30: E.E. Edgar García Casas | D30: =SUM(E30:O30) -> 5 | E30: =COUNTIF(LCB!$C$4:$C$40,C30) -> 0 | F30: =COUNTIF(LM!$C$4:$C$144,C30) -> 5 | G30: =COUNTIF(LO!$C$4:$C$227,C30) -> 0 | H30: =COUNTIF(LE!$C$4:$C$214,C30) -> 0 | I30: =COUNTIF(LN!$C$4:$C$53,C30) -> 0 | J30: =COUNTIF(LCE!$C$3:$C$43,C30) -> 0 | K30: =COUNTIF(LI!$C$4:$C$60,C30) -> 0 | L30: =COUNTIF(LAP!$C$5:$C$45,C30) -> 0 | M30: =COUNTIF(LGDM!$C$4:$C$22,C30) -> 0 | N30: =COUNTIF(LAM!$C$5:$C$21,C30) -> 0 | O30: =COUNTIF(DEP!$C$3:$C$61,C30) -> 0 | P30: =SUMIF(LCB!$C$4:$C$45,C30,LCB!$F$4:$F$45)+SUMIF(LM!$C$4:$C$140,C30,LM!$F$4:$F$140)+SUMIF(LO!$C$4:$C$230,C30,LO!$F$4:$F$230)+SUMIF(LE!$C$4:$C$200,C30,LE!$F$4:$F$200)+SUMIF(LN!$C$4:$C$48,C30,LN!$F$4:$F$48)+SUMIF(LCE!$C$4:$C$40,C30,LCE!$F$4:$F$40)+SUMIF(LI!$C$4:$C$55,C30,LI!$F$4:$F$55)+SUMIF(LAP!$C$4:$C$45,C30,LAP!$F$4:$F$45)+SUMIF(LGDM!$C$4:$C$22,C30,LGDM!$F$4:$F$22)+SUMIF(LAM!$C$4:$C$18,C30,LAM!$F$4:$F$18)+SUMIF(DEP!$C$4:$C$55,C30,DEP!$F$4:$F$55) -> 181 | Q30: =SUMIF(LCB!$C$4:$C$45,C30,LCB!$E$4:$E$45)+SUMIF(LM!$C$4:$C$140,C30,LM!$E$4:$E$140)+SUMIF(LO!$C$4:$C$230,C30,LO!$E$4:$E$230)+SUMIF(LE!$C$4:$C$200,C30,LE!$E$4:$E$200)+SUMIF(LN!$C$4:$C$48,C30,LN!$E$4:$E$48)+SUMIF(LCE!$C$4:$C$40,C30,LCE!$E$4:$E$40)+SUMIF(LI!$C$4:$C$55,C30,LI!$E$4:$E$55)+SUMIF(LAP!$C$4:$C$45,C30,LAP!$E$4:$E$45)+SUMIF(LGDM!$C$4:$C$15,C30,LGDM!$E$4:$E$15)+SUMIF(LAM!$C$5:$C$18,C30,LAM!$E$5:$E$18)+SUMIF(DEP!$C$4:$C$55,C30,DEP!$E$4:$E$55) -> 22
B31: 11 | C31: Méd. Xochiquetzalli García Mendoza | D31: =SUM(E31:O31) -> 5 | E31: =COUNTIF(LCB!$C$4:$C$40,C31) -> 0 | F31: =COUNTIF(LM!$C$4:$C$144,C31) -> 0 | G31: =COUNTIF(LO!$C$4:$C$227,C31) -> 2 | H31: =COUNTIF(LE!$C$4:$C$214,C31) -> 3 | I31: =COUNTIF(LN!$C$4:$C$53,C31) -> 0 | J31: =COUNTIF(LCE!$C$3:$C$43,C31) -> 0 | K31: =COUNTIF(LI!$C$4:$C$60,C31) -> 0 | L31: =COUNTIF(LAP!$C$5:$C$45,C31) -> 0 | M31: =COUNTIF(LGDM!$C$4:$C$22,C31) -> 0 | N31: =COUNTIF(LAM!$C$5:$C$21,C31) -> 0 | O31: =COUNTIF(DEP!$C$3:$C$61,C31) -> 0 | P31: =SUMIF(LCB!$C$4:$C$45,C31,LCB!$F$4:$F$45)+SUMIF(LM!$C$4:$C$140,C31,LM!$F$4:$F$140)+SUMIF(LO!$C$4:$C$230,C31,LO!$F$4:$F$230)+SUMIF(LE!$C$4:$C$200,C31,LE!$F$4:$F$200)+SUMIF(LN!$C$4:$C$48,C31,LN!$F$4:$F$48)+SUMIF(LCE!$C$4:$C$40,C31,LCE!$F$4:$F$40)+SUMIF(LI!$C$4:$C$55,C31,LI!$F$4:$F$55)+SUMIF(LAP!$C$4:$C$45,C31,LAP!$F$4:$F$45)+SUMIF(LGDM!$C$4:$C$22,C31,LGDM!$F$4:$F$22)+SUMIF(LAM!$C$4:$C$18,C31,LAM!$F$4:$F$18)+SUMIF(DEP!$C$4:$C$55,C31,DEP!$F$4:$F$55) -> 92 | Q31: =SUMIF(LCB!$C$4:$C$45,C31,LCB!$E$4:$E$45)+SUMIF(LM!$C$4:$C$140,C31,LM!$E$4:$E$140)+SUMIF(LO!$C$4:$C$230,C31,LO!$E$4:$E$230)+SUMIF(LE!$C$4:$C$200,C31,LE!$E$4:$E$200)+SUMIF(LN!$C$4:$C$48,C31,LN!$E$4:$E$48)+SUMIF(LCE!$C$4:$C$40,C31,LCE!$E$4:$E$40)+SUMIF(LI!$C$4:$C$55,C31,LI!$E$4:$E$55)+SUMIF(LAP!$C$4:$C$45,C31,LAP!$E$4:$E$45)+SUMIF(LGDM!$C$4:$C$15,C31,LGDM!$E$4:$E$15)+SUMIF(LAM!$C$5:$C$18,C31,LAM!$E$5:$E$18)+SUMIF(DEP!$C$4:$C$55,C31,DEP!$E$4:$E$55) -> 27
B32: 12 | C32: E.N. Daniela Ruiz Ramírez | D32: =SUM(E32:O32) -> 5 | E32: =COUNTIF(LCB!$C$4:$C$40,C32) -> 0 | F32: =COUNTIF(LM!$C$4:$C$144,C32) -> 5 | G32: =COUNTIF(LO!$C$4:$C$227,C32) -> 0 | H32: =COUNTIF(LE!$C$4:$C$214,C32) -> 0 | I32: =COUNTIF(LN!$C$4:$C$53,C32) -> 0 | J32: =COUNTIF(LCE!$C$3:$C$43,C32) -> 0 | K32: =COUNTIF(LI!$C$4:$C$60,C32) -> 0 | L32: =COUNTIF(LAP!$C$5:$C$45,C32) -> 0 | M32: =COUNTIF(LGDM!$C$4:$C$22,C32) -> 0 | N32: =COUNTIF(LAM!$C$5:$C$21,C32) -> 0 | O32: =COUNTIF(DEP!$C$3:$C$61,C32) -> 0 | P32: =SUMIF(LCB!$C$4:$C$45,C32,LCB!$F$4:$F$45)+SUMIF(LM!$C$4:$C$140,C32,LM!$F$4:$F$140)+SUMIF(LO!$C$4:$C$230,C32,LO!$F$4:$F$230)+SUMIF(LE!$C$4:$C$200,C32,LE!$F$4:$F$200)+SUMIF(LN!$C$4:$C$48,C32,LN!$F$4:$F$48)+SUMIF(LCE!$C$4:$C$40,C32,LCE!$F$4:$F$40)+SUMIF(LI!$C$4:$C$55,C32,LI!$F$4:$F$55)+SUMIF(LAP!$C$4:$C$45,C32,LAP!$F$4:$F$45)+SUMIF(LGDM!$C$4:$C$22,C32,LGDM!$F$4:$F$22)+SUMIF(LAM!$C$4:$C$18,C32,LAM!$F$4:$F$18)+SUMIF(DEP!$C$4:$C$55,C32,DEP!$F$4:$F$55) -> 203 | Q32: =SUMIF(LCB!$C$4:$C$45,C32,LCB!$E$4:$E$45)+SUMIF(LM!$C$4:$C$140,C32,LM!$E$4:$E$140)+SUMIF(LO!$C$4:$C$230,C32,LO!$E$4:$E$230)+SUMIF(LE!$C$4:$C$200,C32,LE!$E$4:$E$200)+SUMIF(LN!$C$4:$C$48,C32,LN!$E$4:$E$48)+SUMIF(LCE!$C$4:$C$40,C32,LCE!$E$4:$E$40)+SUMIF(LI!$C$4:$C$55,C32,LI!$E$4:$E$55)+SUMIF(LAP!$C$4:$C$45,C32,LAP!$E$4:$E$45)+SUMIF(LGDM!$C$4:$C$15,C32,LGDM!$E$4:$E$15)+SUMIF(LAM!$C$5:$C$18,C32,LAM!$E$5:$E$18)+SUMIF(DEP!$C$4:$C$55,C32,DEP!$E$4:$E$55) -> 27
... B50: 30 | C50: M.S.P. Adrián Gabriel Delgado Lara | D50: =SUM(E50:O50) -> 0 | E50: =COUNTIF(LCB!$C$4:$C$40,C50) -> 0 | F50: =COUNTIF(LM!$C$4:$C$144,C50) -> 0 | G50: =COUNTIF(LO!$C$4:$C$227,C50) -> 0 | H50: =COUNTIF(LE!$C$4:$C$214,C50) -> 0 | I50: =COUNTIF(LN!$C$4:$C$53,C50) -> 0 | J50: =COUNTIF(LCE!$C$3:$C$43,C50) -> 0 | K50: =COUNTIF(LI!$C$4:$C$60,C50) -> 0 | L50: =COUNTIF(LAP!$C$5:$C$45,C50) -> 0 | M50: =COUNTIF(LGDM!$C$4:$C$22,C50) -> 0 | N50: =COUNTIF(LAM!$C$5:$C$21,C50) -> 0 | O50: =COUNTIF(DEP!$C$3:$C$61,C50) -> 0 | P50: =SUMIF(LCB!$C$4:$C$45,C50,LCB!$F$4:$F$45)+SUMIF(LM!$C$4:$C$140,C50,LM!$F$4:$F$140)+SUMIF(LO!$C$4:$C$230,C50,LO!$F$4:$F$230)+SUMIF(LE!$C$4:$C$200,C50,LE!$F$4:$F$200)+SUMIF(LN!$C$4:$C$48,C50,LN!$F$4:$F$48)+SUMIF(LCE!$C$4:$C$40,C50,LCE!$F$4:$F$40)+SUMIF(LI!$C$4:$C$55,C50,LI!$F$4:$F$55)+SUMIF(LAP!$C$4:$C$45,C50,LAP!$F$4:$F$45)+SUMIF(LGDM!$C$4:$C$22,C50,LGDM!$F$4:$F$22)+SUMIF(LAM!$C$4:$C$18,C50,LAM!$F$4:$F$18)+SUMIF(DEP!$C$4:$C$55,C50,DEP!$F$4:$F$55) -> 0 | Q50: =SUMIF(LCB!$C$4:$C$45,C50,LCB!$E$4:$E$45)+SUMIF(LM!$C$4:$C$140,C50,LM!$E$4:$E$140)+SUMIF(LO!$C$4:$C$230,C50,LO!$E$4:$E$230)+SUMIF(LE!$C$4:$C$200,C50,LE!$E$4:$E$200)+SUMIF(LN!$C$4:$C$48,C50,LN!$E$4:$E$48)+SUMIF(LCE!$C$4:$C$40,C50,LCE!$E$4:$E$40)+SUMIF(LI!$C$4:$C$55,C50,LI!$E$4:$E$55)+SUMIF(LAP!$C$4:$C$45,C50,LAP!$E$4:$E$45)+SUMIF(LGDM!$C$4:$C$15,C50,LGDM!$E$4:$E$15)+SUMIF(LAM!$C$5:$C$18,C50,LAM!$E$5:$E$18)+SUMIF(DEP!$C$4:$C$55,C50,DEP!$E$4:$E$55) -> 0
B55: LO | C55: Profesor@ | D55: Materias | E55: LCB | F55: LM | G55: LO | H55: LE | I55: LN | J55: LCE | K55: LI | L55: LAP | M55: LGDM | N55: LAM | O55: DEP | P55: Total alumnos | Q55: Total hrs sem
B56: 1 | C56: L.O. Damary López Reyes | D56: =SUM(E56:O56) -> 2 | E56: =COUNTIF(LCB!$C$4:$C$40,C56) -> 0 | F56: =COUNTIF(LM!$C$4:$C$144,C56) -> 0 | G56: =COUNTIF(LO!$C$4:$C$227,C56) -> 2 | H56: =COUNTIF(LE!$C$4:$C$214,C56) -> 0 | I56: =COUNTIF(LN!$C$4:$C$53,C56) -> 0 | J56: =COUNTIF(LCE!$C$3:$C$43,C56) -> 0 | K56: =COUNTIF(LI!$C$4:$C$60,C56) -> 0 | L56: =COUNTIF(LAP!$C$5:$C$45,C56) -> 0 | M56: =COUNTIF(LGDM!$C$4:$C$22,C56) -> 0 | N56: =COUNTIF(LAM!$C$5:$C$21,C56) -> 0 | O56: =COUNTIF(DEP!$C$3:$C$61,C56) -> 0 | P56: =SUMIF(LCB!$C$4:$C$45,C56,LCB!$F$4:$F$45)+SUMIF(LM!$C$4:$C$140,C56,LM!$F$4:$F$140)+SUMIF(LO!$C$4:$C$230,C56,LO!$F$4:$F$230)+SUMIF(LE!$C$4:$C$200,C56,LE!$F$4:$F$200)+SUMIF(LN!$C$4:$C$48,C56,LN!$F$4:$F$48)+SUMIF(LCE!$C$4:$C$40,C56,LCE!$F$4:$F$40)+SUMIF(LI!$C$4:$C$55,C56,LI!$F$4:$F$55)+SUMIF(LAP!$C$4:$C$45,C56,LAP!$F$4:$F$45)+SUMIF(LGDM!$C$4:$C$22,C56,LGDM!$F$4:$F$22)+SUMIF(LAM!$C$4:$C$18,C56,LAM!$F$4:$F$18)+SUMIF(DEP!$C$4:$C$55,C56,DEP!$F$4:$F$55) -> 64 | Q56: =SUMIF(LCB!$C$4:$C$45,C56,LCB!$E$4:$E$45)+SUMIF(LM!$C$4:$C$140,C56,LM!$E$4:$E$140)+SUMIF(LO!$C$4:$C$230,C56,LO!$E$4:$E$230)+SUMIF(LE!$C$4:$C$200,C56,LE!$E$4:$E$200)+SUMIF(LN!$C$4:$C$48,C56,LN!$E$4:$E$48)+SUMIF(LCE!$C$4:$C$40,C56,LCE!$E$4:$E$40)+SUMIF(LI!$C$4:$C$55,C56,LI!$E$4:$E$55)+SUMIF(LAP!$C$4:$C$45,C56,LAP!$E$4:$E$45)+SUMIF(LGDM!$C$4:$C$15,C56,LGDM!$E$4:$E$15)+SUMIF(LAM!$C$5:$C$18,C56,LAM!$E$5:$E$18)+SUMIF(DEP!$C$4:$C$55,C56,DEP!$E$4:$E$55) -> 10
B57: 2 | C57: C.D. Javier López Reyes | D57: =SUM(E57:O57) -> 5 | E57: =COUNTIF(LCB!$C$4:$C$40,C57) -> 0 | F57: =COUNTIF(LM!$C$4:$C$144,C57) -> 0 | G57: =COUNTIF(LO!$C$4:$C$227,C57) -> 5 | H57: =COUNTIF(LE!$C$4:$C$214,C57) -> 0 | I57: =COUNTIF(LN!$C$4:$C$53,C57) -> 0 | J57: =COUNTIF(LCE!$C$3:$C$43,C57) -> 0 | K57: =COUNTIF(LI!$C$4:$C$60,C57) -> 0 | L57: =COUNTIF(LAP!$C$5:$C$45,C57) -> 0 | M57: =COUNTIF(LGDM!$C$4:$C$22,C57) -> 0 | N57: =COUNTIF(LAM!$C$5:$C$21,C57) -> 0 | O57: =COUNTIF(DEP!$C$3:$C$61,C57) -> 0 | P57: =SUMIF(LCB!$C$4:$C$45,C57,LCB!$F$4:$F$45)+SUMIF(LM!$C$4:$C$140,C57,LM!$F$4:$F$140)+SUMIF(LO!$C$4:$C$230,C57,LO!$F$4:$F$230)+SUMIF(LE!$C$4:$C$200,C57,LE!$F$4:$F$200)+SUMIF(LN!$C$4:$C$48,C57,LN!$F$4:$F$48)+SUMIF(LCE!$C$4:$C$40,C57,LCE!$F$4:$F$40)+SUMIF(LI!$C$4:$C$55,C57,LI!$F$4:$F$55)+SUMIF(LAP!$C$4:$C$45,C57,LAP!$F$4:$F$45)+SUMIF(LGDM!$C$4:$C$22,C57,LGDM!$F$4:$F$22)+SUMIF(LAM!$C$4:$C$18,C57,LAM!$F$4:$F$18)+SUMIF(DEP!$C$4:$C$55,C57,DEP!$F$4:$F$55) -> 128 | Q57: =SUMIF(LCB!$C$4:$C$45,C57,LCB!$E$4:$E$45)+SUMIF(LM!$C$4:$C$140,C57,LM!$E$4:$E$140)+SUMIF(LO!$C$4:$C$230,C57,LO!$E$4:$E$230)+SUMIF(LE!$C$4:$C$200,C57,LE!$E$4:$E$200)+SUMIF(LN!$C$4:$C$48,C57,LN!$E$4:$E$48)+SUMIF(LCE!$C$4:$C$40,C57,LCE!$E$4:$E$40)+SUMIF(LI!$C$4:$C$55,C57,LI!$E$4:$E$55)+SUMIF(LAP!$C$4:$C$45,C57,LAP!$E$4:$E$45)+SUMIF(LGDM!$C$4:$C$15,C57,LGDM!$E$4:$E$15)+SUMIF(LAM!$C$5:$C$18,C57,LAM!$E$5:$E$18)+SUMIF(DEP!$C$4:$C$55,C57,DEP!$E$4:$E$55) -> 30
B58: 3 | C58: C.D. Katia Cecilia González Vázquez | D58: =SUM(E58:O58) -> 5 | E58: =COUNTIF(LCB!$C$4:$C$40,C58) -> 0 | F58: =COUNTIF(LM!$C$4:$C$144,C58) -> 0 | G58: =COUNTIF(LO!$C$4:$C$227,C58) -> 5 | H58: =COUNTIF(LE!$C$4:$C$214,C58) -> 0 | I58: =COUNTIF(LN!$C$4:$C$53,C58) -> 0 | J58: =COUNTIF(LCE!$C$3:$C$43,C58) -> 0 | K58: =COUNTIF(LI!$C$4:$C$60,C58) -> 0 | L58: =COUNTIF(LAP!$C$5:$C$45,C58) -> 0 | M58: =COUNTIF(LGDM!$C$4:$C$22,C58) -> 0 | N58: =COUNTIF(LAM!$C$5:$C$21,C58) -> 0 | O58: =COUNTIF(DEP!$C$3:$C$61,C58) -> 0 | P58: =SUMIF(LCB!$C$4:$C$45,C58,LCB!$F$4:$F$45)+SUMIF(LM!$C$4:$C$140,C58,LM!$F$4:$F$140)+SUMIF(LO!$C$4:$C$230,C58,LO!$F$4:$F$230)+SUMIF(LE!$C$4:$C$200,C58,LE!$F$4:$F$200)+SUMIF(LN!$C$4:$C$48,C58,LN!$F$4:$F$48)+SUMIF(LCE!$C$4:$C$40,C58,LCE!$F$4:$F$40)+SUMIF(LI!$C$4:$C$55,C58,LI!$F$4:$F$55)+SUMIF(LAP!$C$4:$C$45,C58,LAP!$F$4:$F$45)+SUMIF(LGDM!$C$4:$C$22,C58,LGDM!$F$4:$F$22)+SUMIF(LAM!$C$4:$C$18,C58,LAM!$F$4:$F$18)+SUMIF(DEP!$C$4:$C$55,C58,DEP!$F$4:$F$55) -> 144 | Q58: =SUMIF(LCB!$C$4:$C$45,C58,LCB!$E$4:$E$45)+SUMIF(LM!$C$4:$C$140,C58,LM!$E$4:$E$140)+SUMIF(LO!$C$4:$C$230,C58,LO!$E$4:$E$230)+SUMIF(LE!$C$4:$C$200,C58,LE!$E$4:$E$200)+SUMIF(LN!$C$4:$C$48,C58,LN!$E$4:$E$48)+SUMIF(LCE!$C$4:$C$40,C58,LCE!$E$4:$E$40)+SUMIF(LI!$C$4:$C$55,C58,LI!$E$4:$E$55)+SUMIF(LAP!$C$4:$C$45,C58,LAP!$E$4:$E$45)+SUMIF(LGDM!$C$4:$C$15,C58,LGDM!$E$4:$E$15)+SUMIF(LAM!$C$5:$C$18,C58,LAM!$E$5:$E$18)+SUMIF(DEP!$C$4:$C$55,C58,DEP!$E$4:$E$55) -> 30
B59: 4 | C59: M.E. Laura Alejandra Mora González | D59: =SUM(E59:O59) -> 5 | E59: =COUNTIF(LCB!$C$4:$C$40,C59) -> 0 | F59: =COUNTIF(LM!$C$4:$C$144,C59) -> 0 | G59: =COUNTIF(LO!$C$4:$C$227,C59) -> 5 | H59: =COUNTIF(LE!$C$4:$C$214,C59) -> 0 | I59: =COUNTIF(LN!$C$4:$C$53,C59) -> 0 | J59: =COUNTIF(LCE!$C$3:$C$43,C59) -> 0 | K59: =COUNTIF(LI!$C$4:$C$60,C59) -> 0 | L59: =COUNTIF(LAP!$C$5:$C$45,C59) -> 0 | M59: =COUNTIF(LGDM!$C$4:$C$22,C59) -> 0 | N59: =COUNTIF(LAM!$C$5:$C$21,C59) -> 0 | O59: =COUNTIF(DEP!$C$3:$C$61,C59) -> 0 | P59: =SUMIF(LCB!$C$4:$C$45,C59,LCB!$F$4:$F$45)+SUMIF(LM!$C$4:$C$140,C59,LM!$F$4:$F$140)+SUMIF(LO!$C$4:$C$230,C59,LO!$F$4:$F$230)+SUMIF(LE!$C$4:$C$200,C59,LE!$F$4:$F$200)+SUMIF(LN!$C$4:$C$48,C59,LN!$F$4:$F$48)+SUMIF(LCE!$C$4:$C$40,C59,LCE!$F$4:$F$40)+SUMIF(LI!$C$4:$C$55,C59,LI!$F$4:$F$55)+SUMIF(LAP!$C$4:$C$45,C59,LAP!$F$4:$F$45)+SUMIF(LGDM!$C$4:$C$22,C59,LGDM!$F$4:$F$22)+SUMIF(LAM!$C$4:$C$18,C59,LAM!$F$4:$F$18)+SUMIF(DEP!$C$4:$C$55,C59,DEP!$F$4:$F$55) -> 144 | Q59: =SUMIF(LCB!$C$4:$C$45,C59,LCB!$E$4:$E$45)+SUMIF(LM!$C$4:$C$140,C59,LM!$E$4:$E$140)+SUMIF(LO!$C$4:$C$230,C59,LO!$E$4:$E$230)+SUMIF(LE!$C$4:$C$200,C59,LE!$E$4:$E$200)+SUMIF(LN!$C$4:$C$48,C59,LN!$E$4:$E$48)+SUMIF(LCE!$C$4:$C$40,C59,LCE!$E$4:$E$40)+SUMIF(LI!$C$4:$C$55,C59,LI!$E$4:$E$55)+SUMIF(LAP!$C$4:$C$45,C59,LAP!$E$4:$E$45)+SUMIF(LGDM!$C$4:$C$15,C59,LGDM!$E$4:$E$15)+SUMIF(LAM!$C$5:$C$18,C59,LAM!$E$5:$E$18)+SUMIF(DEP!$C$4:$C$55,C59,DEP!$E$4:$E$55) -> 30
B60: 5 | C60: C.D. Mauricio González Osorio | D60: =SUM(E60:O60) -> 4 | E60: =COUNTIF(LCB!$C$4:$C$40,C60) -> 0 | F60: =COUNTIF(LM!$C$4:$C$144,C60) -> 0 | G60: =COUNTIF(LO!$C$4:$C$227,C60) -> 4 | H60: =COUNTIF(LE!$C$4:$C$214,C60) -> 0 | I60: =COUNTIF(LN!$C$4:$C$53,C60) -> 0 | J60: =COUNTIF(LCE!$C$3:$C$43,C60) -> 0 | K60: =COUNTIF(LI!$C$4:$C$60,C60) -> 0 | L60: =COUNTIF(LAP!$C$5:$C$45,C60) -> 0 | M60: =COUNTIF(LGDM!$C$4:$C$22,C60) -> 0 | N60: =COUNTIF(LAM!$C$5:$C$21,C60) -> 0 | O60: =COUNTIF(DEP!$C$3:$C$61,C60) -> 0 | P60: =SUMIF(LCB!$C$4:$C$45,C60,LCB!$F$4:$F$45)+SUMIF(LM!$C$4:$C$140,C60,LM!$F$4:$F$140)+SUMIF(LO!$C$4:$C$230,C60,LO!$F$4:$F$230)+SUMIF(LE!$C$4:$C$200,C60,LE!$F$4:$F$200)+SUMIF(LN!$C$4:$C$48,C60,LN!$F$4:$F$48)+SUMIF(LCE!$C$4:$C$40,C60,LCE!$F$4:$F$40)+SUMIF(LI!$C$4:$C$55,C60,LI!$F$4:$F$55)+SUMIF(LAP!$C$4:$C$45,C60,LAP!$F$4:$F$45)+SUMIF(LGDM!$C$4:$C$22,C60,LGDM!$F$4:$F$22)+SUMIF(LAM!$C$4:$C$18,C60,LAM!$F$4:$F$18)+SUMIF(DEP!$C$4:$C$55,C60,DEP!$F$4:$F$55) -> 96 | Q60: =SUMIF(LCB!$C$4:$C$45,C60,LCB!$E$4:$E$45)+SUMIF(LM!$C$4:$C$140,C60,LM!$E$4:$E$140)+SUMIF(LO!$C$4:$C$230,C60,LO!$E$4:$E$230)+SUMIF(LE!$C$4:$C$200,C60,LE!$E$4:$E$200)+SUMIF(LN!$C$4:$C$48,C60,LN!$E$4:$E$48)+SUMIF(LCE!$C$4:$C$40,C60,LCE!$E$4:$E$40)+SUMIF(LI!$C$4:$C$55,C60,LI!$E$4:$E$55)+SUMIF(LAP!$C$4:$C$45,C60,LAP!$E$4:$E$45)+SUMIF(LGDM!$C$4:$C$15,C60,LGDM!$E$4:$E$15)+SUMIF(LAM!$C$5:$C$18,C60,LAM!$E$5:$E$18)+SUMIF(DEP!$C$4:$C$55,C60,DEP!$E$4:$E$55) -> 25
B61: 6 | C61: Dr. José Eduardo Orellana Centeno | D61: =SUM(E61:O61) -> 4 | E61: =COUNTIF(LCB!$C$4:$C$40,C61) -> 0 | F61: =COUNTIF(LM!$C$4:$C$144,C61) -> 0 | G61: =COUNTIF(LO!$C$4:$C$227,C61) -> 3 | H61: =COUNTIF(LE!$C$4:$C$214,C61) -> 0 | I61: =COUNTIF(LN!$C$4:$C$53,C61) -> 0 | J61: =COUNTIF(LCE!$C$3:$C$43,C61) -> 0 | K61: =COUNTIF(LI!$C$4:$C$60,C61) -> 0 | L61: =COUNTIF(LAP!$C$5:$C$45,C61) -> 0 | M61: =COUNTIF(LGDM!$C$4:$C$22,C61) -> 0 | N61: =COUNTIF(LAM!$C$5:$C$21,C61) -> 0 | O61: =COUNTIF(DEP!$C$3:$C$61,C61) -> 1 | P61: =SUMIF(LCB!$C$4:$C$45,C61,LCB!$F$4:$F$45)+SUMIF(LM!$C$4:$C$140,C61,LM!$F$4:$F$140)+SUMIF(LO!$C$4:$C$230,C61,LO!$F$4:$F$230)+SUMIF(LE!$C$4:$C$200,C61,LE!$F$4:$F$200)+SUMIF(LN!$C$4:$C$48,C61,LN!$F$4:$F$48)+SUMIF(LCE!$C$4:$C$40,C61,LCE!$F$4:$F$40)+SUMIF(LI!$C$4:$C$55,C61,LI!$F$4:$F$55)+SUMIF(LAP!$C$4:$C$45,C61,LAP!$F$4:$F$45)+SUMIF(LGDM!$C$4:$C$22,C61,LGDM!$F$4:$F$22)+SUMIF(LAM!$C$4:$C$18,C61,LAM!$F$4:$F$18)+SUMIF(DEP!$C$4:$C$55,C61,DEP!$F$4:$F$55) -> 120 | Q61: =SUMIF(LCB!$C$4:$C$45,C61,LCB!$E$4:$E$45)+SUMIF(LM!$C$4:$C$140,C61,LM!$E$4:$E$140)+SUMIF(LO!$C$4:$C$230,C61,LO!$E$4:$E$230)+SUMIF(LE!$C$4:$C$200,C61,LE!$E$4:$E$200)+SUMIF(LN!$C$4:$C$48,C61,LN!$E$4:$E$48)+SUMIF(LCE!$C$4:$C$40,C61,LCE!$E$4:$E$40)+SUMIF(LI!$C$4:$C$55,C61,LI!$E$4:$E$55)+SUMIF(LAP!$C$4:$C$45,C61,LAP!$E$4:$E$45)+SUMIF(LGDM!$C$4:$C$15,C61,LGDM!$E$4:$E$15)+SUMIF(LAM!$C$5:$C$18,C61,LAM!$E$5:$E$18)+SUMIF(DEP!$C$4:$C$55,C61,DEP!$E$4:$E$55) -> 19
B62: 7 | C62: C.D. Jesús Cruz Velazquez | D62: =SUM(E62:O62) -> 4 | E62: =COUNTIF(LCB!$C$4:$C$40,C62) -> 0 | F62: =COUNTIF(LM!$C$4:$C$144,C62) -> 0 | G62: =COUNTIF(LO!$C$4:$C$227,C62) -> 4 | H62: =COUNTIF(LE!$C$4:$C$214,C62) -> 0 | I62: =COUNTIF(LN!$C$4:$C$53,C62) -> 0 | J62: =COUNTIF(LCE!$C$3:$C$43,C62) -> 0 | K62: =COUNTIF(LI!$C$4:$C$60,C62) -> 0 | L62: =COUNTIF(LAP!$C$5:$C$45,C62) -> 0 | M62: =COUNTIF(LGDM!$C$4:$C$22,C62) -> 0 | N62: =COUNTIF(LAM!$C$5:$C$21,C62) -> 0 | O62: =COUNTIF(DEP!$C$3:$C$61,C62) -> 0 | P62: =SUMIF(LCB!$C$4:$C$45,C62,LCB!$F$4:$F$45)+SUMIF(LM!$C$4:$C$140,C62,LM!$F$4:$F$140)+SUMIF(LO!$C$4:$C$230,C62,LO!$F$4:$F$230)+SUMIF(LE!$C$4:$C$200,C62,LE!$F$4:$F$200)+SUMIF(LN!$C$4:$C$48,C62,LN!$F$4:$F$48)+SUMIF(LCE!$C$4:$C$40,C62,LCE!$F$4:$F$40)+SUMIF(LI!$C$4:$C$55,C62,LI!$F$4:$F$55)+SUMIF(LAP!$C$4:$C$45,C62,LAP!$F$4:$F$45)+SUMIF(LGDM!$C$4:$C$22,C62,LGDM!$F$4:$F$22)+SUMIF(LAM!$C$4:$C$18,C62,LAM!$F$4:$F$18)+SUMIF(DEP!$C$4:$C$55,C62,DEP!$F$4:$F$55) -> 102 | Q62: =SUMIF(LCB!$C$4:$C$45,C62,LCB!$E$4:$E$45)+SUMIF(LM!$C$4:$C$140,C62,LM!$E$4:$E$140)+SUMIF(LO!$C$4:$C$230,C62,LO!$E$4:$E$230)+SUMIF(LE!$C$4:$C$200,C62,LE!$E$4:$E$200)+SUMIF(LN!$C$4:$C$48,C62,LN!$E$4:$E$48)+SUMIF(LCE!$C$4:$C$40,C62,LCE!$E$4:$E$40)+SUMIF(LI!$C$4:$C$55,C62,LI!$E$4:$E$55)+SUMIF(LAP!$C$4:$C$45,C62,LAP!$E$4:$E$45)+SUMIF(LGDM!$C$4:$C$15,C62,LGDM!$E$4:$E$15)+SUMIF(LAM!$C$5:$C$18,C62,LAM!$E$5:$E$18)+SUMIF(DEP!$C$4:$C$55,C62,DEP!$E$4:$E$55) -> 25
B63: 8 | C63: C.D. Luis Bernardo Martínez Martínez | D63: =SUM(E63:O63) -> 5 | E63: =COUNTIF(LCB!$C$4:$C$40,C63) -> 0 | F63: =COUNTIF(LM!$C$4:$C$144,C63) -> 0 | G63: =COUNTIF(LO!$C$4:$C$227,C63) -> 5 | H63: =COUNTIF(LE!$C$4:$C$214,C63) -> 0 | I63: =COUNTIF(LN!$C$4:$C$53,C63) -> 0 | J63: =COUNTIF(LCE!$C$3:$C$43,C63) -> 0 | K63: =COUNTIF(LI!$C$4:$C$60,C63) -> 0 | L63: =COUNTIF(LAP!$C$5:$C$45,C63) -> 0 | M63: =COUNTIF(LGDM!$C$4:$C$22,C63) -> 0 | N63: =COUNTIF(LAM!$C$5:$C$21,C63) -> 0 | O63: =COUNTIF(DEP!$C$3:$C$61,C63) -> 0 | P63: =SUMIF(LCB!$C$4:$C$45,C63,LCB!$F$4:$F$45)+SUMIF(LM!$C$4:$C$140,C63,LM!$F$4:$F$140)+SUMIF(LO!$C$4:$C$230,C63,LO!$F$4:$F$230)+SUMIF(LE!$C$4:$C$200,C63,LE!$F$4:$F$200)+SUMIF(LN!$C$4:$C$48,C63,LN!$F$4:$F$48)+SUMIF(LCE!$C$4:$C$40,C63,LCE!$F$4:$F$40)+SUMIF(LI!$C$4:$C$55,C63,LI!$F$4:$F$55)+SUMIF(LAP!$C$4:$C$45,C63,LAP!$F$4:$F$45)+SUMIF(LGDM!$C$4:$C$22,C63,LGDM!$F$4:$F$22)+SUMIF(LAM!$C$4:$C$18,C63,LAM!$F$4:$F$18)+SUMIF(DEP!$C$4:$C$55,C63,DEP!$F$4:$F$55) -> 80 | Q63: =SUMIF(LCB!$C$4:$C$45,C63,LCB!$E$4:$E$45)+SUMIF(LM!$C$4:$C$140,C63,LM!$E$4:$E$140)+SUMIF(LO!$C$4:$C$230,C63,LO!$E$4:$E$230)+SUMIF(LE!$C$4:$C$200,C63,LE!$E$4:$E$200)+SUMIF(LN!$C$4:$C$48,C63,LN!$E$4:$E$48)+SUMIF(LCE!$C$4:$C$40,C63,LCE!$E$4:$E$40)+SUMIF(LI!$C$4:$C$55,C63,LI!$E$4:$E$55)+SUMIF(LAP!$C$4:$C$45,C63,LAP!$E$4:$E$45)+SUMIF(LGDM!$C$4:$C$15,C63,LGDM!$E$4:$E$15)+SUMIF(LAM!$C$5:$C$18,C63,LAM!$E$5:$E$18)+SUMIF(DEP!$C$4:$C$55,C63,DEP!$E$4:$E$55) -> 32
B64: 9 | C64: L.O. Zoe Mabel Méndez Cruz | D64: =SUM(E64:O64) -> 5 | E64: =COUNTIF(LCB!$C$4:$C$40,C64) -> 0 | F64: =COUNTIF(LM!$C$4:$C$144,C64) -> 0 | G64: =COUNTIF(LO!$C$4:$C$227,C64) -> 5 | H64: =COUNTIF(LE!$C$4:$C$214,C64) -> 0 | I64: =COUNTIF(LN!$C$4:$C$53,C64) -> 0 | J64: =COUNTIF(LCE!$C$3:$C$43,C64) -> 0 | K64: =COUNTIF(LI!$C$4:$C$60,C64) -> 0 | L64: =COUNTIF(LAP!$C$5:$C$45,C64) -> 0 | M64: =COUNTIF(LGDM!$C$4:$C$22,C64) -> 0 | N64: =COUNTIF(LAM!$C$5:$C$21,C64) -> 0 | O64: =COUNTIF(DEP!$C$3:$C$61,C64) -> 0 | P64: =SUMIF(LCB!$C$4:$C$45,C64,LCB!$F$4:$F$45)+SUMIF(LM!$C$4:$C$140,C64,LM!$F$4:$F$140)+SUMIF(LO!$C$4:$C$230,C64,LO!$F$4:$F$230)+SUMIF(LE!$C$4:$C$200,C64,LE!$F$4:$F$200)+SUMIF(LN!$C$4:$C$48,C64,LN!$F$4:$F$48)+SUMIF(LCE!$C$4:$C$40,C64,LCE!$F$4:$F$40)+SUMIF(LI!$C$4:$C$55,C64,LI!$F$4:$F$55)+SUMIF(LAP!$C$4:$C$45,C64,LAP!$F$4:$F$45)+SUMIF(LGDM!$C$4:$C$22,C64,LGDM!$F$4:$F$22)+SUMIF(LAM!$C$4:$C$18,C64,LAM!$F$4:$F$18)+SUMIF(DEP!$C$4:$C$55,C64,DEP!$F$4:$F$55) -> 136 | Q64: =SUMIF(LCB!$C$4:$C$45,C64,LCB!$E$4:$E$45)+SUMIF(LM!$C$4:$C$140,C64,LM!$E$4:$E$140)+SUMIF(LO!$C$4:$C$230,C64,LO!$E$4:$E$230)+SUMIF(LE!$C$4:$C$200,C64,LE!$E$4:$E$200)+SUMIF(LN!$C$4:$C$48,C64,LN!$E$4:$E$48)+SUMIF(LCE!$C$4:$C$40,C64,LCE!$E$4:$E$40)+SUMIF(LI!$C$4:$C$55,C64,LI!$E$4:$E$55)+SUMIF(LAP!$C$4:$C$45,C64,LAP!$E$4:$E$45)+SUMIF(LGDM!$C$4:$C$15,C64,LGDM!$E$4:$E$15)+SUMIF(LAM!$C$5:$C$18,C64,LAM!$E$5:$E$18)+SUMIF(DEP!$C$4:$C$55,C64,DEP!$E$4:$E$55) -> 30
B65: 10 | C65: L.O. Yamile Yolotzin Vásquez Ríos | D65: =SUM(E65:O65) -> 5 | E65: =COUNTIF(LCB!$C$4:$C$40,C65) -> 0 | F65: =COUNTIF(LM!$C$4:$C$144,C65) -> 0 | G65: =COUNTIF(LO!$C$4:$C$227,C65) -> 5 | H65: =COUNTIF(LE!$C$4:$C$214,C65) -> 0 | I65: =COUNTIF(LN!$C$4:$C$53,C65) -> 0 | J65: =COUNTIF(LCE!$C$3:$C$43,C65) -> 0 | K65: =COUNTIF(LI!$C$4:$C$60,C65) -> 0 | L65: =COUNTIF(LAP!$C$5:$C$45,C65) -> 0 | M65: =COUNTIF(LGDM!$C$4:$C$22,C65) -> 0 | N65: =COUNTIF(LAM!$C$5:$C$21,C65) -> 0 | O65: =COUNTIF(DEP!$C$3:$C$61,C65) -> 0 | P65: =SUMIF(LCB!$C$4:$C$45,C65,LCB!$F$4:$F$45)+SUMIF(LM!$C$4:$C$140,C65,LM!$F$4:$F$140)+SUMIF(LO!$C$4:$C$230,C65,LO!$F$4:$F$230)+SUMIF(LE!$C$4:$C$200,C65,LE!$F$4:$F$200)+SUMIF(LN!$C$4:$C$48,C65,LN!$F$4:$F$48)+SUMIF(LCE!$C$4:$C$40,C65,LCE!$F$4:$F$40)+SUMIF(LI!$C$4:$C$55,C65,LI!$F$4:$F$55)+SUMIF(LAP!$C$4:$C$45,C65,LAP!$F$4:$F$45)+SUMIF(LGDM!$C$4:$C$22,C65,LGDM!$F$4:$F$22)+SUMIF(LAM!$C$4:$C$18,C65,LAM!$F$4:$F$18)+SUMIF(DEP!$C$4:$C$55,C65,DEP!$F$4:$F$55) -> 80 | Q65: =SUMIF(LCB!$C$4:$C$45,C65,LCB!$E$4:$E$45)+SUMIF(LM!$C$4:$C$140,C65,LM!$E$4:$E$140)+SUMIF(LO!$C$4:$C$230,C65,LO!$E$4:$E$230)+SUMIF(LE!$C$4:$C$200,C65,LE!$E$4:$E$200)+SUMIF(LN!$C$4:$C$48,C65,LN!$E$4:$E$48)+SUMIF(LCE!$C$4:$C$40,C65,LCE!$E$4:$E$40)+SUMIF(LI!$C$4:$C$55,C65,LI!$E$4:$E$55)+SUMIF(LAP!$C$4:$C$45,C65,LAP!$E$4:$E$45)+SUMIF(LGDM!$C$4:$C$15,C65,LGDM!$E$4:$E$15)+SUMIF(LAM!$C$5:$C$18,C65,LAM!$E$5:$E$18)+SUMIF(DEP!$C$4:$C$55,C65,DEP!$E$4:$E$55) -> 32
B66: 11 | C66: L.O. Jocabet Ramírez García | D66: =SUM(E66:O66) -> 5 | E66: =COUNTIF(LCB!$C$4:$C$40,C66) -> 0 | F66: =COUNTIF(LM!$C$4:$C$144,C66) -> 0 | G66: =COUNTIF(LO!$C$4:$C$227,C66) -> 5 | H66: =COUNTIF(LE!$C$4:$C$214,C66) -> 0 | I66: =COUNTIF(LN!$C$4:$C$53,C66) -> 0 | J66: =COUNTIF(LCE!$C$3:$C$43,C66) -> 0 | K66: =COUNTIF(LI!$C$4:$C$60,C66) -> 0 | L66: =COUNTIF(LAP!$C$5:$C$45,C66) -> 0 | M66: =COUNTIF(LGDM!$C$4:$C$22,C66) -> 0 | N66: =COUNTIF(LAM!$C$5:$C$21,C66) -> 0 | O66: =COUNTIF(DEP!$C$3:$C$61,C66) -> 0 | P66: =SUMIF(LCB!$C$4:$C$45,C66,LCB!$F$4:$F$45)+SUMIF(LM!$C$4:$C$140,C66,LM!$F$4:$F$140)+SUMIF(LO!$C$4:$C$230,C66,LO!$F$4:$F$230)+SUMIF(LE!$C$4:$C$200,C66,LE!$F$4:$F$200)+SUMIF(LN!$C$4:$C$48,C66,LN!$F$4:$F$48)+SUMIF(LCE!$C$4:$C$40,C66,LCE!$F$4:$F$40)+SUMIF(LI!$C$4:$C$55,C66,LI!$F$4:$F$55)+SUMIF(LAP!$C$4:$C$45,C66,LAP!$F$4:$F$45)+SUMIF(LGDM!$C$4:$C$22,C66,LGDM!$F$4:$F$22)+SUMIF(LAM!$C$4:$C$18,C66,LAM!$F$4:$F$18)+SUMIF(DEP!$C$4:$C$55,C66,DEP!$F$4:$F$55) -> 152 | Q66: =SUMIF(LCB!$C$4:$C$45,C66,LCB!$E$4:$E$45)+SUMIF(LM!$C$4:$C$140,C66,LM!$E$4:$E$140)+SUMIF(LO!$C$4:$C$230,C66,LO!$E$4:$E$230)+SUMIF(LE!$C$4:$C$200,C66,LE!$E$4:$E$200)+SUMIF(LN!$C$4:$C$48,C66,LN!$E$4:$E$48)+SUMIF(LCE!$C$4:$C$40,C66,LCE!$E$4:$E$40)+SUMIF(LI!$C$4:$C$55,C66,LI!$E$4:$E$55)+SUMIF(LAP!$C$4:$C$45,C66,LAP!$E$4:$E$45)+SUMIF(LGDM!$C$4:$C$15,C66,LGDM!$E$4:$E$15)+SUMIF(LAM!$C$5:$C$18,C66,LAM!$E$5:$E$18)+SUMIF(DEP!$C$4:$C$55,C66,DEP!$E$4:$E$55) -> 30
B67: 12 | C67: C.D. Amalinalli Barón Zaragoza | D67: =SUM(E67:O67) -> 5 | E67: =COUNTIF(LCB!$C$4:$C$40,C67) -> 0 | F67: =COUNTIF(LM!$C$4:$C$144,C67) -> 0 | G67: =COUNTIF(LO!$C$4:$C$227,C67) -> 5 | H67: =COUNTIF(LE!$C$4:$C$214,C67) -> 0 | I67: =COUNTIF(LN!$C$4:$C$53,C67) -> 0 | J67: =COUNTIF(LCE!$C$3:$C$43,C67) -> 0 | K67: =COUNTIF(LI!$C$4:$C$60,C67) -> 0 | L67: =COUNTIF(LAP!$C$5:$C$45,C67) -> 0 | M67: =COUNTIF(LGDM!$C$4:$C$22,C67) -> 0 | N67: =COUNTIF(LAM!$C$5:$C$21,C67) -> 0 | O67: =COUNTIF(DEP!$C$3:$C$61,C67) -> 0 | P67: =SUMIF(LCB!$C$4:$C$45,C67,LCB!$F$4:$F$45)+SUMIF(LM!$C$4:$C$140,C67,LM!$F$4:$F$140)+SUMIF(LO!$C$4:$C$230,C67,LO!$F$4:$F$230)+SUMIF(LE!$C$4:$C$200,C67,LE!$F$4:$F$200)+SUMIF(LN!$C$4:$C$48,C67,LN!$F$4:$F$48)+SUMIF(LCE!$C$4:$C$40,C67,LCE!$F$4:$F$40)+SUMIF(LI!$C$4:$C$55,C67,LI!$F$4:$F$55)+SUMIF(LAP!$C$4:$C$45,C67,LAP!$F$4:$F$45)+SUMIF(LGDM!$C$4:$C$22,C67,LGDM!$F$4:$F$22)+SUMIF(LAM!$C$4:$C$18,C67,LAM!$F$4:$F$18)+SUMIF(DEP!$C$4:$C$55,C67,DEP!$F$4:$F$55) -> 152 | Q67: =SUMIF(LCB!$C$4:$C$45,C67,LCB!$E$4:$E$45)+SUMIF(LM!$C$4:$C$140,C67,LM!$E$4:$E$140)+SUMIF(LO!$C$4:$C$230,C67,LO!$E$4:$E$230)+SUMIF(LE!$C$4:$C$200,C67,LE!$E$4:$E$200)+SUMIF(LN!$C$4:$C$48,C67,LN!$E$4:$E$48)+SUMIF(LCE!$C$4:$C$40,C67,LCE!$E$4:$E$40)+SUMIF(LI!$C$4:$C$55,C67,LI!$E$4:$E$55)+SUMIF(LAP!$C$4:$C$45,C67,LAP!$E$4:$E$45)+SUMIF(LGDM!$C$4:$C$15,C67,LGDM!$E$4:$E$15)+SUMIF(LAM!$C$5:$C$18,C67,LAM!$E$5:$E$18)+SUMIF(DEP!$C$4:$C$55,C67,DEP!$E$4:$E$55) -> 30
... B74: 19 | C74: PTC-LO1 | D74: =SUM(E74:O74) -> 4 | E74: =COUNTIF(LCB!$C$4:$C$40,C74) -> 0 | F74: =COUNTIF(LM!$C$4:$C$144,C74) -> 0 | G74: =COUNTIF(LO!$C$4:$C$227,C74) -> 4 | H74: =COUNTIF(LE!$C$4:$C$214,C74) -> 0 | I74: =COUNTIF(LN!$C$4:$C$53,C74) -> 0 | J74: =COUNTIF(LCE!$C$3:$C$43,C74) -> 0 | K74: =COUNTIF(LI!$C$4:$C$60,C74) -> 0 | L74: =COUNTIF(LAP!$C$5:$C$45,C74) -> 0 | M74: =COUNTIF(LGDM!$C$4:$C$22,C74) -> 0 | N74: =COUNTIF(LAM!$C$5:$C$21,C74) -> 0 | O74: =COUNTIF(DEP!$C$3:$C$61,C74) -> 0 | P74: =SUMIF(LCB!$C$4:$C$45,C74,LCB!$F$4:$F$45)+SUMIF(LM!$C$4:$C$140,C74,LM!$F$4:$F$140)+SUMIF(LO!$C$4:$C$230,C74,LO!$F$4:$F$230)+SUMIF(LE!$C$4:$C$200,C74,LE!$F$4:$F$200)+SUMIF(LN!$C$4:$C$48,C74,LN!$F$4:$F$48)+SUMIF(LCE!$C$4:$C$40,C74,LCE!$F$4:$F$40)+SUMIF(LI!$C$4:$C$55,C74,LI!$F$4:$F$55)+SUMIF(LAP!$C$4:$C$45,C74,LAP!$F$4:$F$45)+SUMIF(LGDM!$C$4:$C$22,C74,LGDM!$F$4:$F$22)+SUMIF(LAM!$C$4:$C$18,C74,LAM!$F$4:$F$18)+SUMIF(DEP!$C$4:$C$55,C74,DEP!$F$4:$F$55) -> 96 | Q74: =SUMIF(LCB!$C$4:$C$45,C74,LCB!$E$4:$E$45)+SUMIF(LM!$C$4:$C$140,C74,LM!$E$4:$E$140)+SUMIF(LO!$C$4:$C$230,C74,LO!$E$4:$E$230)+SUMIF(LE!$C$4:$C$200,C74,LE!$E$4:$E$200)+SUMIF(LN!$C$4:$C$48,C74,LN!$E$4:$E$48)+SUMIF(LCE!$C$4:$C$40,C74,LCE!$E$4:$E$40)+SUMIF(LI!$C$4:$C$55,C74,LI!$E$4:$E$55)+SUMIF(LAP!$C$4:$C$45,C74,LAP!$E$4:$E$45)+SUMIF(LGDM!$C$4:$C$15,C74,LGDM!$E$4:$E$15)+SUMIF(LAM!$C$5:$C$18,C74,LAM!$E$5:$E$18)+SUMIF(DEP!$C$4:$C$55,C74,DEP!$E$4:$E$55) -> 25
B75: 22 | C75: E.O. Guadalupe Carlos Ogarrio Ramírez
B78: LE | C78: Profesor@ | D78: Materias | E78: LCB | F78: LM | G78: LO | H78: LE | I78: LN | J78: LCE | K78: LI | L78: LAP | M78: LGDM | N78: LAM | O78: DEP | P78: Total alumnos | Q78: Total hrs sem
B79: 1 | C79: M.E.D. Verónica García Brena | D79: =SUM(E79:O79) -> 1 | E79: =COUNTIF(LCB!$C$4:$C$40,C79) -> 0 | F79: =COUNTIF(LM!$C$4:$C$144,C79) -> 0 | G79: =COUNTIF(LO!$C$4:$C$227,C79) -> 0 | H79: =COUNTIF(LE!$C$4:$C$214,C79) -> 1 | I79: =COUNTIF(LN!$C$4:$C$53,C79) -> 0 | J79: =COUNTIF(LCE!$C$3:$C$43,C79) -> 0 | K79: =COUNTIF(LI!$C$4:$C$60,C79) -> 0 | L79: =COUNTIF(LAP!$C$5:$C$45,C79) -> 0 | M79: =COUNTIF(LGDM!$C$4:$C$22,C79) -> 0 | N79: =COUNTIF(LAM!$C$5:$C$21,C79) -> 0 | O79: =COUNTIF(DEP!$C$3:$C$61,C79) -> 0 | P79: =SUMIF(LCB!$C$4:$C$45,C79,LCB!$F$4:$F$45)+SUMIF(LM!$C$4:$C$140,C79,LM!$F$4:$F$140)+SUMIF(LO!$C$4:$C$230,C79,LO!$F$4:$F$230)+SUMIF(LE!$C$4:$C$200,C79,LE!$F$4:$F$200)+SUMIF(LN!$C$4:$C$48,C79,LN!$F$4:$F$48)+SUMIF(LCE!$C$4:$C$40,C79,LCE!$F$4:$F$40)+SUMIF(LI!$C$4:$C$55,C79,LI!$F$4:$F$55)+SUMIF(LAP!$C$4:$C$45,C79,LAP!$F$4:$F$45)+SUMIF(LGDM!$C$4:$C$22,C79,LGDM!$F$4:$F$22)+SUMIF(LAM!$C$4:$C$18,C79,LAM!$F$4:$F$18)+SUMIF(DEP!$C$4:$C$55,C79,DEP!$F$4:$F$55) -> 36 | Q79: =SUMIF(LCB!$C$4:$C$45,C79,LCB!$E$4:$E$45)+SUMIF(LM!$C$4:$C$140,C79,LM!$E$4:$E$140)+SUMIF(LO!$C$4:$C$230,C79,LO!$E$4:$E$230)+SUMIF(LE!$C$4:$C$200,C79,LE!$E$4:$E$200)+SUMIF(LN!$C$4:$C$48,C79,LN!$E$4:$E$48)+SUMIF(LCE!$C$4:$C$40,C79,LCE!$E$4:$E$40)+SUMIF(LI!$C$4:$C$55,C79,LI!$E$4:$E$55)+SUMIF(LAP!$C$4:$C$45,C79,LAP!$E$4:$E$45)+SUMIF(LGDM!$C$4:$C$15,C79,LGDM!$E$4:$E$15)+SUMIF(LAM!$C$5:$C$18,C79,LAM!$E$5:$E$18)+SUMIF(DEP!$C$4:$C$55,C79,DEP!$E$4:$E$55) -> 5
B80: 2 | C80: M.C.E. Ignacio Grajales Alonso | D80: =SUM(E80:O80) -> 4 | E80: =COUNTIF(LCB!$C$4:$C$40,C80) -> 0 | F80: =COUNTIF(LM!$C$4:$C$144,C80) -> 2 | G80: =COUNTIF(LO!$C$4:$C$227,C80) -> 0 | H80: =COUNTIF(LE!$C$4:$C$214,C80) -> 2 | I80: =COUNTIF(LN!$C$4:$C$53,C80) -> 0 | J80: =COUNTIF(LCE!$C$3:$C$43,C80) -> 0 | K80: =COUNTIF(LI!$C$4:$C$60,C80) -> 0 | L80: =COUNTIF(LAP!$C$5:$C$45,C80) -> 0 | M80: =COUNTIF(LGDM!$C$4:$C$22,C80) -> 0 | N80: =COUNTIF(LAM!$C$5:$C$21,C80) -> 0 | O80: =COUNTIF(DEP!$C$3:$C$61,C80) -> 0 | P80: =SUMIF(LCB!$C$4:$C$45,C80,LCB!$F$4:$F$45)+SUMIF(LM!$C$4:$C$140,C80,LM!$F$4:$F$140)+SUMIF(LO!$C$4:$C$230,C80,LO!$F$4:$F$230)+SUMIF(LE!$C$4:$C$200,C80,LE!$F$4:$F$200)+SUMIF(LN!$C$4:$C$48,C80,LN!$F$4:$F$48)+SUMIF(LCE!$C$4:$C$40,C80,LCE!$F$4:$F$40)+SUMIF(LI!$C$4:$C$55,C80,LI!$F$4:$F$55)+SUMIF(LAP!$C$4:$C$45,C80,LAP!$F$4:$F$45)+SUMIF(LGDM!$C$4:$C$22,C80,LGDM!$F$4:$F$22)+SUMIF(LAM!$C$4:$C$18,C80,LAM!$F$4:$F$18)+SUMIF(DEP!$C$4:$C$55,C80,DEP!$F$4:$F$55) -> 76 | Q80: =SUMIF(LCB!$C$4:$C$45,C80,LCB!$E$4:$E$45)+SUMIF(LM!$C$4:$C$140,C80,LM!$E$4:$E$140)+SUMIF(LO!$C$4:$C$230,C80,LO!$E$4:$E$230)+SUMIF(LE!$C$4:$C$200,C80,LE!$E$4:$E$200)+SUMIF(LN!$C$4:$C$48,C80,LN!$E$4:$E$48)+SUMIF(LCE!$C$4:$C$40,C80,LCE!$E$4:$E$40)+SUMIF(LI!$C$4:$C$55,C80,LI!$E$4:$E$55)+SUMIF(LAP!$C$4:$C$45,C80,LAP!$E$4:$E$45)+SUMIF(LGDM!$C$4:$C$15,C80,LGDM!$E$4:$E$15)+SUMIF(LAM!$C$5:$C$18,C80,LAM!$E$5:$E$18)+SUMIF(DEP!$C$4:$C$55,C80,DEP!$E$4:$E$55) -> 18
B81: 3 | C81: Dra. Roxana Nayeli Guerrero Sotelo | D81: =SUM(E81:O81) -> 4 | E81: =COUNTIF(LCB!$C$4:$C$40,C81) -> 0 | F81: =COUNTIF(LM!$C$4:$C$144,C81) -> 0 | G81: =COUNTIF(LO!$C$4:$C$227,C81) -> 0 | H81: =COUNTIF(LE!$C$4:$C$214,C81) -> 4 | I81: =COUNTIF(LN!$C$4:$C$53,C81) -> 0 | J81: =COUNTIF(LCE!$C$3:$C$43,C81) -> 0 | K81: =COUNTIF(LI!$C$4:$C$60,C81) -> 0 | L81: =COUNTIF(LAP!$C$5:$C$45,C81) -> 0 | M81: =COUNTIF(LGDM!$C$4:$C$22,C81) -> 0 | N81: =COUNTIF(LAM!$C$5:$C$21,C81) -> 0 | O81: =COUNTIF(DEP!$C$3:$C$61,C81) -> 0 | P81: =SUMIF(LCB!$C$4:$C$45,C81,LCB!$F$4:$F$45)+SUMIF(LM!$C$4:$C$140,C81,LM!$F$4:$F$140)+SUMIF(LO!$C$4:$C$230,C81,LO!$F$4:$F$230)+SUMIF(LE!$C$4:$C$200,C81,LE!$F$4:$F$200)+SUMIF(LN!$C$4:$C$48,C81,LN!$F$4:$F$48)+SUMIF(LCE!$C$4:$C$40,C81,LCE!$F$4:$F$40)+SUMIF(LI!$C$4:$C$55,C81,LI!$F$4:$F$55)+SUMIF(LAP!$C$4:$C$45,C81,LAP!$F$4:$F$45)+SUMIF(LGDM!$C$4:$C$22,C81,LGDM!$F$4:$F$22)+SUMIF(LAM!$C$4:$C$18,C81,LAM!$F$4:$F$18)+SUMIF(DEP!$C$4:$C$55,C81,DEP!$F$4:$F$55) -> 108 | Q81: =SUMIF(LCB!$C$4:$C$45,C81,LCB!$E$4:$E$45)+SUMIF(LM!$C$4:$C$140,C81,LM!$E$4:$E$140)+SUMIF(LO!$C$4:$C$230,C81,LO!$E$4:$E$230)+SUMIF(LE!$C$4:$C$200,C81,LE!$E$4:$E$200)+SUMIF(LN!$C$4:$C$48,C81,LN!$E$4:$E$48)+SUMIF(LCE!$C$4:$C$40,C81,LCE!$E$4:$E$40)+SUMIF(LI!$C$4:$C$55,C81,LI!$E$4:$E$55)+SUMIF(LAP!$C$4:$C$45,C81,LAP!$E$4:$E$45)+SUMIF(LGDM!$C$4:$C$15,C81,LGDM!$E$4:$E$15)+SUMIF(LAM!$C$5:$C$18,C81,LAM!$E$5:$E$18)+SUMIF(DEP!$C$4:$C$55,C81,DEP!$E$4:$E$55) -> 19
B82: 4 | C82: M.S.P. Gloria Verónica Alba Alba | D82: =SUM(E82:O82) -> 4 | E82: =COUNTIF(LCB!$C$4:$C$40,C82) -> 0 | F82: =COUNTIF(LM!$C$4:$C$144,C82) -> 0 | G82: =COUNTIF(LO!$C$4:$C$227,C82) -> 0 | H82: =COUNTIF(LE!$C$4:$C$214,C82) -> 4 | I82: =COUNTIF(LN!$C$4:$C$53,C82) -> 0 | J82: =COUNTIF(LCE!$C$3:$C$43,C82) -> 0 | K82: =COUNTIF(LI!$C$4:$C$60,C82) -> 0 | L82: =COUNTIF(LAP!$C$5:$C$45,C82) -> 0 | M82: =COUNTIF(LGDM!$C$4:$C$22,C82) -> 0 | N82: =COUNTIF(LAM!$C$5:$C$21,C82) -> 0 | O82: =COUNTIF(DEP!$C$3:$C$61,C82) -> 0 | P82: =SUMIF(LCB!$C$4:$C$45,C82,LCB!$F$4:$F$45)+SUMIF(LM!$C$4:$C$140,C82,LM!$F$4:$F$140)+SUMIF(LO!$C$4:$C$230,C82,LO!$F$4:$F$230)+SUMIF(LE!$C$4:$C$200,C82,LE!$F$4:$F$200)+SUMIF(LN!$C$4:$C$48,C82,LN!$F$4:$F$48)+SUMIF(LCE!$C$4:$C$40,C82,LCE!$F$4:$F$40)+SUMIF(LI!$C$4:$C$55,C82,LI!$F$4:$F$55)+SUMIF(LAP!$C$4:$C$45,C82,LAP!$F$4:$F$45)+SUMIF(LGDM!$C$4:$C$22,C82,LGDM!$F$4:$F$22)+SUMIF(LAM!$C$4:$C$18,C82,LAM!$F$4:$F$18)+SUMIF(DEP!$C$4:$C$55,C82,DEP!$F$4:$F$55) -> 122 | Q82: =SUMIF(LCB!$C$4:$C$45,C82,LCB!$E$4:$E$45)+SUMIF(LM!$C$4:$C$140,C82,LM!$E$4:$E$140)+SUMIF(LO!$C$4:$C$230,C82,LO!$E$4:$E$230)+SUMIF(LE!$C$4:$C$200,C82,LE!$E$4:$E$200)+SUMIF(LN!$C$4:$C$48,C82,LN!$E$4:$E$48)+SUMIF(LCE!$C$4:$C$40,C82,LCE!$E$4:$E$40)+SUMIF(LI!$C$4:$C$55,C82,LI!$E$4:$E$55)+SUMIF(LAP!$C$4:$C$45,C82,LAP!$E$4:$E$45)+SUMIF(LGDM!$C$4:$C$15,C82,LGDM!$E$4:$E$15)+SUMIF(LAM!$C$5:$C$18,C82,LAM!$E$5:$E$18)+SUMIF(DEP!$C$4:$C$55,C82,DEP!$E$4:$E$55) -> 20
B83: 5 | C83: Dra. Concepción Maritza Jarquín Olivera | D83: =SUM(E83:O83) -> 3 | E83: =COUNTIF(LCB!$C$4:$C$40,C83) -> 0 | F83: =COUNTIF(LM!$C$4:$C$144,C83) -> 0 | G83: =COUNTIF(LO!$C$4:$C$227,C83) -> 0 | H83: =COUNTIF(LE!$C$4:$C$214,C83) -> 3 | I83: =COUNTIF(LN!$C$4:$C$53,C83) -> 0 | J83: =COUNTIF(LCE!$C$3:$C$43,C83) -> 0 | K83: =COUNTIF(LI!$C$4:$C$60,C83) -> 0 | L83: =COUNTIF(LAP!$C$5:$C$45,C83) -> 0 | M83: =COUNTIF(LGDM!$C$4:$C$22,C83) -> 0 | N83: =COUNTIF(LAM!$C$5:$C$21,C83) -> 0 | O83: =COUNTIF(DEP!$C$3:$C$61,C83) -> 0 | P83: =SUMIF(LCB!$C$4:$C$45,C83,LCB!$F$4:$F$45)+SUMIF(LM!$C$4:$C$140,C83,LM!$F$4:$F$140)+SUMIF(LO!$C$4:$C$230,C83,LO!$F$4:$F$230)+SUMIF(LE!$C$4:$C$200,C83,LE!$F$4:$F$200)+SUMIF(LN!$C$4:$C$48,C83,LN!$F$4:$F$48)+SUMIF(LCE!$C$4:$C$40,C83,LCE!$F$4:$F$40)+SUMIF(LI!$C$4:$C$55,C83,LI!$F$4:$F$55)+SUMIF(LAP!$C$4:$C$45,C83,LAP!$F$4:$F$45)+SUMIF(LGDM!$C$4:$C$22,C83,LGDM!$F$4:$F$22)+SUMIF(LAM!$C$4:$C$18,C83,LAM!$F$4:$F$18)+SUMIF(DEP!$C$4:$C$55,C83,DEP!$F$4:$F$55) -> 108 | Q83: =SUMIF(LCB!$C$4:$C$45,C83,LCB!$E$4:$E$45)+SUMIF(LM!$C$4:$C$140,C83,LM!$E$4:$E$140)+SUMIF(LO!$C$4:$C$230,C83,LO!$E$4:$E$230)+SUMIF(LE!$C$4:$C$200,C83,LE!$E$4:$E$200)+SUMIF(LN!$C$4:$C$48,C83,LN!$E$4:$E$48)+SUMIF(LCE!$C$4:$C$40,C83,LCE!$E$4:$E$40)+SUMIF(LI!$C$4:$C$55,C83,LI!$E$4:$E$55)+SUMIF(LAP!$C$4:$C$45,C83,LAP!$E$4:$E$45)+SUMIF(LGDM!$C$4:$C$15,C83,LGDM!$E$4:$E$15)+SUMIF(LAM!$C$5:$C$18,C83,LAM!$E$5:$E$18)+SUMIF(DEP!$C$4:$C$55,C83,DEP!$E$4:$E$55) -> 15
B84: 6 | C84: M.R.N. Lisbeht Amaro López | D84: =SUM(E84:O84) -> 4 | E84: =COUNTIF(LCB!$C$4:$C$40,C84) -> 0 | F84: =COUNTIF(LM!$C$4:$C$144,C84) -> 0 | G84: =COUNTIF(LO!$C$4:$C$227,C84) -> 0 | H84: =COUNTIF(LE!$C$4:$C$214,C84) -> 4 | I84: =COUNTIF(LN!$C$4:$C$53,C84) -> 0 | J84: =COUNTIF(LCE!$C$3:$C$43,C84) -> 0 | K84: =COUNTIF(LI!$C$4:$C$60,C84) -> 0 | L84: =COUNTIF(LAP!$C$5:$C$45,C84) -> 0 | M84: =COUNTIF(LGDM!$C$4:$C$22,C84) -> 0 | N84: =COUNTIF(LAM!$C$5:$C$21,C84) -> 0 | O84: =COUNTIF(DEP!$C$3:$C$61,C84) -> 0 | P84: =SUMIF(LCB!$C$4:$C$45,C84,LCB!$F$4:$F$45)+SUMIF(LM!$C$4:$C$140,C84,LM!$F$4:$F$140)+SUMIF(LO!$C$4:$C$230,C84,LO!$F$4:$F$230)+SUMIF(LE!$C$4:$C$200,C84,LE!$F$4:$F$200)+SUMIF(LN!$C$4:$C$48,C84,LN!$F$4:$F$48)+SUMIF(LCE!$C$4:$C$40,C84,LCE!$F$4:$F$40)+SUMIF(LI!$C$4:$C$55,C84,LI!$F$4:$F$55)+SUMIF(LAP!$C$4:$C$45,C84,LAP!$F$4:$F$45)+SUMIF(LGDM!$C$4:$C$22,C84,LGDM!$F$4:$F$22)+SUMIF(LAM!$C$4:$C$18,C84,LAM!$F$4:$F$18)+SUMIF(DEP!$C$4:$C$55,C84,DEP!$F$4:$F$55) -> 143 | Q84: =SUMIF(LCB!$C$4:$C$45,C84,LCB!$E$4:$E$45)+SUMIF(LM!$C$4:$C$140,C84,LM!$E$4:$E$140)+SUMIF(LO!$C$4:$C$230,C84,LO!$E$4:$E$230)+SUMIF(LE!$C$4:$C$200,C84,LE!$E$4:$E$200)+SUMIF(LN!$C$4:$C$48,C84,LN!$E$4:$E$48)+SUMIF(LCE!$C$4:$C$40,C84,LCE!$E$4:$E$40)+SUMIF(LI!$C$4:$C$55,C84,LI!$E$4:$E$55)+SUMIF(LAP!$C$4:$C$45,C84,LAP!$E$4:$E$45)+SUMIF(LGDM!$C$4:$C$15,C84,LGDM!$E$4:$E$15)+SUMIF(LAM!$C$5:$C$18,C84,LAM!$E$5:$E$18)+SUMIF(DEP!$C$4:$C$55,C84,DEP!$E$4:$E$55) -> 20
B85: 7 | C85: M.R.N. Pedro Luis Hernández González | D85: =SUM(E85:O85) -> 2 | E85: =COUNTIF(LCB!$C$4:$C$40,C85) -> 0 | F85: =COUNTIF(LM!$C$4:$C$144,C85) -> 0 | G85: =COUNTIF(LO!$C$4:$C$227,C85) -> 0 | H85: =COUNTIF(LE!$C$4:$C$214,C85) -> 2 | I85: =COUNTIF(LN!$C$4:$C$53,C85) -> 0 | J85: =COUNTIF(LCE!$C$3:$C$43,C85) -> 0 | K85: =COUNTIF(LI!$C$4:$C$60,C85) -> 0 | L85: =COUNTIF(LAP!$C$5:$C$45,C85) -> 0 | M85: =COUNTIF(LGDM!$C$4:$C$22,C85) -> 0 | N85: =COUNTIF(LAM!$C$5:$C$21,C85) -> 0 | O85: =COUNTIF(DEP!$C$3:$C$61,C85) -> 0 | P85: =SUMIF(LCB!$C$4:$C$45,C85,LCB!$F$4:$F$45)+SUMIF(LM!$C$4:$C$140,C85,LM!$F$4:$F$140)+SUMIF(LO!$C$4:$C$230,C85,LO!$F$4:$F$230)+SUMIF(LE!$C$4:$C$200,C85,LE!$F$4:$F$200)+SUMIF(LN!$C$4:$C$48,C85,LN!$F$4:$F$48)+SUMIF(LCE!$C$4:$C$40,C85,LCE!$F$4:$F$40)+SUMIF(LI!$C$4:$C$55,C85,LI!$F$4:$F$55)+SUMIF(LAP!$C$4:$C$45,C85,LAP!$F$4:$F$45)+SUMIF(LGDM!$C$4:$C$22,C85,LGDM!$F$4:$F$22)+SUMIF(LAM!$C$4:$C$18,C85,LAM!$F$4:$F$18)+SUMIF(DEP!$C$4:$C$55,C85,DEP!$F$4:$F$55) -> 60 | Q85: =SUMIF(LCB!$C$4:$C$45,C85,LCB!$E$4:$E$45)+SUMIF(LM!$C$4:$C$140,C85,LM!$E$4:$E$140)+SUMIF(LO!$C$4:$C$230,C85,LO!$E$4:$E$230)+SUMIF(LE!$C$4:$C$200,C85,LE!$E$4:$E$200)+SUMIF(LN!$C$4:$C$48,C85,LN!$E$4:$E$48)+SUMIF(LCE!$C$4:$C$40,C85,LCE!$E$4:$E$40)+SUMIF(LI!$C$4:$C$55,C85,LI!$E$4:$E$55)+SUMIF(LAP!$C$4:$C$45,C85,LAP!$E$4:$E$45)+SUMIF(LGDM!$C$4:$C$15,C85,LGDM!$E$4:$E$15)+SUMIF(LAM!$C$5:$C$18,C85,LAM!$E$5:$E$18)+SUMIF(DEP!$C$4:$C$55,C85,DEP!$E$4:$E$55) -> 10
B86: 8 | C86: M.C.E. Luis Miguel Márquez Valdez | D86: =SUM(E86:O86) -> 3 | E86: =COUNTIF(LCB!$C$4:$C$40,C86) -> 0 | F86: =COUNTIF(LM!$C$4:$C$144,C86) -> 0 | G86: =COUNTIF(LO!$C$4:$C$227,C86) -> 0 | H86: =COUNTIF(LE!$C$4:$C$214,C86) -> 3 | I86: =COUNTIF(LN!$C$4:$C$53,C86) -> 0 | J86: =COUNTIF(LCE!$C$3:$C$43,C86) -> 0 | K86: =COUNTIF(LI!$C$4:$C$60,C86) -> 0 | L86: =COUNTIF(LAP!$C$5:$C$45,C86) -> 0 | M86: =COUNTIF(LGDM!$C$4:$C$22,C86) -> 0 | N86: =COUNTIF(LAM!$C$5:$C$21,C86) -> 0 | O86: =COUNTIF(DEP!$C$3:$C$61,C86) -> 0 | P86: =SUMIF(LCB!$C$4:$C$45,C86,LCB!$F$4:$F$45)+SUMIF(LM!$C$4:$C$140,C86,LM!$F$4:$F$140)+SUMIF(LO!$C$4:$C$230,C86,LO!$F$4:$F$230)+SUMIF(LE!$C$4:$C$200,C86,LE!$F$4:$F$200)+SUMIF(LN!$C$4:$C$48,C86,LN!$F$4:$F$48)+SUMIF(LCE!$C$4:$C$40,C86,LCE!$F$4:$F$40)+SUMIF(LI!$C$4:$C$55,C86,LI!$F$4:$F$55)+SUMIF(LAP!$C$4:$C$45,C86,LAP!$F$4:$F$45)+SUMIF(LGDM!$C$4:$C$22,C86,LGDM!$F$4:$F$22)+SUMIF(LAM!$C$4:$C$18,C86,LAM!$F$4:$F$18)+SUMIF(DEP!$C$4:$C$55,C86,DEP!$F$4:$F$55) -> 90 | Q86: =SUMIF(LCB!$C$4:$C$45,C86,LCB!$E$4:$E$45)+SUMIF(LM!$C$4:$C$140,C86,LM!$E$4:$E$140)+SUMIF(LO!$C$4:$C$230,C86,LO!$E$4:$E$230)+SUMIF(LE!$C$4:$C$200,C86,LE!$E$4:$E$200)+SUMIF(LN!$C$4:$C$48,C86,LN!$E$4:$E$48)+SUMIF(LCE!$C$4:$C$40,C86,LCE!$E$4:$E$40)+SUMIF(LI!$C$4:$C$55,C86,LI!$E$4:$E$55)+SUMIF(LAP!$C$4:$C$45,C86,LAP!$E$4:$E$45)+SUMIF(LGDM!$C$4:$C$15,C86,LGDM!$E$4:$E$15)+SUMIF(LAM!$C$5:$C$18,C86,LAM!$E$5:$E$18)+SUMIF(DEP!$C$4:$C$55,C86,DEP!$E$4:$E$55) -> 15
B87: 9 | C87: L.E. Amalia Hernández Blas | D87: =SUM(E87:O87) -> 4 | E87: =COUNTIF(LCB!$C$4:$C$40,C87) -> 0 | F87: =COUNTIF(LM!$C$4:$C$144,C87) -> 0 | G87: =COUNTIF(LO!$C$4:$C$227,C87) -> 0 | H87: =COUNTIF(LE!$C$4:$C$214,C87) -> 4 | I87: =COUNTIF(LN!$C$4:$C$53,C87) -> 0 | J87: =COUNTIF(LCE!$C$3:$C$43,C87) -> 0 | K87: =COUNTIF(LI!$C$4:$C$60,C87) -> 0 | L87: =COUNTIF(LAP!$C$5:$C$45,C87) -> 0 | M87: =COUNTIF(LGDM!$C$4:$C$22,C87) -> 0 | N87: =COUNTIF(LAM!$C$5:$C$21,C87) -> 0 | O87: =COUNTIF(DEP!$C$3:$C$61,C87) -> 0 | P87: =SUMIF(LCB!$C$4:$C$45,C87,LCB!$F$4:$F$45)+SUMIF(LM!$C$4:$C$140,C87,LM!$F$4:$F$140)+SUMIF(LO!$C$4:$C$230,C87,LO!$F$4:$F$230)+SUMIF(LE!$C$4:$C$200,C87,LE!$F$4:$F$200)+SUMIF(LN!$C$4:$C$48,C87,LN!$F$4:$F$48)+SUMIF(LCE!$C$4:$C$40,C87,LCE!$F$4:$F$40)+SUMIF(LI!$C$4:$C$55,C87,LI!$F$4:$F$55)+SUMIF(LAP!$C$4:$C$45,C87,LAP!$F$4:$F$45)+SUMIF(LGDM!$C$4:$C$22,C87,LGDM!$F$4:$F$22)+SUMIF(LAM!$C$4:$C$18,C87,LAM!$F$4:$F$18)+SUMIF(DEP!$C$4:$C$55,C87,DEP!$F$4:$F$55) -> 68 | Q87: =SUMIF(LCB!$C$4:$C$45,C87,LCB!$E$4:$E$45)+SUMIF(LM!$C$4:$C$140,C87,LM!$E$4:$E$140)+SUMIF(LO!$C$4:$C$230,C87,LO!$E$4:$E$230)+SUMIF(LE!$C$4:$C$200,C87,LE!$E$4:$E$200)+SUMIF(LN!$C$4:$C$48,C87,LN!$E$4:$E$48)+SUMIF(LCE!$C$4:$C$40,C87,LCE!$E$4:$E$40)+SUMIF(LI!$C$4:$C$55,C87,LI!$E$4:$E$55)+SUMIF(LAP!$C$4:$C$45,C87,LAP!$E$4:$E$45)+SUMIF(LGDM!$C$4:$C$15,C87,LGDM!$E$4:$E$15)+SUMIF(LAM!$C$5:$C$18,C87,LAM!$E$5:$E$18)+SUMIF(DEP!$C$4:$C$55,C87,DEP!$E$4:$E$55) -> 22
B88: 10 | C88: L.E. Yarely Yaneth Zurita López | D88: =SUM(E88:O88) -> 4 | E88: =COUNTIF(LCB!$C$4:$C$40,C88) -> 0 | F88: =COUNTIF(LM!$C$4:$C$144,C88) -> 0 | G88: =COUNTIF(LO!$C$4:$C$227,C88) -> 0 | H88: =COUNTIF(LE!$C$4:$C$214,C88) -> 4 | I88: =COUNTIF(LN!$C$4:$C$53,C88) -> 0 | J88: =COUNTIF(LCE!$C$3:$C$43,C88) -> 0 | K88: =COUNTIF(LI!$C$4:$C$60,C88) -> 0 | L88: =COUNTIF(LAP!$C$5:$C$45,C88) -> 0 | M88: =COUNTIF(LGDM!$C$4:$C$22,C88) -> 0 | N88: =COUNTIF(LAM!$C$5:$C$21,C88) -> 0 | O88: =COUNTIF(DEP!$C$3:$C$61,C88) -> 0 | P88: =SUMIF(LCB!$C$4:$C$45,C88,LCB!$F$4:$F$45)+SUMIF(LM!$C$4:$C$140,C88,LM!$F$4:$F$140)+SUMIF(LO!$C$4:$C$230,C88,LO!$F$4:$F$230)+SUMIF(LE!$C$4:$C$200,C88,LE!$F$4:$F$200)+SUMIF(LN!$C$4:$C$48,C88,LN!$F$4:$F$48)+SUMIF(LCE!$C$4:$C$40,C88,LCE!$F$4:$F$40)+SUMIF(LI!$C$4:$C$55,C88,LI!$F$4:$F$55)+SUMIF(LAP!$C$4:$C$45,C88,LAP!$F$4:$F$45)+SUMIF(LGDM!$C$4:$C$22,C88,LGDM!$F$4:$F$22)+SUMIF(LAM!$C$4:$C$18,C88,LAM!$F$4:$F$18)+SUMIF(DEP!$C$4:$C$55,C88,DEP!$F$4:$F$55) -> 60 | Q88: =SUMIF(LCB!$C$4:$C$45,C88,LCB!$E$4:$E$45)+SUMIF(LM!$C$4:$C$140,C88,LM!$E$4:$E$140)+SUMIF(LO!$C$4:$C$230,C88,LO!$E$4:$E$230)+SUMIF(LE!$C$4:$C$200,C88,LE!$E$4:$E$200)+SUMIF(LN!$C$4:$C$48,C88,LN!$E$4:$E$48)+SUMIF(LCE!$C$4:$C$40,C88,LCE!$E$4:$E$40)+SUMIF(LI!$C$4:$C$55,C88,LI!$E$4:$E$55)+SUMIF(LAP!$C$4:$C$45,C88,LAP!$E$4:$E$45)+SUMIF(LGDM!$C$4:$C$15,C88,LGDM!$E$4:$E$15)+SUMIF(LAM!$C$5:$C$18,C88,LAM!$E$5:$E$18)+SUMIF(DEP!$C$4:$C$55,C88,DEP!$E$4:$E$55) -> 20
B89: 11 | C89: M.E.S. Adriana Zúñiga Jiménez | D89: =SUM(E89:O89) -> 2 | E89: =COUNTIF(LCB!$C$4:$C$40,C89) -> 0 | F89: =COUNTIF(LM!$C$4:$C$144,C89) -> 0 | G89: =COUNTIF(LO!$C$4:$C$227,C89) -> 0 | H89: =COUNTIF(LE!$C$4:$C$214,C89) -> 2 | I89: =COUNTIF(LN!$C$4:$C$53,C89) -> 0 | J89: =COUNTIF(LCE!$C$3:$C$43,C89) -> 0 | K89: =COUNTIF(LI!$C$4:$C$60,C89) -> 0 | L89: =COUNTIF(LAP!$C$5:$C$45,C89) -> 0 | M89: =COUNTIF(LGDM!$C$4:$C$22,C89) -> 0 | N89: =COUNTIF(LAM!$C$5:$C$21,C89) -> 0 | O89: =COUNTIF(DEP!$C$3:$C$61,C89) -> 0 | P89: =SUMIF(LCB!$C$4:$C$45,C89,LCB!$F$4:$F$45)+SUMIF(LM!$C$4:$C$140,C89,LM!$F$4:$F$140)+SUMIF(LO!$C$4:$C$230,C89,LO!$F$4:$F$230)+SUMIF(LE!$C$4:$C$200,C89,LE!$F$4:$F$200)+SUMIF(LN!$C$4:$C$48,C89,LN!$F$4:$F$48)+SUMIF(LCE!$C$4:$C$40,C89,LCE!$F$4:$F$40)+SUMIF(LI!$C$4:$C$55,C89,LI!$F$4:$F$55)+SUMIF(LAP!$C$4:$C$45,C89,LAP!$F$4:$F$45)+SUMIF(LGDM!$C$4:$C$22,C89,LGDM!$F$4:$F$22)+SUMIF(LAM!$C$4:$C$18,C89,LAM!$F$4:$F$18)+SUMIF(DEP!$C$4:$C$55,C89,DEP!$F$4:$F$55) -> 0 | Q89: =SUMIF(LCB!$C$4:$C$45,C89,LCB!$E$4:$E$45)+SUMIF(LM!$C$4:$C$140,C89,LM!$E$4:$E$140)+SUMIF(LO!$C$4:$C$230,C89,LO!$E$4:$E$230)+SUMIF(LE!$C$4:$C$200,C89,LE!$E$4:$E$200)+SUMIF(LN!$C$4:$C$48,C89,LN!$E$4:$E$48)+SUMIF(LCE!$C$4:$C$40,C89,LCE!$E$4:$E$40)+SUMIF(LI!$C$4:$C$55,C89,LI!$E$4:$E$55)+SUMIF(LAP!$C$4:$C$45,C89,LAP!$E$4:$E$45)+SUMIF(LGDM!$C$4:$C$15,C89,LGDM!$E$4:$E$15)+SUMIF(LAM!$C$5:$C$18,C89,LAM!$E$5:$E$18)+SUMIF(DEP!$C$4:$C$55,C89,DEP!$E$4:$E$55) -> 10
B90: 12 | C90: M.S.P. Silvia Mercedes Coca | D90: =SUM(E90:O90) -> 4 | E90: =COUNTIF(LCB!$C$4:$C$40,C90) -> 0 | F90: =COUNTIF(LM!$C$4:$C$144,C90) -> 0 | G90: =COUNTIF(LO!$C$4:$C$227,C90) -> 0 | H90: =COUNTIF(LE!$C$4:$C$214,C90) -> 4 | I90: =COUNTIF(LN!$C$4:$C$53,C90) -> 0 | J90: =COUNTIF(LCE!$C$3:$C$43,C90) -> 0 | K90: =COUNTIF(LI!$C$4:$C$60,C90) -> 0 | L90: =COUNTIF(LAP!$C$5:$C$45,C90) -> 0 | M90: =COUNTIF(LGDM!$C$4:$C$22,C90) -> 0 | N90: =COUNTIF(LAM!$C$5:$C$21,C90) -> 0 | O90: =COUNTIF(DEP!$C$3:$C$61,C90) -> 0 | P90: =SUMIF(LCB!$C$4:$C$45,C90,LCB!$F$4:$F$45)+SUMIF(LM!$C$4:$C$140,C90,LM!$F$4:$F$140)+SUMIF(LO!$C$4:$C$230,C90,LO!$F$4:$F$230)+SUMIF(LE!$C$4:$C$200,C90,LE!$F$4:$F$200)+SUMIF(LN!$C$4:$C$48,C90,LN!$F$4:$F$48)+SUMIF(LCE!$C$4:$C$40,C90,LCE!$F$4:$F$40)+SUMIF(LI!$C$4:$C$55,C90,LI!$F$4:$F$55)+SUMIF(LAP!$C$4:$C$45,C90,LAP!$F$4:$F$45)+SUMIF(LGDM!$C$4:$C$22,C90,LGDM!$F$4:$F$22)+SUMIF(LAM!$C$4:$C$18,C90,LAM!$F$4:$F$18)+SUMIF(DEP!$C$4:$C$55,C90,DEP!$F$4:$F$55) -> 143 | Q90: =SUMIF(LCB!$C$4:$C$45,C90,LCB!$E$4:$E$45)+SUMIF(LM!$C$4:$C$140,C90,LM!$E$4:$E$140)+SUMIF(LO!$C$4:$C$230,C90,LO!$E$4:$E$230)+SUMIF(LE!$C$4:$C$200,C90,LE!$E$4:$E$200)+SUMIF(LN!$C$4:$C$48,C90,LN!$E$4:$E$48)+SUMIF(LCE!$C$4:$C$40,C90,LCE!$E$4:$E$40)+SUMIF(LI!$C$4:$C$55,C90,LI!$E$4:$E$55)+SUMIF(LAP!$C$4:$C$45,C90,LAP!$E$4:$E$45)+SUMIF(LGDM!$C$4:$C$15,C90,LGDM!$E$4:$E$15)+SUMIF(LAM!$C$5:$C$18,C90,LAM!$E$5:$E$18)+SUMIF(DEP!$C$4:$C$55,C90,DEP!$E$4:$E$55) -> 20
... B103: 25 | C103: PTC-LE2 | D103: =SUM(E103:O103) -> 3 | E103: =COUNTIF(LCB!$C$4:$C$40,C103) -> 0 | F103: =COUNTIF(LM!$C$4:$C$144,C103) -> 0 | G103: =COUNTIF(LO!$C$4:$C$227,C103) -> 0 | H103: =COUNTIF(LE!$C$4:$C$214,C103) -> 3 | I103: =COUNTIF(LN!$C$4:$C$53,C103) -> 0 | J103: =COUNTIF(LCE!$C$3:$C$43,C103) -> 0 | K103: =COUNTIF(LI!$C$4:$C$60,C103) -> 0 | L103: =COUNTIF(LAP!$C$5:$C$45,C103) -> 0 | M103: =COUNTIF(LGDM!$C$4:$C$22,C103) -> 0 | N103: =COUNTIF(LAM!$C$5:$C$21,C103) -> 0 | O103: =COUNTIF(DEP!$C$3:$C$61,C103) -> 0 | P103: =SUMIF(LCB!$C$4:$C$45,C103,LCB!$F$4:$F$45)+SUMIF(LM!$C$4:$C$140,C103,LM!$F$4:$F$140)+SUMIF(LO!$C$4:$C$230,C103,LO!$F$4:$F$230)+SUMIF(LE!$C$4:$C$200,C103,LE!$F$4:$F$200)+SUMIF(LN!$C$4:$C$48,C103,LN!$F$4:$F$48)+SUMIF(LCE!$C$4:$C$40,C103,LCE!$F$4:$F$40)+SUMIF(LI!$C$4:$C$55,C103,LI!$F$4:$F$55)+SUMIF(LAP!$C$4:$C$45,C103,LAP!$F$4:$F$45)+SUMIF(LGDM!$C$4:$C$22,C103,LGDM!$F$4:$F$22)+SUMIF(LAM!$C$4:$C$18,C103,LAM!$F$4:$F$18)+SUMIF(DEP!$C$4:$C$55,C103,DEP!$F$4:$F$55) -> 72 | Q103: =SUMIF(LCB!$C$4:$C$45,C103,LCB!$E$4:$E$45)+SUMIF(LM!$C$4:$C$140,C103,LM!$E$4:$E$140)+SUMIF(LO!$C$4:$C$230,C103,LO!$E$4:$E$230)+SUMIF(LE!$C$4:$C$200,C103,LE!$E$4:$E$200)+SUMIF(LN!$C$4:$C$48,C103,LN!$E$4:$E$48)+SUMIF(LCE!$C$4:$C$40,C103,LCE!$E$4:$E$40)+SUMIF(LI!$C$4:$C$55,C103,LI!$E$4:$E$55)+SUMIF(LAP!$C$4:$C$45,C103,LAP!$E$4:$E$45)+SUMIF(LGDM!$C$4:$C$15,C103,LGDM!$E$4:$E$15)+SUMIF(LAM!$C$5:$C$18,C103,LAM!$E$5:$E$18)+SUMIF(DEP!$C$4:$C$55,C103,DEP!$E$4:$E$55) -> 14
B104: 26 | C104: M.C.S. Carmela Cortez Gonsalez
B105: 27 | C105: L.E. Gisela Mayra Bustamante Ramos
B106: 28 | C106: Dr. Samuel Sánchez Hernández
B107: 29 | C107: M.D. Elizabeth Cortés Bohórquez
B108: 30 | C108: M.E. José Alberto Ramírez Rodríguez
B109: 31 | C109: E.E.U. Rolando Emilio Martínez Juárez
B110: 32 | C110: M.T.H.E.Q. Margarita Selene Aragón Sierra
B111: 33 | C111: E.E.N. Maritza Nicolás Santiago
B113: LN | C113: Profesor@ | D113: Materias | E113: LCB | F113: LM | G113: LO | H113: LE | I113: LN | J113: LCE | K113: LI | L113: LAP | M113: LGDM | N113: LAM | O113: DEP | P113: Total alumnos | Q113: Total hrs sem
B114: 1 | C114: M.N.C. Griselda Belén Avendaño Rodríguez | D114: =SUM(E114:O114) -> 1 | E114: =COUNTIF(LCB!$C$4:$C$40,C114) -> 0 | F114: =COUNTIF(LM!$C$4:$C$144,C114) -> 0 | G114: =COUNTIF(LO!$C$4:$C$227,C114) -> 0 | H114: =COUNTIF(LE!$C$4:$C$214,C114) -> 0 | I114: =COUNTIF(LN!$C$4:$C$53,C114) -> 1 | J114: =COUNTIF(LCE!$C$3:$C$43,C114) -> 0 | K114: =COUNTIF(LI!$C$4:$C$60,C114) -> 0 | L114: =COUNTIF(LAP!$C$5:$C$45,C114) -> 0 | M114: =COUNTIF(LGDM!$C$4:$C$22,C114) -> 0 | N114: =COUNTIF(LAM!$C$5:$C$21,C114) -> 0 | O114: =COUNTIF(DEP!$C$3:$C$61,C114) -> 0 | P114: =SUMIF(LCB!$C$4:$C$45,C114,LCB!$F$4:$F$45)+SUMIF(LM!$C$4:$C$140,C114,LM!$F$4:$F$140)+SUMIF(LO!$C$4:$C$230,C114,LO!$F$4:$F$230)+SUMIF(LE!$C$4:$C$200,C114,LE!$F$4:$F$200)+SUMIF(LN!$C$4:$C$48,C114,LN!$F$4:$F$48)+SUMIF(LCE!$C$4:$C$40,C114,LCE!$F$4:$F$40)+SUMIF(LI!$C$4:$C$55,C114,LI!$F$4:$F$55)+SUMIF(LAP!$C$4:$C$45,C114,LAP!$F$4:$F$45)+SUMIF(LGDM!$C$4:$C$22,C114,LGDM!$F$4:$F$22)+SUMIF(LAM!$C$4:$C$18,C114,LAM!$F$4:$F$18)+SUMIF(DEP!$C$4:$C$55,C114,DEP!$F$4:$F$55) -> 34 | Q114: =SUMIF(LCB!$C$4:$C$45,C114,LCB!$E$4:$E$45)+SUMIF(LM!$C$4:$C$140,C114,LM!$E$4:$E$140)+SUMIF(LO!$C$4:$C$230,C114,LO!$E$4:$E$230)+SUMIF(LE!$C$4:$C$200,C114,LE!$E$4:$E$200)+SUMIF(LN!$C$4:$C$48,C114,LN!$E$4:$E$48)+SUMIF(LCE!$C$4:$C$40,C114,LCE!$E$4:$E$40)+SUMIF(LI!$C$4:$C$55,C114,LI!$E$4:$E$55)+SUMIF(LAP!$C$4:$C$45,C114,LAP!$E$4:$E$45)+SUMIF(LGDM!$C$4:$C$15,C114,LGDM!$E$4:$E$15)+SUMIF(LAM!$C$5:$C$18,C114,LAM!$E$5:$E$18)+SUMIF(DEP!$C$4:$C$55,C114,DEP!$E$4:$E$55) -> 6
B115: 2 | C115: M.C.A. Laura Jocelyn Valdez Gutiérrez | D115: =SUM(E115:O115) -> 0 | E115: =COUNTIF(LCB!$C$4:$C$40,C115) -> 0 | F115: =COUNTIF(LM!$C$4:$C$144,C115) -> 0 | G115: =COUNTIF(LO!$C$4:$C$227,C115) -> 0 | H115: =COUNTIF(LE!$C$4:$C$214,C115) -> 0 | I115: =COUNTIF(LN!$C$4:$C$53,C115) -> 0 | J115: =COUNTIF(LCE!$C$3:$C$43,C115) -> 0 | K115: =COUNTIF(LI!$C$4:$C$60,C115) -> 0 | L115: =COUNTIF(LAP!$C$5:$C$45,C115) -> 0 | M115: =COUNTIF(LGDM!$C$4:$C$22,C115) -> 0 | N115: =COUNTIF(LAM!$C$5:$C$21,C115) -> 0 | O115: =COUNTIF(DEP!$C$3:$C$61,C115) -> 0 | P115: =SUMIF(LCB!$C$4:$C$45,C115,LCB!$F$4:$F$45)+SUMIF(LM!$C$4:$C$140,C115,LM!$F$4:$F$140)+SUMIF(LO!$C$4:$C$230,C115,LO!$F$4:$F$230)+SUMIF(LE!$C$4:$C$200,C115,LE!$F$4:$F$200)+SUMIF(LN!$C$4:$C$48,C115,LN!$F$4:$F$48)+SUMIF(LCE!$C$4:$C$40,C115,LCE!$F$4:$F$40)+SUMIF(LI!$C$4:$C$55,C115,LI!$F$4:$F$55)+SUMIF(LAP!$C$4:$C$45,C115,LAP!$F$4:$F$45)+SUMIF(LGDM!$C$4:$C$22,C115,LGDM!$F$4:$F$22)+SUMIF(LAM!$C$4:$C$18,C115,LAM!$F$4:$F$18)+SUMIF(DEP!$C$4:$C$55,C115,DEP!$F$4:$F$55) -> 0 | Q115: =SUMIF(LCB!$C$4:$C$45,C115,LCB!$E$4:$E$45)+SUMIF(LM!$C$4:$C$140,C115,LM!$E$4:$E$140)+SUMIF(LO!$C$4:$C$230,C115,LO!$E$4:$E$230)+SUMIF(LE!$C$4:$C$200,C115,LE!$E$4:$E$200)+SUMIF(LN!$C$4:$C$48,C115,LN!$E$4:$E$48)+SUMIF(LCE!$C$4:$C$40,C115,LCE!$E$4:$E$40)+SUMIF(LI!$C$4:$C$55,C115,LI!$E$4:$E$55)+SUMIF(LAP!$C$4:$C$45,C115,LAP!$E$4:$E$45)+SUMIF(LGDM!$C$4:$C$15,C115,LGDM!$E$4:$E$15)+SUMIF(LAM!$C$5:$C$18,C115,LAM!$E$5:$E$18)+SUMIF(DEP!$C$4:$C$55,C115,DEP!$E$4:$E$55) -> 0
B116: 3 | C116: L.N. César Juárez Durán | D116: =SUM(E116:O116) -> 5 | E116: =COUNTIF(LCB!$C$4:$C$40,C116) -> 0 | F116: =COUNTIF(LM!$C$4:$C$144,C116) -> 0 | G116: =COUNTIF(LO!$C$4:$C$227,C116) -> 2 | H116: =COUNTIF(LE!$C$4:$C$214,C116) -> 0 | I116: =COUNTIF(LN!$C$4:$C$53,C116) -> 3 | J116: =COUNTIF(LCE!$C$3:$C$43,C116) -> 0 | K116: =COUNTIF(LI!$C$4:$C$60,C116) -> 0 | L116: =COUNTIF(LAP!$C$5:$C$45,C116) -> 0 | M116: =COUNTIF(LGDM!$C$4:$C$22,C116) -> 0 | N116: =COUNTIF(LAM!$C$5:$C$21,C116) -> 0 | O116: =COUNTIF(DEP!$C$3:$C$61,C116) -> 0 | P116: =SUMIF(LCB!$C$4:$C$45,C116,LCB!$F$4:$F$45)+SUMIF(LM!$C$4:$C$140,C116,LM!$F$4:$F$140)+SUMIF(LO!$C$4:$C$230,C116,LO!$F$4:$F$230)+SUMIF(LE!$C$4:$C$200,C116,LE!$F$4:$F$200)+SUMIF(LN!$C$4:$C$48,C116,LN!$F$4:$F$48)+SUMIF(LCE!$C$4:$C$40,C116,LCE!$F$4:$F$40)+SUMIF(LI!$C$4:$C$55,C116,LI!$F$4:$F$55)+SUMIF(LAP!$C$4:$C$45,C116,LAP!$F$4:$F$45)+SUMIF(LGDM!$C$4:$C$22,C116,LGDM!$F$4:$F$22)+SUMIF(LAM!$C$4:$C$18,C116,LAM!$F$4:$F$18)+SUMIF(DEP!$C$4:$C$55,C116,DEP!$F$4:$F$55) -> 148 | Q116: =SUMIF(LCB!$C$4:$C$45,C116,LCB!$E$4:$E$45)+SUMIF(LM!$C$4:$C$140,C116,LM!$E$4:$E$140)+SUMIF(LO!$C$4:$C$230,C116,LO!$E$4:$E$230)+SUMIF(LE!$C$4:$C$200,C116,LE!$E$4:$E$200)+SUMIF(LN!$C$4:$C$48,C116,LN!$E$4:$E$48)+SUMIF(LCE!$C$4:$C$40,C116,LCE!$E$4:$E$40)+SUMIF(LI!$C$4:$C$55,C116,LI!$E$4:$E$55)+SUMIF(LAP!$C$4:$C$45,C116,LAP!$E$4:$E$45)+SUMIF(LGDM!$C$4:$C$15,C116,LGDM!$E$4:$E$15)+SUMIF(LAM!$C$5:$C$18,C116,LAM!$E$5:$E$18)+SUMIF(DEP!$C$4:$C$55,C116,DEP!$E$4:$E$55) -> 25
B117: 4 | C117: Dra. Claudia Villanueva Cañongo | D117: =SUM(E117:O117) -> 3 | E117: =COUNTIF(LCB!$C$4:$C$40,C117) -> 0 | F117: =COUNTIF(LM!$C$4:$C$144,C117) -> 0 | G117: =COUNTIF(LO!$C$4:$C$227,C117) -> 0 | H117: =COUNTIF(LE!$C$4:$C$214,C117) -> 0 | I117: =COUNTIF(LN!$C$4:$C$53,C117) -> 3 | J117: =COUNTIF(LCE!$C$3:$C$43,C117) -> 0 | K117: =COUNTIF(LI!$C$4:$C$60,C117) -> 0 | L117: =COUNTIF(LAP!$C$5:$C$45,C117) -> 0 | M117: =COUNTIF(LGDM!$C$4:$C$22,C117) -> 0 | N117: =COUNTIF(LAM!$C$5:$C$21,C117) -> 0 | O117: =COUNTIF(DEP!$C$3:$C$61,C117) -> 0 | P117: =SUMIF(LCB!$C$4:$C$45,C117,LCB!$F$4:$F$45)+SUMIF(LM!$C$4:$C$140,C117,LM!$F$4:$F$140)+SUMIF(LO!$C$4:$C$230,C117,LO!$F$4:$F$230)+SUMIF(LE!$C$4:$C$200,C117,LE!$F$4:$F$200)+SUMIF(LN!$C$4:$C$48,C117,LN!$F$4:$F$48)+SUMIF(LCE!$C$4:$C$40,C117,LCE!$F$4:$F$40)+SUMIF(LI!$C$4:$C$55,C117,LI!$F$4:$F$55)+SUMIF(LAP!$C$4:$C$45,C117,LAP!$F$4:$F$45)+SUMIF(LGDM!$C$4:$C$22,C117,LGDM!$F$4:$F$22)+SUMIF(LAM!$C$4:$C$18,C117,LAM!$F$4:$F$18)+SUMIF(DEP!$C$4:$C$55,C117,DEP!$F$4:$F$55) -> 104 | Q117: =SUMIF(LCB!$C$4:$C$45,C117,LCB!$E$4:$E$45)+SUMIF(LM!$C$4:$C$140,C117,LM!$E$4:$E$140)+SUMIF(LO!$C$4:$C$230,C117,LO!$E$4:$E$230)+SUMIF(LE!$C$4:$C$200,C117,LE!$E$4:$E$200)+SUMIF(LN!$C$4:$C$48,C117,LN!$E$4:$E$48)+SUMIF(LCE!$C$4:$C$40,C117,LCE!$E$4:$E$40)+SUMIF(LI!$C$4:$C$55,C117,LI!$E$4:$E$55)+SUMIF(LAP!$C$4:$C$45,C117,LAP!$E$4:$E$45)+SUMIF(LGDM!$C$4:$C$15,C117,LGDM!$E$4:$E$15)+SUMIF(LAM!$C$5:$C$18,C117,LAM!$E$5:$E$18)+SUMIF(DEP!$C$4:$C$55,C117,DEP!$E$4:$E$55) -> 16
B118: 5 | C118: M.S.P. Eric Ramirez Bohorquez | D118: =SUM(E118:O118) -> 4 | E118: =COUNTIF(LCB!$C$4:$C$40,C118) -> 0 | F118: =COUNTIF(LM!$C$4:$C$144,C118) -> 0 | G118: =COUNTIF(LO!$C$4:$C$227,C118) -> 0 | H118: =COUNTIF(LE!$C$4:$C$214,C118) -> 2 | I118: =COUNTIF(LN!$C$4:$C$53,C118) -> 2 | J118: =COUNTIF(LCE!$C$3:$C$43,C118) -> 0 | K118: =COUNTIF(LI!$C$4:$C$60,C118) -> 0 | L118: =COUNTIF(LAP!$C$5:$C$45,C118) -> 0 | M118: =COUNTIF(LGDM!$C$4:$C$22,C118) -> 0 | N118: =COUNTIF(LAM!$C$5:$C$21,C118) -> 0 | O118: =COUNTIF(DEP!$C$3:$C$61,C118) -> 0 | P118: =SUMIF(LCB!$C$4:$C$45,C118,LCB!$F$4:$F$45)+SUMIF(LM!$C$4:$C$140,C118,LM!$F$4:$F$140)+SUMIF(LO!$C$4:$C$230,C118,LO!$F$4:$F$230)+SUMIF(LE!$C$4:$C$200,C118,LE!$F$4:$F$200)+SUMIF(LN!$C$4:$C$48,C118,LN!$F$4:$F$48)+SUMIF(LCE!$C$4:$C$40,C118,LCE!$F$4:$F$40)+SUMIF(LI!$C$4:$C$55,C118,LI!$F$4:$F$55)+SUMIF(LAP!$C$4:$C$45,C118,LAP!$F$4:$F$45)+SUMIF(LGDM!$C$4:$C$22,C118,LGDM!$F$4:$F$22)+SUMIF(LAM!$C$4:$C$18,C118,LAM!$F$4:$F$18)+SUMIF(DEP!$C$4:$C$55,C118,DEP!$F$4:$F$55) -> 145 | Q118: =SUMIF(LCB!$C$4:$C$45,C118,LCB!$E$4:$E$45)+SUMIF(LM!$C$4:$C$140,C118,LM!$E$4:$E$140)+SUMIF(LO!$C$4:$C$230,C118,LO!$E$4:$E$230)+SUMIF(LE!$C$4:$C$200,C118,LE!$E$4:$E$200)+SUMIF(LN!$C$4:$C$48,C118,LN!$E$4:$E$48)+SUMIF(LCE!$C$4:$C$40,C118,LCE!$E$4:$E$40)+SUMIF(LI!$C$4:$C$55,C118,LI!$E$4:$E$55)+SUMIF(LAP!$C$4:$C$45,C118,LAP!$E$4:$E$45)+SUMIF(LGDM!$C$4:$C$15,C118,LGDM!$E$4:$E$15)+SUMIF(LAM!$C$5:$C$18,C118,LAM!$E$5:$E$18)+SUMIF(DEP!$C$4:$C$55,C118,DEP!$E$4:$E$55) -> 20
B119: 6 | C119: M.S.P. Teófila Enriquez Almaraz | D119: =SUM(E119:O119) -> 3 | E119: =COUNTIF(LCB!$C$4:$C$40,C119) -> 0 | F119: =COUNTIF(LM!$C$4:$C$144,C119) -> 0 | G119: =COUNTIF(LO!$C$4:$C$227,C119) -> 0 | H119: =COUNTIF(LE!$C$4:$C$214,C119) -> 0 | I119: =COUNTIF(LN!$C$4:$C$53,C119) -> 2 | J119: =COUNTIF(LCE!$C$3:$C$43,C119) -> 0 | K119: =COUNTIF(LI!$C$4:$C$60,C119) -> 0 | L119: =COUNTIF(LAP!$C$5:$C$45,C119) -> 0 | M119: =COUNTIF(LGDM!$C$4:$C$22,C119) -> 0 | N119: =COUNTIF(LAM!$C$5:$C$21,C119) -> 0 | O119: =COUNTIF(DEP!$C$3:$C$61,C119) -> 1 | P119: =SUMIF(LCB!$C$4:$C$45,C119,LCB!$F$4:$F$45)+SUMIF(LM!$C$4:$C$140,C119,LM!$F$4:$F$140)+SUMIF(LO!$C$4:$C$230,C119,LO!$F$4:$F$230)+SUMIF(LE!$C$4:$C$200,C119,LE!$F$4:$F$200)+SUMIF(LN!$C$4:$C$48,C119,LN!$F$4:$F$48)+SUMIF(LCE!$C$4:$C$40,C119,LCE!$F$4:$F$40)+SUMIF(LI!$C$4:$C$55,C119,LI!$F$4:$F$55)+SUMIF(LAP!$C$4:$C$45,C119,LAP!$F$4:$F$45)+SUMIF(LGDM!$C$4:$C$22,C119,LGDM!$F$4:$F$22)+SUMIF(LAM!$C$4:$C$18,C119,LAM!$F$4:$F$18)+SUMIF(DEP!$C$4:$C$55,C119,DEP!$F$4:$F$55) -> 77 | Q119: =SUMIF(LCB!$C$4:$C$45,C119,LCB!$E$4:$E$45)+SUMIF(LM!$C$4:$C$140,C119,LM!$E$4:$E$140)+SUMIF(LO!$C$4:$C$230,C119,LO!$E$4:$E$230)+SUMIF(LE!$C$4:$C$200,C119,LE!$E$4:$E$200)+SUMIF(LN!$C$4:$C$48,C119,LN!$E$4:$E$48)+SUMIF(LCE!$C$4:$C$40,C119,LCE!$E$4:$E$40)+SUMIF(LI!$C$4:$C$55,C119,LI!$E$4:$E$55)+SUMIF(LAP!$C$4:$C$45,C119,LAP!$E$4:$E$45)+SUMIF(LGDM!$C$4:$C$15,C119,LGDM!$E$4:$E$15)+SUMIF(LAM!$C$5:$C$18,C119,LAM!$E$5:$E$18)+SUMIF(DEP!$C$4:$C$55,C119,DEP!$E$4:$E$55) -> 15
B120: 7 | C120: M.S.P. Felipe de Jesús Parada Luna | D120: =SUM(E120:O120) -> 5 | E120: =COUNTIF(LCB!$C$4:$C$40,C120) -> 0 | F120: =COUNTIF(LM!$C$4:$C$144,C120) -> 0 | G120: =COUNTIF(LO!$C$4:$C$227,C120) -> 0 | H120: =COUNTIF(LE!$C$4:$C$214,C120) -> 2 | I120: =COUNTIF(LN!$C$4:$C$53,C120) -> 3 | J120: =COUNTIF(LCE!$C$3:$C$43,C120) -> 0 | K120: =COUNTIF(LI!$C$4:$C$60,C120) -> 0 | L120: =COUNTIF(LAP!$C$5:$C$45,C120) -> 0 | M120: =COUNTIF(LGDM!$C$4:$C$22,C120) -> 0 | N120: =COUNTIF(LAM!$C$5:$C$21,C120) -> 0 | O120: =COUNTIF(DEP!$C$3:$C$61,C120) -> 0 | P120: =SUMIF(LCB!$C$4:$C$45,C120,LCB!$F$4:$F$45)+SUMIF(LM!$C$4:$C$140,C120,LM!$F$4:$F$140)+SUMIF(LO!$C$4:$C$230,C120,LO!$F$4:$F$230)+SUMIF(LE!$C$4:$C$200,C120,LE!$F$4:$F$200)+SUMIF(LN!$C$4:$C$48,C120,LN!$F$4:$F$48)+SUMIF(LCE!$C$4:$C$40,C120,LCE!$F$4:$F$40)+SUMIF(LI!$C$4:$C$55,C120,LI!$F$4:$F$55)+SUMIF(LAP!$C$4:$C$45,C120,LAP!$F$4:$F$45)+SUMIF(LGDM!$C$4:$C$22,C120,LGDM!$F$4:$F$22)+SUMIF(LAM!$C$4:$C$18,C120,LAM!$F$4:$F$18)+SUMIF(DEP!$C$4:$C$55,C120,DEP!$F$4:$F$55) -> 154 | Q120: =SUMIF(LCB!$C$4:$C$45,C120,LCB!$E$4:$E$45)+SUMIF(LM!$C$4:$C$140,C120,LM!$E$4:$E$140)+SUMIF(LO!$C$4:$C$230,C120,LO!$E$4:$E$230)+SUMIF(LE!$C$4:$C$200,C120,LE!$E$4:$E$200)+SUMIF(LN!$C$4:$C$48,C120,LN!$E$4:$E$48)+SUMIF(LCE!$C$4:$C$40,C120,LCE!$E$4:$E$40)+SUMIF(LI!$C$4:$C$55,C120,LI!$E$4:$E$55)+SUMIF(LAP!$C$4:$C$45,C120,LAP!$E$4:$E$45)+SUMIF(LGDM!$C$4:$C$15,C120,LGDM!$E$4:$E$15)+SUMIF(LAM!$C$5:$C$18,C120,LAM!$E$5:$E$18)+SUMIF(DEP!$C$4:$C$55,C120,DEP!$E$4:$E$55) -> 29
B121: 8 | C121: Dra. Maria Dolores Caballero Sánchez | D121: =SUM(E121:O121) -> 4 | E121: =COUNTIF(LCB!$C$4:$C$40,C121) -> 0 | F121: =COUNTIF(LM!$C$4:$C$144,C121) -> 0 | G121: =COUNTIF(LO!$C$4:$C$227,C121) -> 2 | H121: =COUNTIF(LE!$C$4:$C$214,C121) -> 0 | I121: =COUNTIF(LN!$C$4:$C$53,C121) -> 2 | J121: =COUNTIF(LCE!$C$3:$C$43,C121) -> 0 | K121: =COUNTIF(LI!$C$4:$C$60,C121) -> 0 | L121: =COUNTIF(LAP!$C$5:$C$45,C121) -> 0 | M121: =COUNTIF(LGDM!$C$4:$C$22,C121) -> 0 | N121: =COUNTIF(LAM!$C$5:$C$21,C121) -> 0 | O121: =COUNTIF(DEP!$C$3:$C$61,C121) -> 0 | P121: =SUMIF(LCB!$C$4:$C$45,C121,LCB!$F$4:$F$45)+SUMIF(LM!$C$4:$C$140,C121,LM!$F$4:$F$140)+SUMIF(LO!$C$4:$C$230,C121,LO!$F$4:$F$230)+SUMIF(LE!$C$4:$C$200,C121,LE!$F$4:$F$200)+SUMIF(LN!$C$4:$C$48,C121,LN!$F$4:$F$48)+SUMIF(LCE!$C$4:$C$40,C121,LCE!$F$4:$F$40)+SUMIF(LI!$C$4:$C$55,C121,LI!$F$4:$F$55)+SUMIF(LAP!$C$4:$C$45,C121,LAP!$F$4:$F$45)+SUMIF(LGDM!$C$4:$C$22,C121,LGDM!$F$4:$F$22)+SUMIF(LAM!$C$4:$C$18,C121,LAM!$F$4:$F$18)+SUMIF(DEP!$C$4:$C$55,C121,DEP!$F$4:$F$55) -> 143 | Q121: =SUMIF(LCB!$C$4:$C$45,C121,LCB!$E$4:$E$45)+SUMIF(LM!$C$4:$C$140,C121,LM!$E$4:$E$140)+SUMIF(LO!$C$4:$C$230,C121,LO!$E$4:$E$230)+SUMIF(LE!$C$4:$C$200,C121,LE!$E$4:$E$200)+SUMIF(LN!$C$4:$C$48,C121,LN!$E$4:$E$48)+SUMIF(LCE!$C$4:$C$40,C121,LCE!$E$4:$E$40)+SUMIF(LI!$C$4:$C$55,C121,LI!$E$4:$E$55)+SUMIF(LAP!$C$4:$C$45,C121,LAP!$E$4:$E$45)+SUMIF(LGDM!$C$4:$C$15,C121,LGDM!$E$4:$E$15)+SUMIF(LAM!$C$5:$C$18,C121,LAM!$E$5:$E$18)+SUMIF(DEP!$C$4:$C$55,C121,DEP!$E$4:$E$55) -> 21
B122: 9 | C122: M.C. Fátima Araceli Ramírez Caballero
B123: 10 | C123: M.C.S. Olaf Montes de Oca Juárez
B124: 11 | C124: M.C.B. Aracelí Meneses Corona
B128: LCE | C128: Profesor@ | D128: Materias | E128: LCB | F128: LM | G128: LO | H128: LE | I128: LN | J128: LCE | K128: LI | L128: LAP | N128: LAM | O128: DEP | P128: Total alumnos | Q128: Total hrs sem
B129: 1 | C129: Dr. Pedro Durán Férman | D129: =SUM(E129:O129) -> 1 | E129: =COUNTIF(LCB!$C$4:$C$40,C129) -> 0 | F129: =COUNTIF(LM!$C$4:$C$144,C129) -> 0 | G129: =COUNTIF(LO!$C$4:$C$227,C129) -> 1 | H129: =COUNTIF(LE!$C$4:$C$214,C129) -> 0 | I129: =COUNTIF(LN!$C$4:$C$53,C129) -> 0 | J129: =COUNTIF(LCE!$C$3:$C$43,C129) -> 0 | K129: =COUNTIF(LI!$C$4:$C$60,C129) -> 0 | L129: =COUNTIF(LAP!$C$5:$C$45,C129) -> 0 | M129: =COUNTIF(LGDM!$C$4:$C$22,C129) -> 0 | N129: =COUNTIF(LAM!$C$5:$C$21,C129) -> 0 | O129: =COUNTIF(DEP!$C$3:$C$61,C129) -> 0 | P129: =SUMIF(LCB!$C$4:$C$45,C129,LCB!$F$4:$F$45)+SUMIF(LM!$C$4:$C$140,C129,LM!$F$4:$F$140)+SUMIF(LO!$C$4:$C$230,C129,LO!$F$4:$F$230)+SUMIF(LE!$C$4:$C$200,C129,LE!$F$4:$F$200)+SUMIF(LN!$C$4:$C$48,C129,LN!$F$4:$F$48)+SUMIF(LCE!$C$4:$C$40,C129,LCE!$F$4:$F$40)+SUMIF(LI!$C$4:$C$55,C129,LI!$F$4:$F$55)+SUMIF(LAP!$C$4:$C$45,C129,LAP!$F$4:$F$45)+SUMIF(LGDM!$C$4:$C$22,C129,LGDM!$F$4:$F$22)+SUMIF(LAM!$C$4:$C$18,C129,LAM!$F$4:$F$18)+SUMIF(DEP!$C$4:$C$55,C129,DEP!$F$4:$F$55) -> 0 | Q129: =SUMIF(LCB!$C$4:$C$45,C129,LCB!$E$4:$E$45)+SUMIF(LM!$C$4:$C$140,C129,LM!$E$4:$E$140)+SUMIF(LO!$C$4:$C$230,C129,LO!$E$4:$E$230)+SUMIF(LE!$C$4:$C$200,C129,LE!$E$4:$E$200)+SUMIF(LN!$C$4:$C$48,C129,LN!$E$4:$E$48)+SUMIF(LCE!$C$4:$C$40,C129,LCE!$E$4:$E$40)+SUMIF(LI!$C$4:$C$55,C129,LI!$E$4:$E$55)+SUMIF(LAP!$C$4:$C$45,C129,LAP!$E$4:$E$45)+SUMIF(LGDM!$C$4:$C$15,C129,LGDM!$E$4:$E$15)+SUMIF(LAM!$C$5:$C$18,C129,LAM!$E$5:$E$18)+SUMIF(DEP!$C$4:$C$55,C129,DEP!$E$4:$E$55) -> 5
B130: 2 | C130: Dr. Ramón Inzunza Acosta | D130: =SUM(E130:O130) -> 3 | E130: =COUNTIF(LCB!$C$4:$C$40,C130) -> 0 | F130: =COUNTIF(LM!$C$4:$C$144,C130) -> 0 | G130: =COUNTIF(LO!$C$4:$C$227,C130) -> 0 | H130: =COUNTIF(LE!$C$4:$C$214,C130) -> 0 | I130: =COUNTIF(LN!$C$4:$C$53,C130) -> 0 | J130: =COUNTIF(LCE!$C$3:$C$43,C130) -> 3 | K130: =COUNTIF(LI!$C$4:$C$60,C130) -> 0 | L130: =COUNTIF(LAP!$C$5:$C$45,C130) -> 0 | M130: =COUNTIF(LGDM!$C$4:$C$22,C130) -> 0 | N130: =COUNTIF(LAM!$C$5:$C$21,C130) -> 0 | O130: =COUNTIF(DEP!$C$3:$C$61,C130) -> 0 | P130: =SUMIF(LCB!$C$4:$C$45,C130,LCB!$F$4:$F$45)+SUMIF(LM!$C$4:$C$140,C130,LM!$F$4:$F$140)+SUMIF(LO!$C$4:$C$230,C130,LO!$F$4:$F$230)+SUMIF(LE!$C$4:$C$200,C130,LE!$F$4:$F$200)+SUMIF(LN!$C$4:$C$48,C130,LN!$F$4:$F$48)+SUMIF(LCE!$C$4:$C$40,C130,LCE!$F$4:$F$40)+SUMIF(LI!$C$4:$C$55,C130,LI!$F$4:$F$55)+SUMIF(LAP!$C$4:$C$45,C130,LAP!$F$4:$F$45)+SUMIF(LGDM!$C$4:$C$22,C130,LGDM!$F$4:$F$22)+SUMIF(LAM!$C$4:$C$18,C130,LAM!$F$4:$F$18)+SUMIF(DEP!$C$4:$C$55,C130,DEP!$F$4:$F$55) -> 55 | Q130: =SUMIF(LCB!$C$4:$C$45,C130,LCB!$E$4:$E$45)+SUMIF(LM!$C$4:$C$140,C130,LM!$E$4:$E$140)+SUMIF(LO!$C$4:$C$230,C130,LO!$E$4:$E$230)+SUMIF(LE!$C$4:$C$200,C130,LE!$E$4:$E$200)+SUMIF(LN!$C$4:$C$48,C130,LN!$E$4:$E$48)+SUMIF(LCE!$C$4:$C$40,C130,LCE!$E$4:$E$40)+SUMIF(LI!$C$4:$C$55,C130,LI!$E$4:$E$55)+SUMIF(LAP!$C$4:$C$45,C130,LAP!$E$4:$E$45)+SUMIF(LGDM!$C$4:$C$15,C130,LGDM!$E$4:$E$15)+SUMIF(LAM!$C$5:$C$18,C130,LAM!$E$5:$E$18)+SUMIF(DEP!$C$4:$C$55,C130,DEP!$E$4:$E$55) -> 15
B131: 3 | C131: M.I.S. Fabiola Crespo Barrios | D131: =SUM(E131:O131) -> 3 | E131: =COUNTIF(LCB!$C$4:$C$40,C131) -> 0 | F131: =COUNTIF(LM!$C$4:$C$144,C131) -> 0 | G131: =COUNTIF(LO!$C$4:$C$227,C131) -> 0 | H131: =COUNTIF(LE!$C$4:$C$214,C131) -> 0 | I131: =COUNTIF(LN!$C$4:$C$53,C131) -> 0 | J131: =COUNTIF(LCE!$C$3:$C$43,C131) -> 2 | K131: =COUNTIF(LI!$C$4:$C$60,C131) -> 1 | L131: =COUNTIF(LAP!$C$5:$C$45,C131) -> 0 | M131: =COUNTIF(LGDM!$C$4:$C$22,C131) -> 0 | N131: =COUNTIF(LAM!$C$5:$C$21,C131) -> 0 | O131: =COUNTIF(DEP!$C$3:$C$61,C131) -> 0 | P131: =SUMIF(LCB!$C$4:$C$45,C131,LCB!$F$4:$F$45)+SUMIF(LM!$C$4:$C$140,C131,LM!$F$4:$F$140)+SUMIF(LO!$C$4:$C$230,C131,LO!$F$4:$F$230)+SUMIF(LE!$C$4:$C$200,C131,LE!$F$4:$F$200)+SUMIF(LN!$C$4:$C$48,C131,LN!$F$4:$F$48)+SUMIF(LCE!$C$4:$C$40,C131,LCE!$F$4:$F$40)+SUMIF(LI!$C$4:$C$55,C131,LI!$F$4:$F$55)+SUMIF(LAP!$C$4:$C$45,C131,LAP!$F$4:$F$45)+SUMIF(LGDM!$C$4:$C$22,C131,LGDM!$F$4:$F$22)+SUMIF(LAM!$C$4:$C$18,C131,LAM!$F$4:$F$18)+SUMIF(DEP!$C$4:$C$55,C131,DEP!$F$4:$F$55) -> 67 | Q131: =SUMIF(LCB!$C$4:$C$45,C131,LCB!$E$4:$E$45)+SUMIF(LM!$C$4:$C$140,C131,LM!$E$4:$E$140)+SUMIF(LO!$C$4:$C$230,C131,LO!$E$4:$E$230)+SUMIF(LE!$C$4:$C$200,C131,LE!$E$4:$E$200)+SUMIF(LN!$C$4:$C$48,C131,LN!$E$4:$E$48)+SUMIF(LCE!$C$4:$C$40,C131,LCE!$E$4:$E$40)+SUMIF(LI!$C$4:$C$55,C131,LI!$E$4:$E$55)+SUMIF(LAP!$C$4:$C$45,C131,LAP!$E$4:$E$45)+SUMIF(LGDM!$C$4:$C$15,C131,LGDM!$E$4:$E$15)+SUMIF(LAM!$C$5:$C$18,C131,LAM!$E$5:$E$18)+SUMIF(DEP!$C$4:$C$55,C131,DEP!$E$4:$E$55) -> 15
B132: 4 | C132: M.E.O. Mariano Olvera Ramírez | D132: =SUM(E132:O132) -> 3 | E132: =COUNTIF(LCB!$C$4:$C$40,C132) -> 0 | F132: =COUNTIF(LM!$C$4:$C$144,C132) -> 0 | G132: =COUNTIF(LO!$C$4:$C$227,C132) -> 0 | H132: =COUNTIF(LE!$C$4:$C$214,C132) -> 0 | I132: =COUNTIF(LN!$C$4:$C$53,C132) -> 0 | J132: =COUNTIF(LCE!$C$3:$C$43,C132) -> 3 | K132: =COUNTIF(LI!$C$4:$C$60,C132) -> 0 | L132: =COUNTIF(LAP!$C$5:$C$45,C132) -> 0 | M132: =COUNTIF(LGDM!$C$4:$C$22,C132) -> 0 | N132: =COUNTIF(LAM!$C$5:$C$21,C132) -> 0 | O132: =COUNTIF(DEP!$C$3:$C$61,C132) -> 0 | P132: =SUMIF(LCB!$C$4:$C$45,C132,LCB!$F$4:$F$45)+SUMIF(LM!$C$4:$C$140,C132,LM!$F$4:$F$140)+SUMIF(LO!$C$4:$C$230,C132,LO!$F$4:$F$230)+SUMIF(LE!$C$4:$C$200,C132,LE!$F$4:$F$200)+SUMIF(LN!$C$4:$C$48,C132,LN!$F$4:$F$48)+SUMIF(LCE!$C$4:$C$40,C132,LCE!$F$4:$F$40)+SUMIF(LI!$C$4:$C$55,C132,LI!$F$4:$F$55)+SUMIF(LAP!$C$4:$C$45,C132,LAP!$F$4:$F$45)+SUMIF(LGDM!$C$4:$C$22,C132,LGDM!$F$4:$F$22)+SUMIF(LAM!$C$4:$C$18,C132,LAM!$F$4:$F$18)+SUMIF(DEP!$C$4:$C$55,C132,DEP!$F$4:$F$55) -> 62 | Q132: =SUMIF(LCB!$C$4:$C$45,C132,LCB!$E$4:$E$45)+SUMIF(LM!$C$4:$C$140,C132,LM!$E$4:$E$140)+SUMIF(LO!$C$4:$C$230,C132,LO!$E$4:$E$230)+SUMIF(LE!$C$4:$C$200,C132,LE!$E$4:$E$200)+SUMIF(LN!$C$4:$C$48,C132,LN!$E$4:$E$48)+SUMIF(LCE!$C$4:$C$40,C132,LCE!$E$4:$E$40)+SUMIF(LI!$C$4:$C$55,C132,LI!$E$4:$E$55)+SUMIF(LAP!$C$4:$C$45,C132,LAP!$E$4:$E$45)+SUMIF(LGDM!$C$4:$C$15,C132,LGDM!$E$4:$E$15)+SUMIF(LAM!$C$5:$C$18,C132,LAM!$E$5:$E$18)+SUMIF(DEP!$C$4:$C$55,C132,DEP!$E$4:$E$55) -> 15
B133: 5 | C133: M.I.A. Hadya Concepción Díaz Ortíz | D133: =SUM(E133:O133) -> 3 | E133: =COUNTIF(LCB!$C$4:$C$40,C133) -> 0 | F133: =COUNTIF(LM!$C$4:$C$144,C133) -> 0 | G133: =COUNTIF(LO!$C$4:$C$227,C133) -> 0 | H133: =COUNTIF(LE!$C$4:$C$214,C133) -> 0 | I133: =COUNTIF(LN!$C$4:$C$53,C133) -> 0 | J133: =COUNTIF(LCE!$C$3:$C$43,C133) -> 2 | K133: =COUNTIF(LI!$C$4:$C$60,C133) -> 1 | L133: =COUNTIF(LAP!$C$5:$C$45,C133) -> 0 | M133: =COUNTIF(LGDM!$C$4:$C$22,C133) -> 0 | N133: =COUNTIF(LAM!$C$5:$C$21,C133) -> 0 | O133: =COUNTIF(DEP!$C$3:$C$61,C133) -> 0 | P133: =SUMIF(LCB!$C$4:$C$45,C133,LCB!$F$4:$F$45)+SUMIF(LM!$C$4:$C$140,C133,LM!$F$4:$F$140)+SUMIF(LO!$C$4:$C$230,C133,LO!$F$4:$F$230)+SUMIF(LE!$C$4:$C$200,C133,LE!$F$4:$F$200)+SUMIF(LN!$C$4:$C$48,C133,LN!$F$4:$F$48)+SUMIF(LCE!$C$4:$C$40,C133,LCE!$F$4:$F$40)+SUMIF(LI!$C$4:$C$55,C133,LI!$F$4:$F$55)+SUMIF(LAP!$C$4:$C$45,C133,LAP!$F$4:$F$45)+SUMIF(LGDM!$C$4:$C$22,C133,LGDM!$F$4:$F$22)+SUMIF(LAM!$C$4:$C$18,C133,LAM!$F$4:$F$18)+SUMIF(DEP!$C$4:$C$55,C133,DEP!$F$4:$F$55) -> 68 | Q133: =SUMIF(LCB!$C$4:$C$45,C133,LCB!$E$4:$E$45)+SUMIF(LM!$C$4:$C$140,C133,LM!$E$4:$E$140)+SUMIF(LO!$C$4:$C$230,C133,LO!$E$4:$E$230)+SUMIF(LE!$C$4:$C$200,C133,LE!$E$4:$E$200)+SUMIF(LN!$C$4:$C$48,C133,LN!$E$4:$E$48)+SUMIF(LCE!$C$4:$C$40,C133,LCE!$E$4:$E$40)+SUMIF(LI!$C$4:$C$55,C133,LI!$E$4:$E$55)+SUMIF(LAP!$C$4:$C$45,C133,LAP!$E$4:$E$45)+SUMIF(LGDM!$C$4:$C$15,C133,LGDM!$E$4:$E$15)+SUMIF(LAM!$C$5:$C$18,C133,LAM!$E$5:$E$18)+SUMIF(DEP!$C$4:$C$55,C133,DEP!$E$4:$E$55) -> 15
B134: 6 | C134: Dra. Reyna Minerva Hernández Vásquez | D134: =SUM(E134:O134) -> 4 | E134: =COUNTIF(LCB!$C$4:$C$40,C134) -> 0 | F134: =COUNTIF(LM!$C$4:$C$144,C134) -> 0 | G134: =COUNTIF(LO!$C$4:$C$227,C134) -> 0 | H134: =COUNTIF(LE!$C$4:$C$214,C134) -> 2 | I134: =COUNTIF(LN!$C$4:$C$53,C134) -> 1 | J134: =COUNTIF(LCE!$C$3:$C$43,C134) -> 1 | K134: =COUNTIF(LI!$C$4:$C$60,C134) -> 0 | L134: =COUNTIF(LAP!$C$5:$C$45,C134) -> 0 | M134: =COUNTIF(LGDM!$C$4:$C$22,C134) -> 0 | N134: =COUNTIF(LAM!$C$5:$C$21,C134) -> 0 | O134: =COUNTIF(DEP!$C$3:$C$61,C134) -> 0 | P134: =SUMIF(LCB!$C$4:$C$45,C134,LCB!$F$4:$F$45)+SUMIF(LM!$C$4:$C$140,C134,LM!$F$4:$F$140)+SUMIF(LO!$C$4:$C$230,C134,LO!$F$4:$F$230)+SUMIF(LE!$C$4:$C$200,C134,LE!$F$4:$F$200)+SUMIF(LN!$C$4:$C$48,C134,LN!$F$4:$F$48)+SUMIF(LCE!$C$4:$C$40,C134,LCE!$F$4:$F$40)+SUMIF(LI!$C$4:$C$55,C134,LI!$F$4:$F$55)+SUMIF(LAP!$C$4:$C$45,C134,LAP!$F$4:$F$45)+SUMIF(LGDM!$C$4:$C$22,C134,LGDM!$F$4:$F$22)+SUMIF(LAM!$C$4:$C$18,C134,LAM!$F$4:$F$18)+SUMIF(DEP!$C$4:$C$55,C134,DEP!$F$4:$F$55) -> 68 | Q134: =SUMIF(LCB!$C$4:$C$45,C134,LCB!$E$4:$E$45)+SUMIF(LM!$C$4:$C$140,C134,LM!$E$4:$E$140)+SUMIF(LO!$C$4:$C$230,C134,LO!$E$4:$E$230)+SUMIF(LE!$C$4:$C$200,C134,LE!$E$4:$E$200)+SUMIF(LN!$C$4:$C$48,C134,LN!$E$4:$E$48)+SUMIF(LCE!$C$4:$C$40,C134,LCE!$E$4:$E$40)+SUMIF(LI!$C$4:$C$55,C134,LI!$E$4:$E$55)+SUMIF(LAP!$C$4:$C$45,C134,LAP!$E$4:$E$45)+SUMIF(LGDM!$C$4:$C$15,C134,LGDM!$E$4:$E$15)+SUMIF(LAM!$C$5:$C$18,C134,LAM!$E$5:$E$18)+SUMIF(DEP!$C$4:$C$55,C134,DEP!$E$4:$E$55) -> 18
B135: 7 | C135: L.C. Zayra Trujillo Báez | D135: =SUM(E135:O135) -> 3 | E135: =COUNTIF(LCB!$C$4:$C$40,C135) -> 0 | F135: =COUNTIF(LM!$C$4:$C$144,C135) -> 0 | G135: =COUNTIF(LO!$C$4:$C$227,C135) -> 0 | H135: =COUNTIF(LE!$C$4:$C$214,C135) -> 0 | I135: =COUNTIF(LN!$C$4:$C$53,C135) -> 0 | J135: =COUNTIF(LCE!$C$3:$C$43,C135) -> 2 | K135: =COUNTIF(LI!$C$4:$C$60,C135) -> 0 | L135: =COUNTIF(LAP!$C$5:$C$45,C135) -> 0 | M135: =COUNTIF(LGDM!$C$4:$C$22,C135) -> 1 | N135: =COUNTIF(LAM!$C$5:$C$21,C135) -> 0 | O135: =COUNTIF(DEP!$C$3:$C$61,C135) -> 0 | P135: =SUMIF(LCB!$C$4:$C$45,C135,LCB!$F$4:$F$45)+SUMIF(LM!$C$4:$C$140,C135,LM!$F$4:$F$140)+SUMIF(LO!$C$4:$C$230,C135,LO!$F$4:$F$230)+SUMIF(LE!$C$4:$C$200,C135,LE!$F$4:$F$200)+SUMIF(LN!$C$4:$C$48,C135,LN!$F$4:$F$48)+SUMIF(LCE!$C$4:$C$40,C135,LCE!$F$4:$F$40)+SUMIF(LI!$C$4:$C$55,C135,LI!$F$4:$F$55)+SUMIF(LAP!$C$4:$C$45,C135,LAP!$F$4:$F$45)+SUMIF(LGDM!$C$4:$C$22,C135,LGDM!$F$4:$F$22)+SUMIF(LAM!$C$4:$C$18,C135,LAM!$F$4:$F$18)+SUMIF(DEP!$C$4:$C$55,C135,DEP!$F$4:$F$55) -> 57 | Q135: =SUMIF(LCB!$C$4:$C$45,C135,LCB!$E$4:$E$45)+SUMIF(LM!$C$4:$C$140,C135,LM!$E$4:$E$140)+SUMIF(LO!$C$4:$C$230,C135,LO!$E$4:$E$230)+SUMIF(LE!$C$4:$C$200,C135,LE!$E$4:$E$200)+SUMIF(LN!$C$4:$C$48,C135,LN!$E$4:$E$48)+SUMIF(LCE!$C$4:$C$40,C135,LCE!$E$4:$E$40)+SUMIF(LI!$C$4:$C$55,C135,LI!$E$4:$E$55)+SUMIF(LAP!$C$4:$C$45,C135,LAP!$E$4:$E$45)+SUMIF(LGDM!$C$4:$C$15,C135,LGDM!$E$4:$E$15)+SUMIF(LAM!$C$5:$C$18,C135,LAM!$E$5:$E$18)+SUMIF(DEP!$C$4:$C$55,C135,DEP!$E$4:$E$55) -> 15
B136: 8 | C136: M.C.P.E.D.R. Elsa A. Mendoza Cortés | D136: =SUM(E136:O136) -> 4 | E136: =COUNTIF(LCB!$C$4:$C$40,C136) -> 0 | F136: =COUNTIF(LM!$C$4:$C$144,C136) -> 1 | G136: =COUNTIF(LO!$C$4:$C$227,C136) -> 0 | H136: =COUNTIF(LE!$C$4:$C$214,C136) -> 2 | I136: =COUNTIF(LN!$C$4:$C$53,C136) -> 0 | J136: =COUNTIF(LCE!$C$3:$C$43,C136) -> 1 | K136: =COUNTIF(LI!$C$4:$C$60,C136) -> 0 | L136: =COUNTIF(LAP!$C$5:$C$45,C136) -> 0 | M136: =COUNTIF(LGDM!$C$4:$C$22,C136) -> 0 | N136: =COUNTIF(LAM!$C$5:$C$21,C136) -> 0 | O136: =COUNTIF(DEP!$C$3:$C$61,C136) -> 0 | P136: =SUMIF(LCB!$C$4:$C$45,C136,LCB!$F$4:$F$45)+SUMIF(LM!$C$4:$C$140,C136,LM!$F$4:$F$140)+SUMIF(LO!$C$4:$C$230,C136,LO!$F$4:$F$230)+SUMIF(LE!$C$4:$C$200,C136,LE!$F$4:$F$200)+SUMIF(LN!$C$4:$C$48,C136,LN!$F$4:$F$48)+SUMIF(LCE!$C$4:$C$40,C136,LCE!$F$4:$F$40)+SUMIF(LI!$C$4:$C$55,C136,LI!$F$4:$F$55)+SUMIF(LAP!$C$4:$C$45,C136,LAP!$F$4:$F$45)+SUMIF(LGDM!$C$4:$C$22,C136,LGDM!$F$4:$F$22)+SUMIF(LAM!$C$4:$C$18,C136,LAM!$F$4:$F$18)+SUMIF(DEP!$C$4:$C$55,C136,DEP!$F$4:$F$55) -> 71 | Q136: =SUMIF(LCB!$C$4:$C$45,C136,LCB!$E$4:$E$45)+SUMIF(LM!$C$4:$C$140,C136,LM!$E$4:$E$140)+SUMIF(LO!$C$4:$C$230,C136,LO!$E$4:$E$230)+SUMIF(LE!$C$4:$C$200,C136,LE!$E$4:$E$200)+SUMIF(LN!$C$4:$C$48,C136,LN!$E$4:$E$48)+SUMIF(LCE!$C$4:$C$40,C136,LCE!$E$4:$E$40)+SUMIF(LI!$C$4:$C$55,C136,LI!$E$4:$E$55)+SUMIF(LAP!$C$4:$C$45,C136,LAP!$E$4:$E$45)+SUMIF(LGDM!$C$4:$C$15,C136,LGDM!$E$4:$E$15)+SUMIF(LAM!$C$5:$C$18,C136,LAM!$E$5:$E$18)+SUMIF(DEP!$C$4:$C$55,C136,DEP!$E$4:$E$55) -> 17
B137: 9 | C137: M.C.D.R.T. Víctor Santiago Sarmiento | D137: =SUM(E137:O137) -> 2 | E137: =COUNTIF(LCB!$C$4:$C$40,C137) -> 0 | F137: =COUNTIF(LM!$C$4:$C$144,C137) -> 0 | G137: =COUNTIF(LO!$C$4:$C$227,C137) -> 0 | H137: =COUNTIF(LE!$C$4:$C$214,C137) -> 0 | I137: =COUNTIF(LN!$C$4:$C$53,C137) -> 0 | J137: =COUNTIF(LCE!$C$3:$C$43,C137) -> 2 | K137: =COUNTIF(LI!$C$4:$C$60,C137) -> 0 | L137: =COUNTIF(LAP!$C$5:$C$45,C137) -> 0 | M137: =COUNTIF(LGDM!$C$4:$C$22,C137) -> 0 | N137: =COUNTIF(LAM!$C$5:$C$21,C137) -> 0 | O137: =COUNTIF(DEP!$C$3:$C$61,C137) -> 0 | P137: =SUMIF(LCB!$C$4:$C$45,C137,LCB!$F$4:$F$45)+SUMIF(LM!$C$4:$C$140,C137,LM!$F$4:$F$140)+SUMIF(LO!$C$4:$C$230,C137,LO!$F$4:$F$230)+SUMIF(LE!$C$4:$C$200,C137,LE!$F$4:$F$200)+SUMIF(LN!$C$4:$C$48,C137,LN!$F$4:$F$48)+SUMIF(LCE!$C$4:$C$40,C137,LCE!$F$4:$F$40)+SUMIF(LI!$C$4:$C$55,C137,LI!$F$4:$F$55)+SUMIF(LAP!$C$4:$C$45,C137,LAP!$F$4:$F$45)+SUMIF(LGDM!$C$4:$C$22,C137,LGDM!$F$4:$F$22)+SUMIF(LAM!$C$4:$C$18,C137,LAM!$F$4:$F$18)+SUMIF(DEP!$C$4:$C$55,C137,DEP!$F$4:$F$55) -> 40 | Q137: =SUMIF(LCB!$C$4:$C$45,C137,LCB!$E$4:$E$45)+SUMIF(LM!$C$4:$C$140,C137,LM!$E$4:$E$140)+SUMIF(LO!$C$4:$C$230,C137,LO!$E$4:$E$230)+SUMIF(LE!$C$4:$C$200,C137,LE!$E$4:$E$200)+SUMIF(LN!$C$4:$C$48,C137,LN!$E$4:$E$48)+SUMIF(LCE!$C$4:$C$40,C137,LCE!$E$4:$E$40)+SUMIF(LI!$C$4:$C$55,C137,LI!$E$4:$E$55)+SUMIF(LAP!$C$4:$C$45,C137,LAP!$E$4:$E$45)+SUMIF(LGDM!$C$4:$C$15,C137,LGDM!$E$4:$E$15)+SUMIF(LAM!$C$5:$C$18,C137,LAM!$E$5:$E$18)+SUMIF(DEP!$C$4:$C$55,C137,DEP!$E$4:$E$55) -> 10
B138: 10 | C138: M.F. Araceli Luz Alva Rodríguez Martínez | D138: =SUM(E138:O138) -> 4 | E138: =COUNTIF(LCB!$C$4:$C$40,C138) -> 1 | F138: =COUNTIF(LM!$C$4:$C$144,C138) -> 2 | G138: =COUNTIF(LO!$C$4:$C$227,C138) -> 1 | H138: =COUNTIF(LE!$C$4:$C$214,C138) -> 0 | I138: =COUNTIF(LN!$C$4:$C$53,C138) -> 0 | J138: =COUNTIF(LCE!$C$3:$C$43,C138) -> 0 | K138: =COUNTIF(LI!$C$4:$C$60,C138) -> 0 | L138: =COUNTIF(LAP!$C$5:$C$45,C138) -> 0 | M138: =COUNTIF(LGDM!$C$4:$C$22,C138) -> 0 | N138: =COUNTIF(LAM!$C$5:$C$21,C138) -> 0 | O138: =COUNTIF(DEP!$C$3:$C$61,C138) -> 0 | P138: =SUMIF(LCB!$C$4:$C$45,C138,LCB!$F$4:$F$45)+SUMIF(LM!$C$4:$C$140,C138,LM!$F$4:$F$140)+SUMIF(LO!$C$4:$C$230,C138,LO!$F$4:$F$230)+SUMIF(LE!$C$4:$C$200,C138,LE!$F$4:$F$200)+SUMIF(LN!$C$4:$C$48,C138,LN!$F$4:$F$48)+SUMIF(LCE!$C$4:$C$40,C138,LCE!$F$4:$F$40)+SUMIF(LI!$C$4:$C$55,C138,LI!$F$4:$F$55)+SUMIF(LAP!$C$4:$C$45,C138,LAP!$F$4:$F$45)+SUMIF(LGDM!$C$4:$C$22,C138,LGDM!$F$4:$F$22)+SUMIF(LAM!$C$4:$C$18,C138,LAM!$F$4:$F$18)+SUMIF(DEP!$C$4:$C$55,C138,DEP!$F$4:$F$55) -> 70 | Q138: =SUMIF(LCB!$C$4:$C$45,C138,LCB!$E$4:$E$45)+SUMIF(LM!$C$4:$C$140,C138,LM!$E$4:$E$140)+SUMIF(LO!$C$4:$C$230,C138,LO!$E$4:$E$230)+SUMIF(LE!$C$4:$C$200,C138,LE!$E$4:$E$200)+SUMIF(LN!$C$4:$C$48,C138,LN!$E$4:$E$48)+SUMIF(LCE!$C$4:$C$40,C138,LCE!$E$4:$E$40)+SUMIF(LI!$C$4:$C$55,C138,LI!$E$4:$E$55)+SUMIF(LAP!$C$4:$C$45,C138,LAP!$E$4:$E$45)+SUMIF(LGDM!$C$4:$C$15,C138,LGDM!$E$4:$E$15)+SUMIF(LAM!$C$5:$C$18,C138,LAM!$E$5:$E$18)+SUMIF(DEP!$C$4:$C$55,C138,DEP!$E$4:$E$55) -> 17
B139: 11 | C139: M.A. Aurelia Gómez Gómez | D139: =SUM(E139:O139) -> 4 | E139: =COUNTIF(LCB!$C$4:$C$40,C139) -> 0 | F139: =COUNTIF(LM!$C$4:$C$144,C139) -> 2 | G139: =COUNTIF(LO!$C$4:$C$227,C139) -> 2 | H139: =COUNTIF(LE!$C$4:$C$214,C139) -> 0 | I139: =COUNTIF(LN!$C$4:$C$53,C139) -> 0 | J139: =COUNTIF(LCE!$C$3:$C$43,C139) -> 0 | K139: =COUNTIF(LI!$C$4:$C$60,C139) -> 0 | L139: =COUNTIF(LAP!$C$5:$C$45,C139) -> 0 | M139: =COUNTIF(LGDM!$C$4:$C$22,C139) -> 0 | N139: =COUNTIF(LAM!$C$5:$C$21,C139) -> 0 | O139: =COUNTIF(DEP!$C$3:$C$61,C139) -> 0 | P139: =SUMIF(LCB!$C$4:$C$45,C139,LCB!$F$4:$F$45)+SUMIF(LM!$C$4:$C$140,C139,LM!$F$4:$F$140)+SUMIF(LO!$C$4:$C$230,C139,LO!$F$4:$F$230)+SUMIF(LE!$C$4:$C$200,C139,LE!$F$4:$F$200)+SUMIF(LN!$C$4:$C$48,C139,LN!$F$4:$F$48)+SUMIF(LCE!$C$4:$C$40,C139,LCE!$F$4:$F$40)+SUMIF(LI!$C$4:$C$55,C139,LI!$F$4:$F$55)+SUMIF(LAP!$C$4:$C$45,C139,LAP!$F$4:$F$45)+SUMIF(LGDM!$C$4:$C$22,C139,LGDM!$F$4:$F$22)+SUMIF(LAM!$C$4:$C$18,C139,LAM!$F$4:$F$18)+SUMIF(DEP!$C$4:$C$55,C139,DEP!$F$4:$F$55) -> 92 | Q139: =SUMIF(LCB!$C$4:$C$45,C139,LCB!$E$4:$E$45)+SUMIF(LM!$C$4:$C$140,C139,LM!$E$4:$E$140)+SUMIF(LO!$C$4:$C$230,C139,LO!$E$4:$E$230)+SUMIF(LE!$C$4:$C$200,C139,LE!$E$4:$E$200)+SUMIF(LN!$C$4:$C$48,C139,LN!$E$4:$E$48)+SUMIF(LCE!$C$4:$C$40,C139,LCE!$E$4:$E$40)+SUMIF(LI!$C$4:$C$55,C139,LI!$E$4:$E$55)+SUMIF(LAP!$C$4:$C$45,C139,LAP!$E$4:$E$45)+SUMIF(LGDM!$C$4:$C$15,C139,LGDM!$E$4:$E$15)+SUMIF(LAM!$C$5:$C$18,C139,LAM!$E$5:$E$18)+SUMIF(DEP!$C$4:$C$55,C139,DEP!$E$4:$E$55) -> 18
B140: 12 | C140: M.F. Máximo Jorge Saavedra García | D140: =SUM(E140:O140) -> 3 | E140: =COUNTIF(LCB!$C$4:$C$40,C140) -> 0 | F140: =COUNTIF(LM!$C$4:$C$144,C140) -> 0 | G140: =COUNTIF(LO!$C$4:$C$227,C140) -> 0 | H140: =COUNTIF(LE!$C$4:$C$214,C140) -> 0 | I140: =COUNTIF(LN!$C$4:$C$53,C140) -> 0 | J140: =COUNTIF(LCE!$C$3:$C$43,C140) -> 2 | K140: =COUNTIF(LI!$C$4:$C$60,C140) -> 0 | L140: =COUNTIF(LAP!$C$5:$C$45,C140) -> 1 | M140: =COUNTIF(LGDM!$C$4:$C$22,C140) -> 0 | N140: =COUNTIF(LAM!$C$5:$C$21,C140) -> 0 | O140: =COUNTIF(DEP!$C$3:$C$61,C140) -> 0 | P140: =SUMIF(LCB!$C$4:$C$45,C140,LCB!$F$4:$F$45)+SUMIF(LM!$C$4:$C$140,C140,LM!$F$4:$F$140)+SUMIF(LO!$C$4:$C$230,C140,LO!$F$4:$F$230)+SUMIF(LE!$C$4:$C$200,C140,LE!$F$4:$F$200)+SUMIF(LN!$C$4:$C$48,C140,LN!$F$4:$F$48)+SUMIF(LCE!$C$4:$C$40,C140,LCE!$F$4:$F$40)+SUMIF(LI!$C$4:$C$55,C140,LI!$F$4:$F$55)+SUMIF(LAP!$C$4:$C$45,C140,LAP!$F$4:$F$45)+SUMIF(LGDM!$C$4:$C$22,C140,LGDM!$F$4:$F$22)+SUMIF(LAM!$C$4:$C$18,C140,LAM!$F$4:$F$18)+SUMIF(DEP!$C$4:$C$55,C140,DEP!$F$4:$F$55) -> 43 | Q140: =SUMIF(LCB!$C$4:$C$45,C140,LCB!$E$4:$E$45)+SUMIF(LM!$C$4:$C$140,C140,LM!$E$4:$E$140)+SUMIF(LO!$C$4:$C$230,C140,LO!$E$4:$E$230)+SUMIF(LE!$C$4:$C$200,C140,LE!$E$4:$E$200)+SUMIF(LN!$C$4:$C$48,C140,LN!$E$4:$E$48)+SUMIF(LCE!$C$4:$C$40,C140,LCE!$E$4:$E$40)+SUMIF(LI!$C$4:$C$55,C140,LI!$E$4:$E$55)+SUMIF(LAP!$C$4:$C$45,C140,LAP!$E$4:$E$45)+SUMIF(LGDM!$C$4:$C$15,C140,LGDM!$E$4:$E$15)+SUMIF(LAM!$C$5:$C$18,C140,LAM!$E$5:$E$18)+SUMIF(DEP!$C$4:$C$55,C140,DEP!$E$4:$E$55) -> 15
B141: 13 | C141: M.C.P.E.D.R. Marco A. Santos Martínez
B142: 14 | C142: Dra. Felícitas Ortíz García
B145: LI | C145: Profesor@ | D145: Materias | E145: LCB | F145: LM | G145: LO | H145: LE | I145: LN | J145: LCE | K145: LI | L145: LAP | M145: LGDM | N145: LAM | O145: DEP | P145: Total alumnos | Q145: Total hrs sem
B146: 1 | C146: M.T.I.E. Irving Ulises Hernández Miguel | D146: =SUM(E146:O146) -> 1 | E146: =COUNTIF(LCB!$C$4:$C$40,C146) -> 0 | F146: =COUNTIF(LM!$C$4:$C$144,C146) -> 0 | G146: =COUNTIF(LO!$C$4:$C$227,C146) -> 0 | H146: =COUNTIF(LE!$C$4:$C$214,C146) -> 0 | I146: =COUNTIF(LN!$C$4:$C$53,C146) -> 0 | J146: =COUNTIF(LCE!$C$3:$C$43,C146) -> 0 | K146: =COUNTIF(LI!$C$4:$C$60,C146) -> 1 | L146: =COUNTIF(LAP!$C$5:$C$45,C146) -> 0 | M146: =COUNTIF(LGDM!$C$4:$C$22,C146) -> 0 | N146: =COUNTIF(LAM!$C$5:$C$21,C146) -> 0 | O146: =COUNTIF(DEP!$C$3:$C$61,C146) -> 0 | P146: =SUMIF(LCB!$C$4:$C$45,C146,LCB!$F$4:$F$45)+SUMIF(LM!$C$4:$C$140,C146,LM!$F$4:$F$140)+SUMIF(LO!$C$4:$C$230,C146,LO!$F$4:$F$230)+SUMIF(LE!$C$4:$C$200,C146,LE!$F$4:$F$200)+SUMIF(LN!$C$4:$C$48,C146,LN!$F$4:$F$48)+SUMIF(LCE!$C$4:$C$40,C146,LCE!$F$4:$F$40)+SUMIF(LI!$C$4:$C$55,C146,LI!$F$4:$F$55)+SUMIF(LAP!$C$4:$C$45,C146,LAP!$F$4:$F$45)+SUMIF(LGDM!$C$4:$C$22,C146,LGDM!$F$4:$F$22)+SUMIF(LAM!$C$4:$C$18,C146,LAM!$F$4:$F$18)+SUMIF(DEP!$C$4:$C$55,C146,DEP!$F$4:$F$55) -> 16 | Q146: =SUMIF(LCB!$C$4:$C$45,C146,LCB!$E$4:$E$45)+SUMIF(LM!$C$4:$C$140,C146,LM!$E$4:$E$140)+SUMIF(LO!$C$4:$C$230,C146,LO!$E$4:$E$230)+SUMIF(LE!$C$4:$C$200,C146,LE!$E$4:$E$200)+SUMIF(LN!$C$4:$C$48,C146,LN!$E$4:$E$48)+SUMIF(LCE!$C$4:$C$40,C146,LCE!$E$4:$E$40)+SUMIF(LI!$C$4:$C$55,C146,LI!$E$4:$E$55)+SUMIF(LAP!$C$4:$C$45,C146,LAP!$E$4:$E$45)+SUMIF(LGDM!$C$4:$C$15,C146,LGDM!$E$4:$E$15)+SUMIF(LAM!$C$5:$C$18,C146,LAM!$E$5:$E$18)+SUMIF(DEP!$C$4:$C$55,C146,DEP!$E$4:$E$55) -> 5
B147: 2 | C147: M.C.C. Lirio Ruíz Guerra | D147: =SUM(E147:O147) -> 3 | E147: =COUNTIF(LCB!$C$4:$C$40,C147) -> 0 | F147: =COUNTIF(LM!$C$4:$C$144,C147) -> 0 | G147: =COUNTIF(LO!$C$4:$C$227,C147) -> 0 | H147: =COUNTIF(LE!$C$4:$C$214,C147) -> 0 | I147: =COUNTIF(LN!$C$4:$C$53,C147) -> 0 | J147: =COUNTIF(LCE!$C$3:$C$43,C147) -> 0 | K147: =COUNTIF(LI!$C$4:$C$60,C147) -> 3 | L147: =COUNTIF(LAP!$C$5:$C$45,C147) -> 0 | M147: =COUNTIF(LGDM!$C$4:$C$22,C147) -> 0 | N147: =COUNTIF(LAM!$C$5:$C$21,C147) -> 0 | O147: =COUNTIF(DEP!$C$3:$C$61,C147) -> 0 | P147: =SUMIF(LCB!$C$4:$C$45,C147,LCB!$F$4:$F$45)+SUMIF(LM!$C$4:$C$140,C147,LM!$F$4:$F$140)+SUMIF(LO!$C$4:$C$230,C147,LO!$F$4:$F$230)+SUMIF(LE!$C$4:$C$200,C147,LE!$F$4:$F$200)+SUMIF(LN!$C$4:$C$48,C147,LN!$F$4:$F$48)+SUMIF(LCE!$C$4:$C$40,C147,LCE!$F$4:$F$40)+SUMIF(LI!$C$4:$C$55,C147,LI!$F$4:$F$55)+SUMIF(LAP!$C$4:$C$45,C147,LAP!$F$4:$F$45)+SUMIF(LGDM!$C$4:$C$22,C147,LGDM!$F$4:$F$22)+SUMIF(LAM!$C$4:$C$18,C147,LAM!$F$4:$F$18)+SUMIF(DEP!$C$4:$C$55,C147,DEP!$F$4:$F$55) -> 61 | Q147: =SUMIF(LCB!$C$4:$C$45,C147,LCB!$E$4:$E$45)+SUMIF(LM!$C$4:$C$140,C147,LM!$E$4:$E$140)+SUMIF(LO!$C$4:$C$230,C147,LO!$E$4:$E$230)+SUMIF(LE!$C$4:$C$200,C147,LE!$E$4:$E$200)+SUMIF(LN!$C$4:$C$48,C147,LN!$E$4:$E$48)+SUMIF(LCE!$C$4:$C$40,C147,LCE!$E$4:$E$40)+SUMIF(LI!$C$4:$C$55,C147,LI!$E$4:$E$55)+SUMIF(LAP!$C$4:$C$45,C147,LAP!$E$4:$E$45)+SUMIF(LGDM!$C$4:$C$15,C147,LGDM!$E$4:$E$15)+SUMIF(LAM!$C$5:$C$18,C147,LAM!$E$5:$E$18)+SUMIF(DEP!$C$4:$C$55,C147,DEP!$E$4:$E$55) -> 15
B148: 3 | C148: M.C. Mónica Pérez Meza | D148: =SUM(E148:O148) -> 3 | E148: =COUNTIF(LCB!$C$4:$C$40,C148) -> 1 | F148: =COUNTIF(LM!$C$4:$C$144,C148) -> 0 | G148: =COUNTIF(LO!$C$4:$C$227,C148) -> 0 | H148: =COUNTIF(LE!$C$4:$C$214,C148) -> 0 | I148: =COUNTIF(LN!$C$4:$C$53,C148) -> 0 | J148: =COUNTIF(LCE!$C$3:$C$43,C148) -> 0 | K148: =COUNTIF(LI!$C$4:$C$60,C148) -> 2 | L148: =COUNTIF(LAP!$C$5:$C$45,C148) -> 0 | M148: =COUNTIF(LGDM!$C$4:$C$22,C148) -> 0 | N148: =COUNTIF(LAM!$C$5:$C$21,C148) -> 0 | O148: =COUNTIF(DEP!$C$3:$C$61,C148) -> 0 | P148: =SUMIF(LCB!$C$4:$C$45,C148,LCB!$F$4:$F$45)+SUMIF(LM!$C$4:$C$140,C148,LM!$F$4:$F$140)+SUMIF(LO!$C$4:$C$230,C148,LO!$F$4:$F$230)+SUMIF(LE!$C$4:$C$200,C148,LE!$F$4:$F$200)+SUMIF(LN!$C$4:$C$48,C148,LN!$F$4:$F$48)+SUMIF(LCE!$C$4:$C$40,C148,LCE!$F$4:$F$40)+SUMIF(LI!$C$4:$C$55,C148,LI!$F$4:$F$55)+SUMIF(LAP!$C$4:$C$45,C148,LAP!$F$4:$F$45)+SUMIF(LGDM!$C$4:$C$22,C148,LGDM!$F$4:$F$22)+SUMIF(LAM!$C$4:$C$18,C148,LAM!$F$4:$F$18)+SUMIF(DEP!$C$4:$C$55,C148,DEP!$F$4:$F$55) -> 43 | Q148: =SUMIF(LCB!$C$4:$C$45,C148,LCB!$E$4:$E$45)+SUMIF(LM!$C$4:$C$140,C148,LM!$E$4:$E$140)+SUMIF(LO!$C$4:$C$230,C148,LO!$E$4:$E$230)+SUMIF(LE!$C$4:$C$200,C148,LE!$E$4:$E$200)+SUMIF(LN!$C$4:$C$48,C148,LN!$E$4:$E$48)+SUMIF(LCE!$C$4:$C$40,C148,LCE!$E$4:$E$40)+SUMIF(LI!$C$4:$C$55,C148,LI!$E$4:$E$55)+SUMIF(LAP!$C$4:$C$45,C148,LAP!$E$4:$E$45)+SUMIF(LGDM!$C$4:$C$15,C148,LGDM!$E$4:$E$15)+SUMIF(LAM!$C$5:$C$18,C148,LAM!$E$5:$E$18)+SUMIF(DEP!$C$4:$C$55,C148,DEP!$E$4:$E$55) -> 15
B149: 4 | C149: M.C.A.C. José Alberto Cruz Tolentino | D149: =SUM(E149:O149) -> 3 | E149: =COUNTIF(LCB!$C$4:$C$40,C149) -> 0 | F149: =COUNTIF(LM!$C$4:$C$144,C149) -> 0 | G149: =COUNTIF(LO!$C$4:$C$227,C149) -> 3 | H149: =COUNTIF(LE!$C$4:$C$214,C149) -> 0 | I149: =COUNTIF(LN!$C$4:$C$53,C149) -> 0 | J149: =COUNTIF(LCE!$C$3:$C$43,C149) -> 0 | K149: =COUNTIF(LI!$C$4:$C$60,C149) -> 0 | L149: =COUNTIF(LAP!$C$5:$C$45,C149) -> 0 | M149: =COUNTIF(LGDM!$C$4:$C$22,C149) -> 0 | N149: =COUNTIF(LAM!$C$5:$C$21,C149) -> 0 | O149: =COUNTIF(DEP!$C$3:$C$61,C149) -> 0 | P149: =SUMIF(LCB!$C$4:$C$45,C149,LCB!$F$4:$F$45)+SUMIF(LM!$C$4:$C$140,C149,LM!$F$4:$F$140)+SUMIF(LO!$C$4:$C$230,C149,LO!$F$4:$F$230)+SUMIF(LE!$C$4:$C$200,C149,LE!$F$4:$F$200)+SUMIF(LN!$C$4:$C$48,C149,LN!$F$4:$F$48)+SUMIF(LCE!$C$4:$C$40,C149,LCE!$F$4:$F$40)+SUMIF(LI!$C$4:$C$55,C149,LI!$F$4:$F$55)+SUMIF(LAP!$C$4:$C$45,C149,LAP!$F$4:$F$45)+SUMIF(LGDM!$C$4:$C$22,C149,LGDM!$F$4:$F$22)+SUMIF(LAM!$C$4:$C$18,C149,LAM!$F$4:$F$18)+SUMIF(DEP!$C$4:$C$55,C149,DEP!$F$4:$F$55) -> 96 | Q149: =SUMIF(LCB!$C$4:$C$45,C149,LCB!$E$4:$E$45)+SUMIF(LM!$C$4:$C$140,C149,LM!$E$4:$E$140)+SUMIF(LO!$C$4:$C$230,C149,LO!$E$4:$E$230)+SUMIF(LE!$C$4:$C$200,C149,LE!$E$4:$E$200)+SUMIF(LN!$C$4:$C$48,C149,LN!$E$4:$E$48)+SUMIF(LCE!$C$4:$C$40,C149,LCE!$E$4:$E$40)+SUMIF(LI!$C$4:$C$55,C149,LI!$E$4:$E$55)+SUMIF(LAP!$C$4:$C$45,C149,LAP!$E$4:$E$45)+SUMIF(LGDM!$C$4:$C$15,C149,LGDM!$E$4:$E$15)+SUMIF(LAM!$C$5:$C$18,C149,LAM!$E$5:$E$18)+SUMIF(DEP!$C$4:$C$55,C149,DEP!$E$4:$E$55) -> 15
B150: 5 | C150: Dra. Aidee Cruz Barragán | D150: =SUM(E150:O150) -> 3 | E150: =COUNTIF(LCB!$C$4:$C$40,C150) -> 1 | F150: =COUNTIF(LM!$C$4:$C$144,C150) -> 0 | G150: =COUNTIF(LO!$C$4:$C$227,C150) -> 0 | H150: =COUNTIF(LE!$C$4:$C$214,C150) -> 0 | I150: =COUNTIF(LN!$C$4:$C$53,C150) -> 0 | J150: =COUNTIF(LCE!$C$3:$C$43,C150) -> 0 | K150: =COUNTIF(LI!$C$4:$C$60,C150) -> 0 | L150: =COUNTIF(LAP!$C$5:$C$45,C150) -> 0 | M150: =COUNTIF(LGDM!$C$4:$C$22,C150) -> 0 | N150: =COUNTIF(LAM!$C$5:$C$21,C150) -> 0 | O150: =COUNTIF(DEP!$C$3:$C$61,C150) -> 2 | P150: =SUMIF(LCB!$C$4:$C$45,C150,LCB!$F$4:$F$45)+SUMIF(LM!$C$4:$C$140,C150,LM!$F$4:$F$140)+SUMIF(LO!$C$4:$C$230,C150,LO!$F$4:$F$230)+SUMIF(LE!$C$4:$C$200,C150,LE!$F$4:$F$200)+SUMIF(LN!$C$4:$C$48,C150,LN!$F$4:$F$48)+SUMIF(LCE!$C$4:$C$40,C150,LCE!$F$4:$F$40)+SUMIF(LI!$C$4:$C$55,C150,LI!$F$4:$F$55)+SUMIF(LAP!$C$4:$C$45,C150,LAP!$F$4:$F$45)+SUMIF(LGDM!$C$4:$C$22,C150,LGDM!$F$4:$F$22)+SUMIF(LAM!$C$4:$C$18,C150,LAM!$F$4:$F$18)+SUMIF(DEP!$C$4:$C$55,C150,DEP!$F$4:$F$55) -> 0 | Q150: =SUMIF(LCB!$C$4:$C$45,C150,LCB!$E$4:$E$45)+SUMIF(LM!$C$4:$C$140,C150,LM!$E$4:$E$140)+SUMIF(LO!$C$4:$C$230,C150,LO!$E$4:$E$230)+SUMIF(LE!$C$4:$C$200,C150,LE!$E$4:$E$200)+SUMIF(LN!$C$4:$C$48,C150,LN!$E$4:$E$48)+SUMIF(LCE!$C$4:$C$40,C150,LCE!$E$4:$E$40)+SUMIF(LI!$C$4:$C$55,C150,LI!$E$4:$E$55)+SUMIF(LAP!$C$4:$C$45,C150,LAP!$E$4:$E$45)+SUMIF(LGDM!$C$4:$C$15,C150,LGDM!$E$4:$E$15)+SUMIF(LAM!$C$5:$C$18,C150,LAM!$E$5:$E$18)+SUMIF(DEP!$C$4:$C$55,C150,DEP!$E$4:$E$55) -> 12
B151: 6 | C151: Dr. Arisaí Darío Barragán López | D151: =SUM(E151:O151) -> 2 | E151: =COUNTIF(LCB!$C$4:$C$40,C151) -> 0 | F151: =COUNTIF(LM!$C$4:$C$144,C151) -> 0 | G151: =COUNTIF(LO!$C$4:$C$227,C151) -> 0 | H151: =COUNTIF(LE!$C$4:$C$214,C151) -> 0 | I151: =COUNTIF(LN!$C$4:$C$53,C151) -> 0 | J151: =COUNTIF(LCE!$C$3:$C$43,C151) -> 0 | K151: =COUNTIF(LI!$C$4:$C$60,C151) -> 2 | L151: =COUNTIF(LAP!$C$5:$C$45,C151) -> 0 | M151: =COUNTIF(LGDM!$C$4:$C$22,C151) -> 0 | N151: =COUNTIF(LAM!$C$5:$C$21,C151) -> 0 | O151: =COUNTIF(DEP!$C$3:$C$61,C151) -> 0 | P151: =SUMIF(LCB!$C$4:$C$45,C151,LCB!$F$4:$F$45)+SUMIF(LM!$C$4:$C$140,C151,LM!$F$4:$F$140)+SUMIF(LO!$C$4:$C$230,C151,LO!$F$4:$F$230)+SUMIF(LE!$C$4:$C$200,C151,LE!$F$4:$F$200)+SUMIF(LN!$C$4:$C$48,C151,LN!$F$4:$F$48)+SUMIF(LCE!$C$4:$C$40,C151,LCE!$F$4:$F$40)+SUMIF(LI!$C$4:$C$55,C151,LI!$F$4:$F$55)+SUMIF(LAP!$C$4:$C$45,C151,LAP!$F$4:$F$45)+SUMIF(LGDM!$C$4:$C$22,C151,LGDM!$F$4:$F$22)+SUMIF(LAM!$C$4:$C$18,C151,LAM!$F$4:$F$18)+SUMIF(DEP!$C$4:$C$55,C151,DEP!$F$4:$F$55) -> 40 | Q151: =SUMIF(LCB!$C$4:$C$45,C151,LCB!$E$4:$E$45)+SUMIF(LM!$C$4:$C$140,C151,LM!$E$4:$E$140)+SUMIF(LO!$C$4:$C$230,C151,LO!$E$4:$E$230)+SUMIF(LE!$C$4:$C$200,C151,LE!$E$4:$E$200)+SUMIF(LN!$C$4:$C$48,C151,LN!$E$4:$E$48)+SUMIF(LCE!$C$4:$C$40,C151,LCE!$E$4:$E$40)+SUMIF(LI!$C$4:$C$55,C151,LI!$E$4:$E$55)+SUMIF(LAP!$C$4:$C$45,C151,LAP!$E$4:$E$45)+SUMIF(LGDM!$C$4:$C$15,C151,LGDM!$E$4:$E$15)+SUMIF(LAM!$C$5:$C$18,C151,LAM!$E$5:$E$18)+SUMIF(DEP!$C$4:$C$55,C151,DEP!$E$4:$E$55) -> 10
B152: 7 | C152: M.C. Enrique García Reyes | D152: =SUM(E152:O152) -> 3 | E152: =COUNTIF(LCB!$C$4:$C$40,C152) -> 0 | F152: =COUNTIF(LM!$C$4:$C$144,C152) -> 0 | G152: =COUNTIF(LO!$C$4:$C$227,C152) -> 0 | H152: =COUNTIF(LE!$C$4:$C$214,C152) -> 0 | I152: =COUNTIF(LN!$C$4:$C$53,C152) -> 0 | J152: =COUNTIF(LCE!$C$3:$C$43,C152) -> 0 | K152: =COUNTIF(LI!$C$4:$C$60,C152) -> 3 | L152: =COUNTIF(LAP!$C$5:$C$45,C152) -> 0 | M152: =COUNTIF(LGDM!$C$4:$C$22,C152) -> 0 | N152: =COUNTIF(LAM!$C$5:$C$21,C152) -> 0 | O152: =COUNTIF(DEP!$C$3:$C$61,C152) -> 0 | P152: =SUMIF(LCB!$C$4:$C$45,C152,LCB!$F$4:$F$45)+SUMIF(LM!$C$4:$C$140,C152,LM!$F$4:$F$140)+SUMIF(LO!$C$4:$C$230,C152,LO!$F$4:$F$230)+SUMIF(LE!$C$4:$C$200,C152,LE!$F$4:$F$200)+SUMIF(LN!$C$4:$C$48,C152,LN!$F$4:$F$48)+SUMIF(LCE!$C$4:$C$40,C152,LCE!$F$4:$F$40)+SUMIF(LI!$C$4:$C$55,C152,LI!$F$4:$F$55)+SUMIF(LAP!$C$4:$C$45,C152,LAP!$F$4:$F$45)+SUMIF(LGDM!$C$4:$C$22,C152,LGDM!$F$4:$F$22)+SUMIF(LAM!$C$4:$C$18,C152,LAM!$F$4:$F$18)+SUMIF(DEP!$C$4:$C$55,C152,DEP!$F$4:$F$55) -> 67 | Q152: =SUMIF(LCB!$C$4:$C$45,C152,LCB!$E$4:$E$45)+SUMIF(LM!$C$4:$C$140,C152,LM!$E$4:$E$140)+SUMIF(LO!$C$4:$C$230,C152,LO!$E$4:$E$230)+SUMIF(LE!$C$4:$C$200,C152,LE!$E$4:$E$200)+SUMIF(LN!$C$4:$C$48,C152,LN!$E$4:$E$48)+SUMIF(LCE!$C$4:$C$40,C152,LCE!$E$4:$E$40)+SUMIF(LI!$C$4:$C$55,C152,LI!$E$4:$E$55)+SUMIF(LAP!$C$4:$C$45,C152,LAP!$E$4:$E$45)+SUMIF(LGDM!$C$4:$C$15,C152,LGDM!$E$4:$E$15)+SUMIF(LAM!$C$5:$C$18,C152,LAM!$E$5:$E$18)+SUMIF(DEP!$C$4:$C$55,C152,DEP!$E$4:$E$55) -> 15
...

Sheet GRUPOS UNSIS
A1: LCB | F1: LM | K1: LO | P1: LE
A2: SEMESTRE | B2: GRUPOS | C2: GRUPO RECURSION | D2: TOTAL GRUPOS | F2: SEMESTRE | G2: GRUPOS | H2: GRUPO RECURSION | I2: TOTAL GRUPOS | K2: SEMESTRE | L2: GRUPOS | M2: GRUPO RECURSION | N2: TOTAL GRUPOS | P2: SEMESTRE | Q2: GRUPOS | R2: GRUPO RECURSION | S2: TOTAL GRUPOS
A3: 2 | B3: 2 | D3: =SUM(B3:C3) -> 2 | F3: 2 | G3: 3 | H3: 1 | I3: =SUM(G3:H3) -> 4 | K3: 2 | L3: 9 | N3: =SUM(L3:M3) -> 9 | P3: 2 | Q3: 9 | S3: =SUM(Q3:R3) -> 9
A4: 4 | B4: 1 | D4: =SUM(B4:C4) -> 1 | F4: 4 | G4: 3 | I4: =SUM(G4:H4) -> 3 | K4: 4 | L4: 4 | N4: =SUM(L4:M4) -> 4 | P4: 4 | Q4: 5 | R4: 1 | S4: =SUM(Q4:R4) -> 6
C5: TOTAL | D5: =SUM(D3:D4) -> 3 | E5: =D5 -> 3 | F5: 6 | G5: 3 | I5: =SUM(G5:H5) -> 3 | K5: 6 | L5: 4 | N5: =SUM(L5:M5) -> 4 | P5: 6 | Q5: 4 | S5: =SUM(Q5:R5) -> 4
F6: 8 | G6: 2 | I6: =SUM(G6:H6) -> 2 | K6: 8 | L6: 3 | N6: =SUM(L6:M6) -> 3 | P6: 8 | Q6: 3 | S6: =SUM(Q6:R6) -> 3
F7: 10 | G7: 3 | I7: =SUM(G7:H7) -> 3 | K7: 10 | L7: 3 | N7: =SUM(L7:M7) -> 3 | P7: 10 | Q7: 3 | S7: =SUM(Q7:R7) -> 3
F8: 12 | G8: 3 | I8: =SUM(G8:H8) -> 3 | M8: TOTAL | N8: =SUM(N3:N7) -> 23 | O8: =N8 -> 23 | R8: TOTAL | S8: =SUM(S3:S7) -> 25 | T8: =S8 -> 25
H9: TOTAL | I9: =SUM(I3:I8) -> 18 | J9: =I9 -> 18
A14: LN | F14: LCE | K14: LI | P14: LAP
A15: SEMESTRE | B15: GRUPOS | C15: GRUPO RECURSION | D15: TOTAL GRUPOS | F15: SEMESTRE | G15: GRUPOS | H15: GRUPO RECURSION | I15: TOTAL GRUPOS | K15: SEMESTRE | L15: GRUPOS | M15: GRUPO RECURSION | N15: TOTAL GRUPOS | P15: SEMESTRE | Q15: GRUPOS | R15: GRUPO RECURSION | S15: TOTAL GRUPOS
A16: 2 | B16: 2 | D16: =SUM(B16:C16) -> 2 | F16: 2 | G16: 2 | I16: =SUM(G16:H16) -> 2 | K16: 2 | L16: 2 | N16: =SUM(L16:M16) -> 2 | P16: 2 | Q16: 1 | S16: =SUM(Q16:R16) -> 1
A17: 4 | B17: 1 | D17: =SUM(B17:C17) -> 1 | F17: 4 | G17: 1 | I17: =SUM(G17:H17) -> 1 | K17: 4 | L17: 1 | N17: =SUM(L17:M17) -> 1 | P17: 4 | Q17: 1 | S17: =SUM(Q17:R17) -> 1
A18: 6 | B18: 1 | D18: =SUM(B18:C18) -> 1 | F18: 6 | G18: 1 | I18: =SUM(G18:H18) -> 1 | K18: 6 | L18: 1 | N18: =SUM(L18:M18) -> 1 | P18: 6 | Q18: 1 | S18: =SUM(Q18:R18) -> 1
A19: 8 | B19: 1 | D19: =SUM(B19:C19) -> 1 | F19: 8 | G19: 1 | I19: =SUM(G19:H19) -> 1 | K19: 8 | L19: 1 | M19: 1 | N19: =SUM(L19:M19) -> 2 | P19: 8 | Q19: 1 | S19: =SUM(Q19:R19) -> 1
A20: 10 | B20: 1 | D20: =SUM(B20:C20) -> 1 | F20: 10 | G20: 1 | I20: =SUM(G20:H20) -> 1 | K20: 10 | L20: 1 | N20: =SUM(L20:M20) -> 1 | P20: 10 | Q20: 1 | S20: =SUM(Q20:R20) -> 1
C21: TOTAL | D21: =SUM(D16:D20) -> 6 | E21: =D21 -> 6 | H21: TOTAL | I21: =SUM(I16:I20) -> 6 | J21: =I21 -> 6 | M21: TOTAL | N21: =SUM(N16:N20) -> 7 | O21: =N21 -> 7 | R21: TOTAL | S21: =SUM(S16:S20) -> 5 | T21: =S21 -> 5
A25: LAM | F25: MPEM | K25: MSP | P25: MGE
A26: SEMESTRE | B26: GRUPOS | C26: GRUPO RECURSION | D26: TOTAL GRUPOS | F26: SEMESTRE | G26: GRUPOS | H26: GRUPO RECURSION | I26: TOTAL GRUPOS | K26: SEMESTRE | L26: GRUPOS | M26: GRUPO RECURSION | N26: TOTAL GRUPOS | P26: SEMESTRE | Q26: GRUPOS | R26: GRUPO RECURSION | S26: TOTAL GRUPOS
A27: 6 | B27: 1 | D27: =SUM(B27:C27) -> 1 | F27: 2 | G27: 1 | H27: 1 | I27: =SUM(G27:H27) -> 2 | K27: 2 | L27: 1 | N27: =SUM(L27:M27) -> 1 | P27: 2 | Q27: 0 | S27: =SUM(Q27:R27) -> 0
A28: 8 | B28: 1 | D28: =SUM(B28:C28) -> 1 | F28: 4 | G28: 1 | I28: =SUM(G28:H28) -> 1 | K28: 4 | L28: 1 | N28: =SUM(L28:M28) -> 1 | P28: 4 | Q28: 1 | S28: =SUM(Q28:R28) -> 1
A29: 10 | B29: 1 | D29: =SUM(B29:C29) -> 1 | H29: TOTAL | I29: =SUM(I27:I28) -> 3 | J29: =I29 -> 3 | M29: TOTAL | N29: =SUM(N27:N28) -> 2 | O29: =N29 -> 2 | R29: TOTAL | S29: =SUM(S27:S28) -> 1 | T29: =S29 -> 1
C30: TOTAL | D30: =SUM(D27:D29) -> 3 | E30: =D30 -> 3
P32: DGE
P33: SEMESTRE | Q33: GRUPOS | R33: GRUPO RECURSION | S33: TOTAL GRUPOS
P34: 6 | Q34: 1 | S34: =SUM(Q34:R34) -> 1
P35: 8 | Q35: 1 | S35: =SUM(Q35:R35) -> 1
P36: 10 | Q36: 1 | S36: =SUM(Q36:R36) -> 1
R37: TOTAL | S37: =SUM(S34:S36) -> 3 | T37: =S37 -> 3
A38: TOTAL FINAL= | B38: =SUM(E38:T38) -> 105 | E38: =SUM(E5:E30) -> 12 | J38: =SUM(J9:J29) -> 27 | O38: =SUM(O8:O29) -> 32 | T38: =SUM(T8:T37) -> 34
B39: 3 POR RECURSION DE UNA MATERIA

Sheet usuario-profesor
A1: NOMBRE DEL PROFESOR | B1: NOMBRE DE USUARIO
A2: Mtra. Dulce Mercedes Cabrera Santiago | B2: dulce2020le
A3: M.E. José Alberto Ramírez Rodríguez | B3: jose2020le
A4: Dr. Samuel Sánchez Hernández | B4: samuel2020le
A5: Dra. Roxana Nayeli Guerrero Sotelo | B5: roxana2020le
A6: M.T.F. Laura Gabriela López Álvarez | B6: laura2020le
A7: Dr. Gerardo Roberto Aragón Gonzalez | B7: gerardo2020le
A8: L.E. Silvia Mercedes Coca | B8: silvia2020le
A9: L.E. Gisela Mayra Bustamante Ramos | B9: mayra2020le
A10: L.E. Amalia Hernández Blas | B10: amalia2020le
A11: M.C.E. Ignacio Grajales Alonso | B11: ignacio2020le
A12: Med. Enedina Balderas Ruíz | B12: enedina2020le
... A332: L.O. César Yazid Martínez Martínez | B332: cesary2026lo

Sheet AsigTotalPTC
A3: No | B3: Profesor(a) | C3: Tot gpos | D3: Tot alum | E3: Tot hrs sem | F3: Cargo UNSIS | G3: Comisión o Asignación del Consejo Académico | H3: Comisión de Vice-Rectoría Académica | I3: Comisión de Jefatura de Carrera/DEP | J3: Comisión de Dirección de Instituto | K3: Comisión de Promoción del Desarrollo | L3: Apoyo en Actividades Extra-Escolares | M3: Otra(s) Comisión(es) | N3: Producción Científica 2017 | O3: Producción Científica 2016 | P3: Colaboración en Convocatorias y Proyectos Institucionales 2016-2017
A4: Licenciatura en Odontología
A5: 1 | B5: Odónt. Mauricio González Osorio | C5: =#REF! -> #REF! | D5: =#REF! -> #REF! | E5: =#REF! -> #REF! | F5: Jefe(a) de Carrera | G5: Comisión de Becas | H5: --- | I5: --- | J5: --- | K5: --- | L5: Taller de Cine | P5: PE: Odontología
A6: 2 | B6: Mtro. Eric Beljour | C6: =#REF! -> #REF! | D6: =#REF! -> #REF! | E6: =#REF! -> #REF! | F6: --- | G6: --- | H6: --- | I6: --- | J6: --- | K6: --- | L6: --- | M6: Jornada de Odontologia
A7: 3 | B7: Méd. Diana Cristal Jiménez Mejía | C7: =#REF! -> #REF! | D7: =#REF! -> #REF! | E7: =#REF! -> #REF! | F7: --- | G7: Comisión de Ética | H7: --- | I7: --- | J7: --- | K7: --- | L7: --- | N7: 1 artículo
A8: 4 | B8: M.S.P. Pablo Cataneo Pérez | C8: =#REF! -> #REF! | D8: =#REF! -> #REF! | E8: =#REF! -> #REF! | F8: --- | G8: --- | H8: --- | I8: --- | J8: Coordinador(a) de CA | K8: --- | L8: ---
A9: 5 | B9: M.C. Horacio Duque Bautista | C9: =#REF! -> #REF! | D9: =#REF! -> #REF! | E9: =#REF! -> #REF! | F9: --- | G9: Comisión de Bioseguridad del área de Salud | H9: --- | I9: --- | J9: --- | K9: --- | L9: ---
A11: Licenciatura en Enfermería
A12: 1 | B12: M.A. Francisco Ordaz Zurita | C12: =#REF! -> #REF! | D12: =#REF! -> #REF! | E12: =#REF! -> #REF! | F12: --- | G12: --- | H12: --- | I12: --- | J12: Coordinador(a) de CA | K12: --- | L12: --- | M12: Recursos Humanos | N12: 1 artículo
A13: 2 | B13: Dr. Abisaí Martínez Sánchez | C13: =#REF! -> #REF! | D13: =#REF! -> #REF! | E13: =#REF! -> #REF! | F13: --- | G13: --- | H13: --- | I13: --- | J13: --- | K13: --- | L13: --- | O13: 4 articulos
A14: 3 | B14: M.D. Elizabeth Cortés Bohórquez | C14: =#REF! -> #REF! | D14: =#REF! -> #REF! | E14: =#REF! -> #REF! | F14: --- | G14: Comisión de Ética | H14: --- | I14: Comisión de Servicio Social | J14: --- | K14: --- | L14: --- | N14: 1 libro
A15: 4 | B15: M.C. Ericay Berenice Martínez Ramos | C15: =#REF! -> #REF! | D15: =#REF! -> #REF! | E15: =#REF! -> #REF! | F15: --- | G15: Comisión de Bioseguridad del área de Salud | H15: --- | I15: --- | J15: --- | K15: --- | L15: ---
A16: 5 | B16: M.R.N. Laura Isabel Hernández Arzola | C16: =#REF! -> #REF! | D16: =#REF! -> #REF! | E16: =#REF! -> #REF! | F16: Jefe(a) de Carrera | G16: --- | H16: --- | I16: --- | J16: --- | K16: --- | L16: --- | N16: 1 libro | O16: 1 artículo
